Workbook

Sheet Lisez-moi
A1: CAXE — Thèmes et chiffres des 4 agents
A2: Version 11 du 20 octobre 2026 : la version post-audit du 14 octobre, mise à jour d'après la banque de questions validée le 20 octobre.
A4: Ce qui a changé le 20 octobre
A5: Pourquoi | B5: La banque de questions des 4 agents a été validée le 20 octobre. Claude Code n'a pu y brancher que 385 questions sur 519 : les 134 autres portaient sur des données absentes du classeur ou marquées « Importées ». Cette version met le classeur à jour sur tout ce que la banque a changé, pas seulement ces 134 lignes.
A6: En chiffres | B6: 19 thèmes ajoutés, 103 données ajoutées, 31 données importées passées en demandées, 13 données qui ne sont plus posées (lues dans une autre réponse), 48 conditions d'affichage, 23 niveaux, 38 profils, 38 déclencheurs ajoutés (D28 à D65), le profil Location et les lexiques par métier.
A7: Où le voir | B7: Onglet « Modifications 20 oct. » : une ligne par changement, avec l'avant et l'après. Dans les autres onglets, le code est vert sur une ligne nouvelle et violet sur une ligne modifiée ; la dernière colonne dit ce qui a changé.
A8: À valider | B8: La nature de notation et l'impact des 19 thèmes nouveaux sont des propositions : la banque ne les dit pas. Leur liste est en tête de l'onglet « Modifications 20 oct. ».
A10: Provenance de ce fichier
A11: Source | B11: Les fichiers data/*.json du dépôt calixtecaxe-hue/Test (importés le 15 octobre depuis CAXE_Themes_Chiffres_4_agents_8.xlsx, la version post-audit), puis la page « Banque de questions CAXE » validée le 20 octobre.
A12: Contrôle | B12: Ce classeur se réimporte avec scripts/importer-classeur.py. Les colonnes « Location » et « Clé dans les questions » ne sont pas encore lues par ce script : Claude Code doit les brancher (voir l'onglet Modifications).
A13: Différences avec l'original | B13: La colonne « Chiffres à demander » de l'onglet Thèmes liste les codes demandés ou partagés de chaque thème ; l'onglet Synthèse est en formules.
A15: Utilisation avec le moteur
A16: Règle | B16: Le classeur reste l'outil d'écriture. On le modifie, puis on relance l'import : on ne modifie jamais les JSON à la main.
A17: Commandes | B17: python3 scripts/importer-classeur.py CAXE_Themes_Chiffres_4_agents.xlsx, puis npm run donnees:controle.
A18: À ne pas faire | B18: Renommer un onglet, déplacer une colonne ou insérer une ligne au-dessus des en-têtes : l'import lit les colonnes par position.
A20: Légende
A21: Marché | B21: Le chiffre du client comparé à une référence de marché sourcée. La moyenne du marché est orange, le vert est au-dessus.
A22: Pratique | B22: Une bonne pratique reconnue est-elle en place : absente, partielle ou en place.
A23: Cohérence | B23: Les réponses du client comparées entre elles.
A24: Contexte | B24: Non noté. Sert seulement à l'IA pour expliquer le diagnostic.
A25: Impact | B25: Chiffré (CA, trésorerie, contacts, marge ou heures) quand le thème est sur une vraie chaîne de calcul ; sinon Qualifié (Bloquant, Frein, Secondaire).
A26: Mode d'une donnée | B26: Demandée : posée au dirigeant. Partagée : posée une seule fois, par le premier agent souscrit qui en a besoin. Importée : lue dans un outil connecté. Calculée : déduite d'autres données. Autre agent : reprise d'un autre agent.
A27: Niveau | B27: Essentiel : audit initial. Approfondi : posé dans un second temps. Les données calculées n'ont pas de niveau.
A28: Condition d'affichage | B28: La question déclencheuse (D01 à D65, onglet Déclencheurs) dont dépend la donnée. Une case orange signale une donnée qui n'est pas posée à tout le monde. « D26 + D63 » : les deux conditions sont nécessaires.
A29: Profils | B29: RDV = rendez-vous · Commerce · E-commerce · Restaurant · Chantier = artisan ou chantier · B2B = cycle long · Abonnement · Location = hébergement et location de véhicules. Un ● signifie que la donnée est posée à ce profil.
A30: Couleur du code | B30: Vert : ligne nouvelle le 20 octobre. Violet : ligne modifiée le 20 octobre (le détail est dans la dernière colonne).
A31: Tailles (onglets RH) | B31: L'agent RH se règle sur la taille de l'entreprise : Seul · 2 à 5 · 6 et +.
A32: Nom du thème | B32: Colonne C des onglets de données : formule qui reprend le nom depuis l'onglet Thèmes.

Sheet Modifications 20 oct.
A1: Modifications du 20 octobre 2026
A2: Le classeur mis à jour d'après la banque de questions validée le 20 octobre. Trois parties : ce que tu dois valider, ce que Claude Code doit faire après l'import, puis chaque modification avec l'avant et l'après.
A4: 1. À valider par toi : nature de notation et impact des 19 thèmes nouveaux (propositions)
A5: Thème | B5: Nature | C5: Impact | D5: Bloc | E5: Pourquoi
A6: FIN-46 Rémunération du dirigeant | B6: Cohérence | C6: Qualifié | D6: Marges et rentabilité | E6: Ce que le dirigeant se verse, ses cotisations et ce qu'il souhaite se lisent entre eux.
A7: FIN-47 Cadre de l'activité | B7: Contexte | C7: — | D7: Pilotage | E7: Forme de l'entreprise : sert seulement à lire les chiffres (D31). Rien à noter.
A8: FIN-48 Relation avec la banque | B8: Pratique | C8: Qualifié | D8: Financement | E8: Bonne pratique : faire le point avec son banquier. Une seule question : le contrôle le signalera.
A9: RH-41 Projet d'équipe | B9: Contexte | C9: — | D9: S'entourer (dirigeant seul) | E9: Projet de se faire aider : décrit une intention. Rien à noter.
A10: RH-42 Tâches à confier | B10: Contexte | C10: — | D10: S'entourer (dirigeant seul) | E10: Tâches à confier : nourrit le plan d'action. Rien à noter.
A11: RH-43 Moyens pour une première aide | B11: Cohérence | C11: Qualifié | D11: S'entourer (dirigeant seul) | E11: Budget envisagé face aux demandes perdues et aux heures à confier : les réponses se lisent entre elles.
A12: RH-44 Freins | B12: Contexte | C12: — | D12: S'entourer (dirigeant seul) | E12: Ce qui retient de se faire aider : contexte pour l'IA.
A13: RH-45 Relais quand on est seul | B13: Pratique | C13: Qualifié | D13: S'entourer (dirigeant seul) | E13: Relais auprès des clients, informations notées, réseau : pratique absente, partielle ou en place.
A14: RH-46 Composition de l'équipe | B14: Contexte | C14: — | D14: Rôles et délégation | E14: Qui fait quoi dans l'équipe : décrit, ne se note pas. Partagée avec ACQ-21.01.
A15: RH-47 Planning de l'équipe | B15: Pratique | C15: Qualifié | D15: Charge et planification | E15: Qui fait le planning, délai de prévenance, changements de dernière minute : pratique.
A16: RH-48 Objectifs individuels | B16: Pratique | C16: Qualifié | D16: Management | E16: Objectifs écrits et revus, part variable : pratique.
... A24: COM-61 Funnel 7 · Relancer les intéressés | B24: Pratique | C24: Qualifié | D24: De la publication au contact | E24: Relance des personnes intéressées : pratique ; le taux de transformation vient de COM-61.02.
A26: 2. À faire par Claude Code après l'import
A27: 1. Importer | B27: python3 scripts/importer-classeur.py CAXE_Themes_Chiffres_4_agents_11.xlsx
A28: 2. Brancher deux colonnes | B28: Dans scripts/importer-classeur.py, AVANT l'import : lire la colonne « Clé dans les questions » de l'onglet Lexique (écrire « cle » quand elle diffère de cle_lexique(mot)). Sans elle, 8 mots ({demandes}, {unites_vendues}, {unites_a_louer}, {jours_ouverture}, {hors_location}, {devis_pluriel}, {ventes_realisees}, {exemples_travail}) perdent leur clé et les questions qui les emploient ne s'affichent plus. Avec cette lecture, data/lexique.json ressort identique. Ensuite : la colonne « Location » des onglets de données (8e profil) et les lexiques par métier.
A29: 3. Profil location | B29: Ajouter le profil location au code (constantes, routage des métiers d'hébergement et de location de véhicules, lexique) et une colonne Location dans les onglets Croisements.
A30: 4. Règles d'affichage | B30: data/regles-affichage.json : une règle pour chacune des 42 conditions qui n'en ont pas encore, plus le masquage « Au moins un salarié » (liste exacte : npm run donnees:controle après l'import ; ce sont ses 43 seules erreurs une fois les points 2, 5 et 6 faits), dont « D26 + D63 » (les deux nécessaires) et « Pas posée si les agents Acquisition et Comm sont faits : calculée » (FIN-05.02). D21 devient un choix à trois réponses (« Oui, au moins une fois par mois » = parcours amélioration). D03 passe à 17 canaux. Masquage nouveau « Au moins un salarié » (D02 différent de « seul ») pour les thèmes RH-41 à RH-45.
A31: 5. Catalogue des thèmes | B31: Fiches des 19 thèmes nouveaux dans data/catalogue-themes.json (python3 scripts/ecrire-catalogue-themes.py).
A32: 6. Limite de texte | B32: COM-44.04 (les 20 derniers avis, copiés-collés) accepte 8 000 caractères dans la banque ; src/lib/donnees/reponse-spec.ts plafonne un texte à 2 000. Monter ce plafond à 8 000, sinon le contrôle refuse data/banque/questions.json.
A33: 7. Questions en attente | B33: Relancer python3 scripts/importer-banque.py <page de la banque> --ecarter-inconnues : data/banque/en-attente.json disparaît, les 519 questions sont posables (vérifié le 20 octobre sur une copie du dépôt : 519 écrites, 0 manquante). Puis npm run donnees:controle.
A34: 8. Tests à mettre à jour | B34: Comptes écrits en dur dans tests/donnees.test.mts : thèmes par agent 23 / 48 / 49 / 61 (au lieu de 23 / 45 / 40 / 54), 11 thèmes de nature Contexte (au lieu de 4), 65 déclencheurs (au lieu de 27). Les autres tests en échec tombent avec les règles d'affichage (point 4) et le profil location (point 3 : ACQ-11.31 à 11.37 ne sont posées à aucun des 7 profils).
A35: 9. Calculs à écrire | B35: Annoncés par la banque, pas encore dans le classeur (rien n'est inventé ici) : ACQ-11.38 taux d'occupation, ACQ-11.39 prix moyen d'une unité vendue, ACQ-11.40 CA perdu par mois et un croisement location en miroir de XA34 (formules dans l'onglet Modifications de la banque, point D1) ; couverts par mois = ACQ-11.07 × ACQ-11.09 × 4,33 ; nombres par canal = ACQ-02.01 × ACQ-03.02 et ACQ-11.01 × ACQ-03.03, repris par ACQ-03.07, 03.08, 03.09, 03.10, 03.12, 06.09, 18.04, COM-12.01, COM-19.03 et COM-22.02 ; calculs du funnel Comm (COM-58.03, COM-61.03, COM-39.06) ; formules et croisements des 19 thèmes nouveaux.
A37: 3. Toutes les modifications (438 lignes)
A38: Catégorie | B38: Code | C38: Ce qui change | D38: Avant | E38: Après
A39: Thème ajouté | B39: COM-55 | C39: Thème nouveau (nature et impact proposés, à valider) | D39: — | E39: Funnel 3 · Visiter le profil : ce qu'il contient · bloc « De la publication au contact » · Pratique · impact Qualifié · masqué pour « Ne publie pas (parcours mise en place) »
A40: Thème ajouté | B40: COM-56 | C40: Thème nouveau (nature et impact proposés, à valider) | D40: — | E40: Démarrage · bloc « Présence et canaux » · Contexte · impact —
A41: Thème ajouté | B41: COM-57 | C41: Thème nouveau (nature et impact proposés, à valider) | D41: — | E41: Brief de création · bloc « Production » · Contexte · impact —
A42: Thème ajouté | B42: COM-58 | C42: Thème nouveau (nature et impact proposés, à valider) | D42: — | E42: Funnel 0 · Le chemin prévu · bloc « De la publication au contact » · Pratique · impact Qualifié
A43: Thème ajouté | B43: COM-59 | C43: Thème nouveau (nature et impact proposés, à valider) | D43: — | E43: Funnel 3 · Visiter le profil · bloc « De la publication au contact » · Cohérence · impact Chiffré (contacts) · masqué pour « Ne publie pas (parcours mise en place) »
A44: Thème ajouté | B44: COM-60 | C44: Thème nouveau (nature et impact proposés, à valider) | D44: — | E44: Funnel 5 · Arriver au bon endroit · bloc « De la publication au contact » · Pratique · impact Qualifié · masqué pour « Ne publie pas (parcours mise en place) »
A45: Thème ajouté | B45: COM-61 | C45: Thème nouveau (nature et impact proposés, à valider) | D45: — | E45: Funnel 7 · Relancer les intéressés · bloc « De la publication au contact » · Pratique · impact Qualifié · masqué pour « Ne publie pas (parcours mise en place) »
A46: Thème ajouté | B46: FIN-46 | C46: Thème nouveau (nature et impact proposés, à valider) | D46: — | E46: Rémunération du dirigeant · bloc « Marges et rentabilité » · Cohérence · impact Qualifié
A47: Thème ajouté | B47: FIN-47 | C47: Thème nouveau (nature et impact proposés, à valider) | D47: — | E47: Cadre de l'activité · bloc « Pilotage » · Contexte · impact —
A48: Thème ajouté | B48: FIN-48 | C48: Thème nouveau (nature et impact proposés, à valider) | D48: — | E48: Relation avec la banque · bloc « Financement » · Pratique · impact Qualifié
A49: Thème ajouté | B49: RH-41 | C49: Thème nouveau (nature et impact proposés, à valider) | D49: — | E49: Projet d'équipe · bloc « S'entourer (dirigeant seul) » · Contexte · impact — · masqué pour « Au moins un salarié »
... A476: Déclencheur | B476: D26 | C476: Déclencheur : effet | D476: Connecté : statistiques des 10 dernières publications lues automatiquement. Accès manuel : saisie des 3 meilleures et 3 moins bonnes. Non : estimations en tranches | E476: Oui : saisie des statistiques des 3 meilleures et 3 moins bonnes publications ; lecture automatique quand la connexion existera. Non : estimations.

Sheet Modifications 28 oct.
A1: Code | B1: Champ | C1: Avant | D1: Après | E1: Pourquoi
A2: ACQ-02.02 | B2: periode | C2: Si plus de 6 mois d'existence (sinon masquée) | D2: 3 mois, 6 mois plus tôt (masquée avant 9 mois d'existence) | E2: Comparée à la moyenne des 3 derniers mois (ACQ-02.01) : mêmes 3 mois de longueur, 6 mois plus tôt. Avant 9 mois, ces mois précèdent la création.
A3: ACQ-02.03 | B3: periode | C3: Si plus de 12 mois d'existence (sinon masquée) | D3: Mêmes 3 mois, un an plus tôt (masquée avant 15 mois d'existence) | E3: « Il y a un an, à la même période » ne disait pas quels mois : ce sont les mêmes 3 mois qu'ACQ-02.01, un an plus tôt. Avant 15 mois, ils précèdent la création.
A4: ACQ-11.02 | B4: periode | C4: Si plus de 12 mois d'existence (sinon masquée) | D4: Mêmes 3 mois, un an plus tôt (masquée avant 15 mois d'existence) | E4: Comme ACQ-02.03, pour les nouveaux clients (comparée à ACQ-11.01).
A5: ACQ-03.06 | B5: periode | C5: Période adaptée : depuis la création si moins de 12 mois | D5: 12 mois précédents (masquée avant 24 mois d'existence) | E5: Compare les 12 derniers mois aux 12 mois précédents : il faut 24 mois d'existence. « Période adaptée » posait la question à une entreprise de 13 mois.
A6: ACQ-06.07 | B6: periode | C6: — | D6: Période adaptée : depuis la création si moins de 3 mois | E6: Période déjà écrite dans la question (moyenne des 3 derniers mois) ; nécessaire pour la comparer à COM-13.06.
A7: ACQ-07.05 | B7: periode | C7: Si plus de 12 mois d'existence (sinon masquée) | D7: Il y a 12 mois (masquée avant 12 mois d'existence) | E7: Même masquage ; le mois comparé est maintenant précisé.
A8: ACQ-03.05 | B8: periode | C8: — | D8: Aujourd'hui | E8: Montant par mois actuel, comparé au budget d'il y a 12 mois (ACQ-07.05).
A9: ACQ-07.01 | B9: periode | C9: — | D9: Aujourd'hui | E9: Montant par mois actuel, comparé au budget d'il y a 12 mois (ACQ-07.05).
A10: ACQ-07.03 | B10: periode | C10: — | D10: Aujourd'hui | E10: Montant par mois actuel, comparé au budget d'il y a 12 mois (ACQ-07.05).
A11: ACQ-07.04 | B11: periode | C11: — | D11: Aujourd'hui | E11: Montant par mois actuel, comparé au budget d'il y a 12 mois (ACQ-07.05).
A12: ACQ-16.03 | B12: periode | C12: Période adaptée : depuis la création si moins de 12 mois | D12: 12 mois précédents (masquée avant 24 mois d'existence) | E12: « L'année d'avant » est comparée aux 12 derniers mois (ACQ-16.01) : il faut 24 mois. « Période adaptée » la posait dès la création.
... A55: FIN-37.06 | B55: entrees | C55: FIN-37.01, FIN-37.02, ACQ-23.01 | D55: FIN-37.01, FIN-37.02, ACQ-23.10 | E55: Entrées du calcul réécrit.
A56: ACQ-23.13 | B56: nouvelle donnée | D56: Changement de périmètre de l'activité sur les 24 derniers mois (ouverture ou fermeture d'un établissement, rachat ou vente, nouvelle activité ou arrêt) et mois du changement — partagée avec FIN-14.04 | E56: Une évolution d'une année sur l'autre n'a pas de sens si l'activité n'a pas le même périmètre : ouverture d'un second site, rachat, arrêt d'une activité.
A57: ACQ-23.12 | B57: nouvelle donnée | D57: Nombre de ventes sur les 12 mois précédents (pour comparer le montant moyen d'une vente d'une année sur l'autre) | E57: L'évolution du panier (ACQ-15.07) compare deux années ; le nombre de ventes de l'année précédente n'était demandé nulle part.
A58: FIN-07.17 | B58: nouvelle donnée | D58: Nombre de personnes dans l'entreprise il y a 12 mois, vous compris (même définition que le dossier d'entreprise) | E58: Une masse salariale qui augmente n'a pas le même sens si l'équipe a grandi : l'effectif d'il y a 12 mois n'était demandé nulle part (le dossier ne donne que l'effectif actuel).
A59: FIN-14.04 | B59: nouvelle donnée | D59: Changement de périmètre de l'activité sur les 24 derniers mois, et mois du changement | E59: Partage avec la Finance de la question sur le périmètre.
A60: FIN-14.03 | B60: nouvelle donnée | D60: CA des mêmes mois l'année précédente | E60: La Finance compare son chiffre d'affaires d'une année sur l'autre (XF07, FIN-04, FIN-07.15, FIN-37.06) sans que ce chiffre lui soit demandé.

Sheet Synthèse
A1: Synthèse par agent
A2: Tous les chiffres sont des formules sur les onglets Thèmes, données et croisements.
A4: Agent | B4: Thèmes | C4: Marché | D4: Pratique | E4: Cohérence | F4: Contexte | G4: Impact chiffré | H4: Impact qualifié | I4: Données | J4: Demandées | K4: Partagées | L4: Importées | M4: Calculées | N4: Autre agent | O4: Essentielles | P4: Approfondies | Q4: Croisements | R4: Scénarios
A5: Acquisition & CA | B5: =COUNTIF(Thèmes!$B:$B,$A5) | C5: =COUNTIFS(Thèmes!$B:$B,$A5,Thèmes!$E:$E,"Marché") | D5: =COUNTIFS(Thèmes!$B:$B,$A5,Thèmes!$E:$E,"Pratique") | E5: =COUNTIFS(Thèmes!$B:$B,$A5,Thèmes!$E:$E,"Cohérence") | F5: =COUNTIFS(Thèmes!$B:$B,$A5,Thèmes!$E:$E,"Contexte") | G5: =COUNTIFS(Thèmes!$B:$B,$A5,Thèmes!$F:$F,"Chiffré*") | H5: =COUNTIFS(Thèmes!$B:$B,$A5,Thèmes!$F:$F,"Qualifié") | I5: =COUNTA('Acquisition — données'!$A:$A)-1 | J5: =COUNTIF('Acquisition — données'!$G:$G,"Demandée") | K5: =COUNTIF('Acquisition — données'!$G:$G,"Partagée") | L5: =COUNTIF('Acquisition — données'!$G:$G,"Importée") | M5: =COUNTIF('Acquisition — données'!$G:$G,"Calculée") | N5: =COUNTIF('Acquisition — données'!$G:$G,"Autre agent") | O5: =COUNTIF('Acquisition — données'!$H:$H,"Essentiel") | P5: =COUNTIF('Acquisition — données'!$H:$H,"Approfondi") | Q5: =COUNTIF(Croisements!$B:$B,$A5) | R5: 0
A6: Finance & Rentabilité | B6: =COUNTIF(Thèmes!$B:$B,$A6) | C6: =COUNTIFS(Thèmes!$B:$B,$A6,Thèmes!$E:$E,"Marché") | D6: =COUNTIFS(Thèmes!$B:$B,$A6,Thèmes!$E:$E,"Pratique") | E6: =COUNTIFS(Thèmes!$B:$B,$A6,Thèmes!$E:$E,"Cohérence") | F6: =COUNTIFS(Thèmes!$B:$B,$A6,Thèmes!$E:$E,"Contexte") | G6: =COUNTIFS(Thèmes!$B:$B,$A6,Thèmes!$F:$F,"Chiffré*") | H6: =COUNTIFS(Thèmes!$B:$B,$A6,Thèmes!$F:$F,"Qualifié") | I6: =COUNTA('Finance — données'!$A:$A)-1 | J6: =COUNTIF('Finance — données'!$G:$G,"Demandée") | K6: =COUNTIF('Finance — données'!$G:$G,"Partagée") | L6: =COUNTIF('Finance — données'!$G:$G,"Importée") | M6: =COUNTIF('Finance — données'!$G:$G,"Calculée") | N6: =COUNTIF('Finance — données'!$G:$G,"Autre agent") | O6: =COUNTIF('Finance — données'!$H:$H,"Essentiel") | P6: =COUNTIF('Finance — données'!$H:$H,"Approfondi") | Q6: =COUNTIF(Croisements!$B:$B,$A6) | R6: =COUNTA(Scénarios!$A$5:$A$200)
A7: RH & Organisation | B7: =COUNTIF(Thèmes!$B:$B,$A7) | C7: =COUNTIFS(Thèmes!$B:$B,$A7,Thèmes!$E:$E,"Marché") | D7: =COUNTIFS(Thèmes!$B:$B,$A7,Thèmes!$E:$E,"Pratique") | E7: =COUNTIFS(Thèmes!$B:$B,$A7,Thèmes!$E:$E,"Cohérence") | F7: =COUNTIFS(Thèmes!$B:$B,$A7,Thèmes!$E:$E,"Contexte") | G7: =COUNTIFS(Thèmes!$B:$B,$A7,Thèmes!$F:$F,"Chiffré*") | H7: =COUNTIFS(Thèmes!$B:$B,$A7,Thèmes!$F:$F,"Qualifié") | I7: =COUNTA('RH — données'!$A:$A)-1 | J7: =COUNTIF('RH — données'!$G:$G,"Demandée") | K7: =COUNTIF('RH — données'!$G:$G,"Partagée") | L7: =COUNTIF('RH — données'!$G:$G,"Importée") | M7: =COUNTIF('RH — données'!$G:$G,"Calculée") | N7: =COUNTIF('RH — données'!$G:$G,"Autre agent") | O7: =COUNTIF('RH — données'!$H:$H,"Essentiel") | P7: =COUNTIF('RH — données'!$H:$H,"Approfondi") | Q7: =COUNTIF('Croisements RH'!$B:$B,$A7) | R7: 0
A8: Comm & Création | B8: =COUNTIF(Thèmes!$B:$B,$A8) | C8: =COUNTIFS(Thèmes!$B:$B,$A8,Thèmes!$E:$E,"Marché") | D8: =COUNTIFS(Thèmes!$B:$B,$A8,Thèmes!$E:$E,"Pratique") | E8: =COUNTIFS(Thèmes!$B:$B,$A8,Thèmes!$E:$E,"Cohérence") | F8: =COUNTIFS(Thèmes!$B:$B,$A8,Thèmes!$E:$E,"Contexte") | G8: =COUNTIFS(Thèmes!$B:$B,$A8,Thèmes!$F:$F,"Chiffré*") | H8: =COUNTIFS(Thèmes!$B:$B,$A8,Thèmes!$F:$F,"Qualifié") | I8: =COUNTA('Comm — données'!$A:$A)-1 | J8: =COUNTIF('Comm — données'!$G:$G,"Demandée") | K8: =COUNTIF('Comm — données'!$G:$G,"Partagée") | L8: =COUNTIF('Comm — données'!$G:$G,"Importée") | M8: =COUNTIF('Comm — données'!$G:$G,"Calculée") | N8: =COUNTIF('Comm — données'!$G:$G,"Autre agent") | O8: =COUNTIF('Comm — données'!$H:$H,"Essentiel") | P8: =COUNTIF('Comm — données'!$H:$H,"Approfondi") | Q8: =COUNTIF(Croisements!$B:$B,$A8) | R8: 0
A9: Total | B9: =SUM(B5:B8) | C9: =SUM(C5:C8) | D9: =SUM(D5:D8) | E9: =SUM(E5:E8) | F9: =SUM(F5:F8) | G9: =SUM(G5:G8) | H9: =SUM(H5:H8) | I9: =SUM(I5:I8) | ... R9: =SUM(R5:R8)
A11: Déclencheurs | B11: =COUNTA(Déclencheurs!$A$5:$A$200)
A12: Mots du lexique | B12: =COUNTA(Lexique!$A$5:$A$200)
A13: Problèmes du diagnostic Comm | B13: =COUNTIF('Diagnostic Comm'!$A$5:$A$200,"DC*")
A14: Les données partagées sont posées une seule fois, par le premier agent souscrit qui en a besoin : la colonne « Partagées » compte ces lignes une fois chacune.

Sheet Thèmes
A1: Code | B1: Agent | C1: Bloc / étape | D1: Thème | E1: Nature de notation | F1: Impact sur l'objectif | G1: Chiffre nécessaire | H1: Chiffres demandés (codes, d'après les onglets de données) | I1: Déjà connu ailleurs | J1: Comment le volume change la méthode | K1: Si le chiffre est inconnu | L1: Masqué pour | M1: Changement du 20 oct.
A2: ACQ-01 | B2: Acquisition & CA | C2: Attirer | D2: Cible | E2: Cohérence | F2: Qualifié | G2: Oui | H2: ACQ-01.01, ACQ-01.02, ACQ-01.03, ACQ-01.04, ACQ-01.05, ACQ-01.06, ACQ-01.07, ACQ-01.08, ACQ-01.09, ACQ-01.10 | I2: Métier et zone (inscription) | J2: 70 % du CA vient d'un type de client non ciblé → recentrer la cible sur lui. CA éparpillé sur 5 types → choisir un segment prioritaire. | K2: Classer ses types de clients du plus au moins rentable, sans chiffre. | L2: —
A3: ACQ-02 | B3: Acquisition & CA | C3: Attirer | D3: Volume de contacts | E3: Marché | F3: Chiffré (CA) | G3: Oui | H3: ACQ-02.01, ACQ-02.02, ACQ-02.03, ACQ-02.04, ACQ-02.05 | I3: Partagé avec COM-13 (posé une seule fois) | J3: Peu de contacts mais bonne transformation → travailler l'apport de contacts. Beaucoup de contacts mal transformés → travailler la conversion d'abord. | K3: Première action : compter les demandes pendant 4 semaines. | L3: —
A4: ACQ-03 | B4: Acquisition & CA | C4: Attirer | D4: Canaux | E4: Cohérence | F4: Chiffré (CA) | G4: Oui | H4: ACQ-03.01, ACQ-03.02, ACQ-03.03, ACQ-03.04, ACQ-03.05, ACQ-03.06 | I4: Partagé avec COM-12 (posé une seule fois) | J4: Un canal = 80 % des contacts → ouvrir un 2e canal. 5 canaux à 5 contacts chacun → concentrer l'effort sur le meilleur. | K4: Classer ses canaux du plus au moins efficace. | L4: —
A5: ACQ-04 | B5: Acquisition & CA | C5: Attirer | D5: Prospection active | E5: Pratique | F5: Chiffré (CA) | G5: Oui | H5: ACQ-04.01, ACQ-04.02, ACQ-04.03, ACQ-04.04, ACQ-04.05, ACQ-04.06 | I5: — | J5: Aucune action → installer une routine minimale. 50 appels pour 0 rendez-vous → revoir le message, pas le volume. | K5: Noter ses actions de prospection pendant 2 semaines. | L5: —
A6: ACQ-05 | B6: Acquisition & CA | C6: Attirer | D6: Partenaires | E6: Pratique | F6: Chiffré (CA) | G6: Oui | H6: ACQ-05.01, ACQ-05.02, ACQ-05.03, ACQ-05.04 | I6: — | J6: Aucun partenaire → identifier 3 prescripteurs naturels du métier. 10 partenaires dont un seul apporte → l'entretenir et réactiver les autres. | K6: Citer les partenaires qui ont apporté au moins un client cette année. | L6: —
A7: ACQ-06 | B7: Acquisition & CA | C7: Attirer | D7: Présence en ligne | E7: Pratique | F7: Qualifié | G7: Oui | H7: ACQ-06.01, ACQ-06.04, ACQ-06.06, ACQ-06.07, ACQ-06.08, ACQ-06.12, ACQ-06.13 | I7: Partagé avec COM-13, COM-14 et COM-44 (posé une seule fois) ; lu sur la fiche Google si connectée | J7: 5 avis → campagne de sollicitation. 200 avis à 4,8 → maintenir, le levier est ailleurs. Analyse du contenu → renvoi Comm. | K7: Lu directement sur la fiche Google. | L7: —
A8: ACQ-07 | B8: Acquisition & CA | C8: Attirer | D8: Budget et coût d'acquisition | E8: Cohérence | F8: Chiffré (CA) | G8: Oui | H8: ACQ-07.01, ACQ-07.02, ACQ-07.03, ACQ-07.04, ACQ-07.05, ACQ-07.15 | I8: Partagé avec FIN-05 et COM-32 (posé une seule fois) ; CA mensuel (inscription) ; clients signés (ACQ-11) | J8: Coût d'un client supérieur à son panier → couper le canal le plus cher. Budget nul et peu de clients → tester un petit budget sur le meilleur canal. | K8: Additionner les dépenses marketing des 3 derniers relevés bancaires. | L8: —
A9: ACQ-08 | B9: Acquisition & CA | C9: Convertir | D9: Réactivité | E9: Marché | F9: Chiffré (CA) | G9: Oui | H9: ACQ-08.01, ACQ-08.02, ACQ-08.03, ACQ-08.04, ACQ-08.05 | I9: Demandes par mois (ACQ-02) | J9: 5 demandes par mois → réponse personnelle dans l'heure. 100 par mois → accusé de réception automatique et créneau de rappel. | K9: Noter l'heure de réception et de réponse des 10 prochaines demandes. | L9: —
A10: ACQ-09 | B10: Acquisition & CA | C10: Convertir | D10: Rendez-vous | E10: Marché | F10: Chiffré (CA) | G10: Oui | H10: ACQ-09.01, ACQ-09.02, ACQ-09.05, ACQ-09.06, ACQ-09.07 | I10: Demandes par mois (ACQ-02) | J10: Absences fréquentes sur gros volume → rappel automatique la veille. Petit volume → appel de confirmation personnel. | K10: Compter les rendez-vous du mois dernier dans l'agenda. | L10: Métiers sans rendez-vous
A11: ACQ-10 | B11: Acquisition & CA | C11: Convertir | D11: Devis et relances | E11: Marché | F11: Chiffré (CA) | G11: Oui | H11: ACQ-10.01, ACQ-10.03, ACQ-10.05, ACQ-10.06, ACQ-10.07, ACQ-10.08, ACQ-10.09, ACQ-10.10, ACQ-10.11 | I11: — | J11: 5 devis par mois → relance à la main sous 3 jours. 150 par mois → séquence de relance automatique. | K11: Compter les devis du dernier mois dans le logiciel ou la boîte mail. | L11: Métiers sans devis
A12: ACQ-11 | B12: Acquisition & CA | C12: Convertir | D12: Transformation | E12: Marché | F12: Chiffré (CA) | G12: Oui | H12: ACQ-11.01, ACQ-11.02, ACQ-11.03, ACQ-11.04, ACQ-11.05, ACQ-11.07, ACQ-11.08, ACQ-11.09, ACQ-11.10, ACQ-11.11, ACQ-11.12, ACQ-11.13, ACQ-11.15, ACQ-11.16, ACQ-11.17, ACQ-11.31, ACQ-11.32, ACQ-11.33, ACQ-11.34, ACQ-11.35, ACQ-11.36, ACQ-11.37, ACQ-11.38, ACQ-11.39 | I12: Partagé avec FIN-06 (posé une seule fois) ; Rendez-vous (ACQ-09) | J12: Peu de rendez-vous mal transformés → mieux préparer chaque rendez-vous. Beaucoup de rendez-vous mal transformés → mieux qualifier avant le rendez-vous. | K12: Compter les clients signés le mois dernier. | L12: —
A13: ACQ-12 | B13: Acquisition & CA | C13: Convertir | D13: Durée du cycle de vente | E13: Marché | F13: Chiffré (CA) | G13: Oui | H13: ACQ-12.01, ACQ-12.02, ACQ-12.03, ACQ-12.04 | I13: — | J13: Cycle long sur peu de dossiers → suivi individuel de chaque dossier. Cycle long sur gros volume → étapes et relances standardisées. | K13: Prendre les 5 dernières ventes et noter leurs deux dates. | L13: Vente immédiate (commerce)
... A24: ACQ-23 | B24: Acquisition & CA | C24: Piloter | D24: Saisonnalité | E24: Cohérence | F24: Chiffré (CA) | G24: Oui | H24: ACQ-23.01, ACQ-23.02, ACQ-23.03, ACQ-23.04, ACQ-23.12, ACQ-23.13 | I24: Partagé avec FIN-14 et RH-11 (posé une seule fois) | J24: Écart faible → pas d'action. Creux de 50 % → lancer la prospection 2 mois avant le creux. | K24: Citer les mois forts et faibles, sans chiffre. | L24: —
A25: ACQ-24 | B25: Acquisition & CA | C25: Piloter | D25: Objectif et moyens | E25: Contexte | F25: — | G25: Non | H25: ACQ-24.02 | I25: — | J25: — | K25: — | L25: — | M25: Nouveau : nature, impact et étape proposés, à valider
A26: ACQ-25 | B26: Acquisition & CA | C26: Votre métier | D26: Métier · Transport de personnes et coursiers | E26: Contexte | F26: — | G26: Non | H26: ACQ-25.01, ACQ-25.02, ACQ-25.03, ACQ-25.04 | I26: — | J26: — | K26: — | L26: — | M26: Nouveau : module métier ; nature, impact et étape proposés, à valider
A27: ACQ-27 | B27: Acquisition & CA | C27: Votre métier | D27: Métier · Négoce | E27: Contexte | F27: — | G27: Non | H27: ACQ-27.01, ACQ-27.02, ACQ-27.03, ACQ-27.04 | I27: — | J27: — | K27: — | L27: — | M27: Nouveau : module métier ; nature, impact et étape proposés, à valider
A28: ACQ-28 | B28: Acquisition & CA | C28: Votre métier | D28: Métier · Vente de véhicules et de logements | E28: Contexte | F28: — | G28: Non | H28: ACQ-28.01, ACQ-28.02, ACQ-28.03, ACQ-28.04 | I28: — | J28: — | K28: — | L28: — | M28: Nouveau : module métier ; nature, impact et étape proposés, à valider
A29: ACQ-29 | B29: Acquisition & CA | C29: Votre métier | D29: Métier · Immobilier | E29: Contexte | F29: — | G29: Non | H29: ACQ-29.01, ACQ-29.02, ACQ-29.03, ACQ-29.04 | I29: — | J29: — | K29: — | L29: — | M29: Nouveau : module métier ; nature, impact et étape proposés, à valider
A30: ACQ-30 | B30: Acquisition & CA | C30: Piloter | D30: Contexte | E30: Contexte | F30: — | G30: Non | H30: ACQ-30.01 | I30: — | J30: — | K30: — | L30: — | M30: Nouveau : nature, impact et étape proposés, à valider
A31: FIN-01 | B31: Finance & Rentabilité | C31: Marges et rentabilité | D31: Marge par offre | E31: Cohérence | F31: Chiffré (marge) | G31: Oui | H31: FIN-01.01, FIN-01.02, FIN-01.03 | I31: Partagé avec ACQ-13 (posé une seule fois) | J31: L'offre la moins rentable fait 50 % du CA → revoir son prix. Elle fait 5 % du CA → envisager de l'arrêter. | K31: Classer ses offres de la plus à la moins rentable, sans chiffre. | L31: —
A32: FIN-02 | B32: Finance & Rentabilité | C32: Marges et rentabilité | D32: Marge par client | E32: Cohérence | F32: Chiffré (marge) | G32: Oui | H32: FIN-02.01 | I32: Répartition du CA (ACQ-16) | J32: 1 client non rentable sur 50 → revoir ses conditions. 30 % des clients non rentables → revoir la grille de prix. | K32: Citer les clients qui prennent le plus de temps pour le moins de CA. | L32: —
A33: FIN-03 | B33: Finance & Rentabilité | C33: Marges et rentabilité | D33: Coût de revient | E33: Pratique | F33: Qualifié | G33: Calculé | H33: FIN-03.01 | I33: — | J33: Coût inconnu sur l'offre phare → le calculer sur elle seule d'abord. Inconnu sur 20 offres → méthode simple par familles. | K33: Première action : chiffrer une prestation type de bout en bout. | L33: —
A34: FIN-04 | B34: Finance & Rentabilité | C34: Marges et rentabilité | D34: Érosion des marges | E34: Cohérence | F34: Chiffré (marge) | G34: Calculé | H34: FIN-04.01 | I34: Prix (ACQ-13) — partagé, posé une seule fois | J34: Coûts +8 % et prix inchangés → répercussion urgente. Écart d'un point → ajustement à la prochaine révision annuelle. | K34: Comparer les 2 dernières factures du principal fournisseur. | L34: —
A35: FIN-05 | B35: Finance & Rentabilité | C35: Marges et rentabilité | D35: Seuil de rentabilité | E35: Cohérence | F35: Chiffré (marge) | G35: Oui | H35: FIN-05.01, FIN-05.02, FIN-05.03, FIN-05.04, FIN-05.05, FIN-05.06, FIN-05.07 | I35: Partagé avec ACQ-07, ACQ-17 et COM-32 (posé une seule fois) ; CA mensuel (inscription) | J35: CA à 105 % du seuil → sécuriser les charges fixes en priorité. À 150 % → marge de manœuvre pour investir. | K35: Additionner les charges fixes du dernier relevé bancaire. | L35: —
A36: FIN-06 | B36: Finance & Rentabilité | C36: Structure de coûts | D36: Charges fixes et variables | E36: Cohérence | F36: Qualifié | G36: Oui | H36: FIN-06.01, FIN-06.02, FIN-06.03, FIN-06.04 | I36: Partagé avec ACQ-11 et ACQ-21 (posé une seule fois) ; Charges fixes (FIN-05) | J36: 70 % de charges fixes avec une activité saisonnière → transformer des fixes en variables. 30 % → pas prioritaire. | K36: Séparer les dépenses du dernier mois en « tous les mois » et « selon l'activité ». | L36: —
A37: FIN-07 | B37: Finance & Rentabilité | C37: Structure de coûts | D37: Coût de l'équipe | E37: Marché | F37: Chiffré (marge) | G37: Oui | H37: FIN-07.01, FIN-07.02, FIN-07.03, FIN-07.04, FIN-07.05, FIN-07.06, FIN-07.17 | I37: Partagé avec ACQ-13, ACQ-21 et RH-06 (posé une seule fois) ; CA mensuel et effectif (inscription) | J37: Poids élevé et carnet plein → hausse de prix. Poids élevé et carnet vide → renvoi RH (charge) et Acquisition (volume). | K37: Total des salaires et charges du dernier mois. | L37: Seul
A38: FIN-08 | B38: Finance & Rentabilité | C38: Structure de coûts | D38: Achats et sous-traitance | E38: Cohérence | F38: Chiffré (marge) | G38: Oui | H38: FIN-08.01, FIN-08.02, FIN-08.03, FIN-08.04, FIN-08.05, FIN-08.06 | I38: — | J38: Un fournisseur = 60 % des achats → renégocier ou mettre en concurrence. 30 petits fournisseurs → regrouper les achats. | K38: Total des factures fournisseurs du dernier mois. | L38: Sans achats (services purs)
A39: FIN-09 | B39: Finance & Rentabilité | C39: Structure de coûts | D39: Dépenses récurrentes | E39: Pratique | F39: Chiffré (marge) | G39: Oui | H39: FIN-09.01, FIN-09.02, FIN-09.03, FIN-09.10 | I39: — | J39: 5 abonnements → revue en 30 minutes. 40 → inventaire complet sur les relevés. | K39: Lister les prélèvements du dernier relevé bancaire. | L39: —
A40: FIN-10 | B40: Finance & Rentabilité | C40: Structure de coûts | D40: Coût des erreurs | E40: Pratique | F40: Chiffré (marge) | G40: Oui | H40: FIN-10.01, FIN-10.02, FIN-10.03, FIN-10.04, FIN-10.05 | I40: Nombre de reprises partagé avec RH-16 (posé une seule fois) ; pertes de marchandises comptées en FIN-40 | J40: 2 reprises par mois → traiter au cas par cas. 20 → chercher la cause commune (renvoi RH). | K40: Noter les reprises et gestes du mois en cours. | L40: —
A41: FIN-11 | B41: Finance & Rentabilité | C41: Trésorerie | D41: Trésorerie disponible | E41: Pratique | F41: Chiffré (trésorerie) | G41: Oui | H41: FIN-11.01, FIN-11.02, FIN-11.03 | I41: Charges fixes (FIN-05) → nombre de mois couverts calculé | J41: Moins d'un mois couvert → plan de trésorerie semaine par semaine. Plus de 6 mois → réfléchir à l'usage de l'excédent. | K41: Lu sur le compte bancaire. | L41: —
A42: FIN-12 | B42: Finance & Rentabilité | C42: Trésorerie | D42: Flux | E42: Cohérence | F42: Qualifié | G42: Oui | H42: FIN-12.01 | I42: — | J42: Un mois négatif par an → l'anticiper. Un mois sur deux → problème de fond (marges ou délais). | K42: Lu sur les 3 derniers relevés. | L42: —
... A75: FIN-45 | B75: Finance & Rentabilité | C75: Stock (si l'entreprise en a) | D75: Suivi du stock | E75: Pratique | F75: Qualifié | G75: Oui | H75: FIN-45.01, FIN-45.02, FIN-45.03 | I75: — | J75: 50 références → inventaire tournant chaque mois, à la main. 2 000 → logiciel de stock relié à la caisse. | K75: — | L75: Sans stock
A76: FIN-46 | B76: Finance & Rentabilité | C76: Marges et rentabilité | D76: Rémunération du dirigeant | E76: Cohérence | F76: Qualifié | G76: Oui | H76: FIN-46.01, FIN-46.02, FIN-46.03 | I76: — | J76: — | K76: — | L76: — | M76: Nouveau
A77: FIN-47 | B77: Finance & Rentabilité | C77: Pilotage | D77: Cadre de l'activité | E77: Contexte | F77: — | G77: Non | H77: FIN-47.01, FIN-47.02 | I77: — | J77: — | K77: — | L77: — | M77: Nouveau
A78: FIN-48 | B78: Finance & Rentabilité | C78: Financement | D78: Relation avec la banque | E78: Pratique | F78: Qualifié | G78: Non | H78: FIN-48.01 | I78: — | J78: — | K78: — | L78: — | M78: Nouveau
A79: RH-01 | B79: RH & Organisation | C79: Rôles et délégation | D79: Clarté des missions | E79: Pratique | F79: Qualifié | G79: Oui | H79: RH-01.01, RH-01.02 | I79: Effectif (inscription) | J79: 3 personnes → une phrase de mission par personne. 20 → une fiche par fonction. | K79: — | L79: Seul
A80: RH-02 | B80: RH & Organisation | C80: Rôles et délégation | D80: Répartition des responsabilités | E80: Pratique | F80: Qualifié | G80: Oui | H80: RH-02.01, RH-02.02 | I80: Effectif (inscription) | J80: 2 personnes → une liste « qui décide quoi ». 15 → un tableau par domaine. | K80: — | L80: —
A81: RH-03 | B81: RH & Organisation | C81: Rôles et délégation | D81: Autonomie | E81: Cohérence | F81: Qualifié | G81: Oui | H81: RH-03.01, RH-03.02, RH-03.03, RH-03.04, RH-03.05 | I81: Effectif (inscription) | J81: 5 par jour → règles écrites pour les cas fréquents. 40 par jour → déléguer un niveau de décision. | K81: Compter les sollicitations sur une journée type. | L81: Seul
A82: RH-04 | B82: RH & Organisation | C82: Rôles et délégation | D82: Délégation réelle | E82: Cohérence | F82: Qualifié | G82: Oui | H82: RH-04.01, RH-04.02, RH-04.03, RH-04.04, RH-04.05 | I82: — | J82: Peu de tâches confiées → commencer par une tâche récurrente simple. Beaucoup confiées mais reprises → le problème est le suivi, pas la délégation. | K82: — | L82: Seul
A83: RH-05 | B83: RH & Organisation | C83: Rôles et délégation | D83: Temps du dirigeant | E83: Cohérence | F83: Chiffré (heures) | G83: Oui | H83: RH-05.01, RH-05.02, RH-05.03, RH-05.04, RH-05.05, RH-05.10, RH-05.11 | I83: Partagé avec ACQ-21 (posé une seule fois) | J83: 5 h déléguables → réorganiser les tâches. 20 h → envisager un renfort ou un prestataire (coût → Finance). | K83: Noter son temps pendant une semaine type. | L83: —
A84: RH-06 | B84: RH & Organisation | C84: Charge et planification | D84: Volume de travail | E84: Cohérence | F84: Qualifié | G84: Oui | H84: RH-06.01, RH-06.02, RH-06.03, RH-06.04, RH-06.05, RH-06.06, RH-06.07 | I84: Partagé avec ACQ-21 et FIN-07 (posé une seule fois) ; Effectif (inscription) | J84: Surcharge ponctuelle → mieux planifier. Surcharge permanente → bloquant pour l'objectif. | K84: Estimer une semaine type, en fourchette. | L84: Seul
A85: RH-07 | B85: RH & Organisation | C85: Charge et planification | D85: Capacité disponible | E85: Cohérence | F85: Chiffré (heures) | G85: Oui | H85: RH-07.01, RH-07.02 | I85: Partagé avec ACQ-21 (posé une seule fois) ; Objectif (inscription) ; capacité commerciale (ACQ-22) | J85: Objectif +15 % et aucune heure disponible → bloquant. 20 % de marge → l'objectif est absorbable sans renfort. | K85: Estimer en fourchette. | L85: —
A86: RH-08 | B86: RH & Organisation | C86: Charge et planification | D86: Répartition de la charge | E86: Cohérence | F86: Qualifié | G86: Oui | H86: RH-08.01, RH-08.02, RH-08.03, RH-08.04, RH-08.05, RH-08.06 | I86: Moyenne (RH-06) | J86: Une personne à 55 h quand les autres sont à 35 h → rééquilibrer. Charge homogène → pas d'action. | K86: — | L86: Seul
A87: RH-09 | B87: RH & Organisation | C87: Charge et planification | D87: Urgences | E87: Cohérence | F87: Chiffré (heures) | G87: Oui | H87: RH-09.01, RH-09.02, RH-09.03, RH-09.04 | I87: — | J87: Urgences surtout imprévisibles → organiser une permanence. Surtout anticipables → planifier et écrire les procédures des activités en cause. | K87: Tranches proposées, « je ne sais pas » accepté. | L87: —
A88: RH-10 | B88: RH & Organisation | C88: Charge et planification | D88: Interruptions | E88: Cohérence | F88: Chiffré (heures) | G88: Oui | H88: RH-10.01, RH-10.02, RH-10.03, RH-10.04, RH-10.05, RH-10.06 | I88: — | J88: 3 interruptions par jour → pas d'action. 15 par jour, surtout des validations → règles de décision écrites et créneaux d'échange regroupés. | K88: Tranches proposées, « je ne sais pas » accepté. | L88: —
A89: RH-11 | B89: RH & Organisation | C89: Charge et planification | D89: Pics et creux | E89: Cohérence | F89: Qualifié | G89: Calculé | H89: RH-11.01, RH-11.02 | I89: Mois forts et faibles (ACQ-23) — partagé, posé une seule fois | J89: Pic d'un mois → heures supplémentaires planifiées. Pic de 4 mois → renfort saisonnier anticipé. | K89: — | L89: —
A90: RH-12 | B90: RH & Organisation | C90: Processus et outils | D90: Méthodes reproductibles | E90: Pratique | F90: Qualifié | G90: Oui | H90: RH-12.01 | I90: — | J90: 3 tâches clés → les écrire soi-même en une heure. 30 → commencer par les 3 plus fréquentes. | K90: — | L90: —
... A118: RH-40 | B118: RH & Organisation | C118: Continuité | D118: Indicateurs de suivi | E118: Pratique | F118: Qualifié | G118: Calculé | H118: RH-40.01 | I118: — | J118: — | K118: — | L118: —
A119: RH-41 | B119: RH & Organisation | C119: S'entourer (dirigeant seul) | D119: Projet d'équipe | E119: Contexte | F119: — | G119: Non | H119: RH-41.01, RH-41.02, RH-41.03 | I119: — | J119: — | K119: — | L119: Au moins un salarié | M119: Nouveau
A120: RH-42 | B120: RH & Organisation | C120: S'entourer (dirigeant seul) | D120: Tâches à confier | E120: Contexte | F120: — | G120: Non | H120: RH-42.01, RH-42.02 | I120: — | J120: — | K120: — | L120: Au moins un salarié | M120: Nouveau
A121: RH-43 | B121: RH & Organisation | C121: S'entourer (dirigeant seul) | D121: Moyens pour une première aide | E121: Cohérence | F121: Qualifié | G121: Oui | H121: RH-43.01, RH-43.02, RH-43.03 | I121: Demandes perdues partagées avec ACQ-22 (posées une seule fois) | J121: — | K121: — | L121: Au moins un salarié | M121: Nouveau
A122: RH-44 | B122: RH & Organisation | C122: S'entourer (dirigeant seul) | D122: Freins | E122: Contexte | F122: — | G122: Non | H122: RH-44.01, RH-44.02, RH-44.03 | I122: — | J122: — | K122: — | L122: Au moins un salarié | M122: Nouveau
A123: RH-45 | B123: RH & Organisation | C123: S'entourer (dirigeant seul) | D123: Relais quand on est seul | E123: Pratique | F123: Qualifié | G123: Non | H123: RH-45.01, RH-45.02, RH-45.03 | I123: — | J123: — | K123: — | L123: Au moins un salarié | M123: Nouveau
A124: RH-46 | B124: RH & Organisation | C124: Rôles et délégation | D124: Composition de l'équipe | E124: Contexte | F124: — | G124: Non | H124: RH-46.01, RH-46.02 | I124: Partagé avec ACQ-21 (posé une seule fois) | J124: — | K124: — | L124: Seul | M124: Nouveau
A125: RH-47 | B125: RH & Organisation | C125: Charge et planification | D125: Planning de l'équipe | E125: Pratique | F125: Qualifié | G125: Non | H125: RH-47.01, RH-47.02, RH-47.03 | I125: — | J125: — | K125: — | L125: Seul | M125: Nouveau
A126: RH-48 | B126: RH & Organisation | C126: Management | D126: Objectifs individuels | E126: Pratique | F126: Qualifié | G126: Non | H126: RH-48.01, RH-48.02 | I126: — | J126: — | K126: — | L126: Seul | M126: Nouveau
A127: RH-49 | B127: RH & Organisation | C127: Management | D127: Encadrement | E127: Pratique | F127: Qualifié | G127: Non | H127: RH-49.01, RH-49.02 | I127: — | J127: — | K127: — | L127: Moins de 6 personnes | M127: Nouveau
A128: COM-01 | B128: Comm & Création | C128: Identité et offre | D128: Positionnement | E128: Pratique | F128: Qualifié | G128: Non | H128: COM-01.01 | I128: — | J128: — | K128: — | L128: —
A129: COM-02 | B129: Comm & Création | C129: Identité et offre | D129: Cible | E129: Cohérence | F129: Qualifié | G129: Non | H129: COM-02.01 | I129: Cible (ACQ-01) | J129: Cible déclarée différente des clients qui rapportent → aligner la communication sur les clients réels. | K129: — | L129: —
A130: COM-03 | B130: Comm & Création | C130: Identité et offre | D130: Promesse | E130: Pratique | F130: Qualifié | G130: Non | H130: COM-03.01 | I130: — | J130: — | K130: — | L130: —
A131: COM-04 | B131: Comm & Création | C131: Identité et offre | D131: Force de l'offre | E131: Pratique | F131: Qualifié | G131: Non | H131: COM-04.01 | I131: — | J131: — | K131: — | L131: —
A132: COM-05 | B132: Comm & Création | C132: Identité et offre | D132: Garantie | E132: Pratique | F132: Qualifié | G132: Non | H132: COM-05.01, COM-05.02 | I132: — | J132: — | K132: — | L132: —
A133: COM-06 | B133: Comm & Création | C133: Identité et offre | D133: Ton | E133: Pratique | F133: Qualifié | G133: Non | H133: — | I133: — | J133: — | K133: — | L133: —
A134: COM-07 | B134: Comm & Création | C134: Identité et offre | D134: Cohérence de marque | E134: Pratique | F134: Qualifié | G134: Non | H134: COM-07.01 | I134: — | J134: — | K134: — | L134: —
A135: COM-08 | B135: Comm & Création | C135: Identité et offre | D135: Réassurance | E135: Pratique | F135: Qualifié | G135: Non | H135: COM-08.01 | I135: Avis (COM-44) ; ancienneté (inscription) | J135: — | K135: — | L135: —
A136: COM-09 | B136: Comm & Création | C136: Identité et offre | D136: Preuve et expertise | E136: Pratique | F136: Qualifié | G136: Oui | H136: COM-09.01, COM-09.02, COM-09.03, COM-09.08 | I136: — | J136: Aucun cas → en collecter 3. 50 réalisations → sélectionner les 5 meilleures. | K136: — | L136: —
A137: COM-10 | B137: Comm & Création | C137: Présence et canaux | D137: Réseaux actifs | E137: Pratique | F137: Qualifié | G137: Oui | H137: COM-10.01, COM-10.03, COM-10.04, COM-10.05, COM-10.07, COM-10.08 | I137: — | J137: 3 réseaux à 1 publication par mois → n'en garder qu'un. 1 réseau bien tenu → l'amplifier avant d'en ouvrir un autre. | K137: Lu sur les profils. | L137: Ne publie pas (parcours mise en place)
A138: COM-11 | B138: Comm & Création | C138: Présence et canaux | D138: Adéquation canal-cible | E138: Cohérence | F138: Qualifié | G138: Non | H138: — | I138: Cible (COM-02) ; réseaux (COM-10) | J138: Réseau où la cible n'est pas → déplacer l'effort. Bon réseau → pas d'action. | K138: — | L138: Ne publie pas (parcours mise en place)
A139: COM-12 | B139: Comm & Création | C139: Présence et canaux | D139: Les quatre canaux d'acquisition | E139: Cohérence | F139: Chiffré (contacts) | G139: Calculé | H139: COM-12.01 | I139: Contacts par canal (ACQ-03) — partagé, posé une seule fois | J139: Un seul canal utilisé sur 4 → en tester un second. Les 4 utilisés mais dispersés → concentrer sur le plus rentable. | K139: — | L139: —
... A143: COM-16 | B143: Comm & Création | C143: Présence et canaux | D143: Référencement local | E143: Pratique | F143: Qualifié | G143: Non | H143: COM-16.01 | I143: Constaté par une recherche test « métier + ville » | J143: — | K143: — | L143: —
A144: COM-17 | B144: Comm & Création | C144: De la publication au contact | D144: Funnel 1 · Être vu : portée | E144: Cohérence | F144: Chiffré (contacts) | G144: Oui | H144: COM-17.01, COM-17.02, COM-17.03 | I144: Statistiques Google ou Meta si connectées | J144: Faible portée et peu d'abonnés → activer le réseau existant. Bonne portée et peu de contacts → le blocage est plus loin dans le parcours. | K144: Lu dans les statistiques de la plateforme. | L144: Ne publie pas (parcours mise en place) | M144: Nom du thème
A145: COM-18 | B145: Comm & Création | C145: De la publication au contact | D145: Funnel 2 · Intéresser : réactions | E145: Marché | F145: Chiffré (contacts) | G145: Oui | H145: COM-18.01 | I145: Portée (COM-17) | J145: Engagement faible sur peu de publications → tester les formats. Sur beaucoup → revoir accroche et angle (grille COM-49 à COM-54). | K145: Lu dans les statistiques de la plateforme. | L145: Ne publie pas (parcours mise en place) | M145: Nom du thème
A146: COM-19 | B146: Comm & Création | C146: De la publication au contact | D146: Funnel 4 · Passer à l'action : clics | E146: Marché | F146: Chiffré (contacts) | G146: Oui | H146: COM-19.01 | I146: Portée (COM-17) | J146: Peu de clics et pas de lien → ajouter un lien. Lien présent et peu de clics → revoir l'appel à l'action. | K146: Lu dans les statistiques de la plateforme. | L146: Ne publie pas (parcours mise en place) | M146: Nom du thème
A147: COM-20 | B147: Comm & Création | C147: De la publication au contact | D147: Appel à l'action | E147: Pratique | F147: Qualifié | G147: Calculé | H147: — | I147: Grille de qualité (COM-53) | J147: — | K147: — | L147: Ne publie pas (parcours mise en place)
A148: COM-21 | B148: Comm & Création | C148: De la publication au contact | D148: Funnel 6 · Devenir un contact : offre gratuite | E148: Pratique | F148: Chiffré (contacts) | G148: Oui | H148: COM-21.01, COM-21.02, COM-21.03, COM-21.04 | I148: — | J148: Aucune offre d'appel → en créer une. Offre existante qui récolte peu → revoir sa promesse. | K148: — | L148: — | M148: Nom du thème
A149: COM-22 | B149: Comm & Création | C149: De la publication au contact | D149: Funnel 6 · Devenir un contact : demandes venues des réseaux | E149: Cohérence | F149: Chiffré (contacts) | G149: Oui | H149: COM-22.01, COM-22.04 | I149: Contacts par canal (ACQ-03) | J149: Beaucoup de portée et peu de contacts → travailler le passage au contact. Peu des deux → travailler la portée. | K149: — | L149: Ne publie pas (parcours mise en place) | M149: Nom du thème
A150: COM-23 | B150: Comm & Création | C150: De la publication au contact | D150: Funnel 4 · Passer à l'action : messages privés | E150: Marché | F150: Chiffré (contacts) | G150: Oui | H150: COM-23.01, COM-23.02, COM-23.03 | I150: — | J150: 10 messages par mois → réponse personnelle dans la journée. 200 → réponses types et notifications. | K150: Noter le délai sur les 10 prochains messages. | L150: Ne publie pas (parcours mise en place) | M150: Nom du thème
A151: COM-24 | B151: Comm & Création | C151: Stratégie de contenu | D151: Objectif | E151: Pratique | F151: Qualifié | G151: Non | H151: COM-24.01 | I151: Objectif (inscription) | J151: — | K151: — | L151: —
A152: COM-25 | B152: Comm & Création | C152: Stratégie de contenu | D152: Lignes éditoriales | E152: Pratique | F152: Qualifié | G152: Non | H152: COM-25.01 | I152: — | J152: — | K152: — | L152: Ne publie pas (parcours mise en place)
A153: COM-26 | B153: Comm & Création | C153: Stratégie de contenu | D153: Équilibre des formats | E153: Cohérence | F153: Qualifié | G153: Oui | H153: COM-26.01 | I153: Lue sur les publications si connectées | J153: Un seul format qui marche → le garder et le décliner. Formats variés sans résultat → revenir au plus performant (COM-39). | K153: Lu sur les profils. | L153: Ne publie pas (parcours mise en place)
A154: COM-27 | B154: Comm & Création | C154: Stratégie de contenu | D154: Funnel 0 · Publications par étape | E154: Pratique | F154: Qualifié | G154: Calculé | H154: COM-27.02 | I154: Lue sur les publications | J154: — | K154: — | L154: Ne publie pas (parcours mise en place) | M154: Nom du thème
A155: COM-28 | B155: Comm & Création | C155: Stratégie de contenu | D155: Planification | E155: Pratique | F155: Qualifié | G155: Non | H155: COM-28.01 | I155: — | J155: — | K155: — | L155: Ne publie pas (parcours mise en place)
A156: COM-29 | B156: Comm & Création | C156: Stratégie de contenu | D156: Veille concurrentielle | E156: Pratique | F156: Qualifié | G156: Non | H156: COM-29.01 | I156: — | J156: — | K156: — | L156: —
A157: COM-30 | B157: Comm & Création | C157: Production | D157: Qui produit | E157: Contexte | F157: — | G157: Non | H157: — | I157: — | J157: Non noté : sert à l'IA pour expliquer le diagnostic. | K157: — | L157: Ne publie pas (parcours mise en place)
A158: COM-31 | B158: Comm & Création | C158: Production | D158: Temps consacré | E158: Cohérence | F158: Chiffré (heures) | G158: Oui | H158: COM-31.01, COM-31.02, COM-31.03, COM-31.04 | I158: Coût d'une heure (FIN-07) pour valoriser ce temps | J158: 1 h par semaine → un format simple, décliné partout. 10 h sans contact généré → revoir la stratégie avant de produire plus. | K158: Estimer une semaine type. | L158: Ne publie pas (parcours mise en place)
A159: COM-32 | B159: Comm & Création | C159: Production | D159: Moyens | E159: Cohérence | F159: Chiffré (contacts) | G159: Oui | H159: COM-32.01, COM-32.02, COM-32.03 | I159: Partagé avec FIN-05 (posé une seule fois) ; Création de contenu, agence, outils (ACQ-07) — partagé, posé une seule fois | J159: Budget élevé et peu de demandes → couper le poste le plus cher par demande. Budget nul et contenu qui convertit → un petit budget sur ce contenu. | K159: Additionner les factures de prestataires et outils du dernier mois. | L159: —
A160: COM-33 | B160: Comm & Création | C160: Production | D160: Rythme réel | E160: Pratique | F160: Qualifié | G160: Oui | H160: COM-33.01 | I160: Lu sur les profils si connectés | J160: Publications irrégulières → un rythme plus bas mais tenu. Rythme tenu → pas d'action. | K160: Lu sur les profils. | L160: Ne publie pas (parcours mise en place)
A161: COM-34 | B161: Comm & Création | C161: Production | D161: Réemploi du contenu | E161: Pratique | F161: Qualifié | G161: Oui | H161: COM-34.01, COM-34.02 | I161: — | J161: — | K161: — | L161: Ne publie pas (parcours mise en place)
A162: COM-35 | B162: Comm & Création | C162: Production | D162: Réserve d'avance | E162: Pratique | F162: Qualifié | G162: Oui | H162: COM-35.01, COM-35.02 | I162: Rythme (COM-33) | J162: Aucune réserve et rythme irrégulier → préparer 4 contenus d'avance. Réserve existante → pas d'action. | K162: — | L162: Ne publie pas (parcours mise en place)
A163: COM-36 | B163: Comm & Création | C163: Performance | D163: Taux d'engagement | E163: Marché | F163: Chiffré (contacts) | G163: Calculé | H163: — | I163: Réactions (COM-18) ÷ portée (COM-17) | J163: — | K163: — | L163: Ne publie pas (parcours mise en place)
A164: COM-37 | B164: Comm & Création | C164: Performance | D164: Funnel 1 · Être vu : évolution de l'audience | E164: Cohérence | F164: Qualifié | G164: Oui | H164: COM-37.01 | I164: Abonnés actuels (COM-17) | J164: Érosion → retravailler les contenus. Croissance sans contacts → le blocage est le passage au contact. | K164: Lu dans les statistiques de la plateforme. | L164: Ne publie pas (parcours mise en place) | M164: Nom du thème
A165: COM-38 | B165: Comm & Création | C165: Performance | D165: Rendement de l'audience | E165: Cohérence | F165: Chiffré (contacts) | G165: Calculé | H165: — | I165: Contacts (COM-22) ÷ abonnés (COM-17) | J165: — | K165: — | L165: Ne publie pas (parcours mise en place)
A166: COM-39 | B166: Comm & Création | C166: Performance | D166: Contenus les plus performants | E166: Cohérence | F166: Qualifié | G166: Oui | H166: COM-39.01, COM-39.02, COM-39.03, COM-39.07 | I166: Lues si connectées | J166: — | K166: Saisir les chiffres des 10 dernières publications. | L166: Ne publie pas (parcours mise en place)
A167: COM-40 | B167: Comm & Création | C167: Performance | D167: Écart entre ce qui marche et ce qui est publié | E167: Cohérence | F167: Qualifié | G167: Calculé | H167: — | I167: COM-39 comparé à COM-26 | J167: Écart fort → publier plus de ce qui marche (amplifier avant de diversifier). | K167: — | L167: Ne publie pas (parcours mise en place)
A168: COM-41 | B168: Comm & Création | C168: Performance | D168: Contenus les moins performants | E168: Cohérence | F168: Qualifié | G168: Calculé | H168: — | I168: Statistiques (COM-39) | J168: — | K168: — | L168: Ne publie pas (parcours mise en place)
A169: COM-42 | B169: Comm & Création | C169: Performance | D169: Notoriété | E169: Contexte | F169: — | G169: Oui | H169: COM-42.01, COM-42.02 | I169: — | J169: Non noté : sert à l'IA pour expliquer le diagnostic. | K169: — | L169: —
A170: COM-43 | B170: Comm & Création | C170: Performance | D170: Suivi des chiffres | E170: Pratique | F170: Qualifié | G170: Calculé | H170: COM-43.01, COM-43.03 | I170: Partagé avec ACQ-20 (posé une seule fois) ; Calculé sur le questionnaire | J170: — | K170: — | L170: Ne publie pas (parcours mise en place)
A171: COM-44 | B171: Comm & Création | C171: Vitrines et relation | D171: Avis clients | E171: Marché | F171: Qualifié | G171: Oui | H171: COM-44.01, COM-44.02, COM-44.03, COM-44.04 | I171: Partagé avec ACQ-06 (posé une seule fois) | J171: 5 avis → campagne de sollicitation. 200 avis à 4,8 → maintenir. | K171: Lu sur la fiche Google. | L171: —
A172: COM-45 | B172: Comm & Création | C172: Vitrines et relation | D172: Sollicitation d'avis | E172: Pratique | F172: Qualifié | G172: Non | H172: COM-45.01, COM-45.02 | I172: Clients signés (ACQ-11) → part des clients qui laissent un avis | J172: 20 clients par mois → demande en main propre. 500 → envoi automatique après prestation. | K172: — | L172: —
...

Sheet Acquisition — données
A1: Code | B1: Thème | C1: Nom du thème | D1: Écran | E1: Donnée | F1: Format de réponse | G1: Mode | H1: Niveau | I1: Condition d'affichage | J1: Période (selon l'ancienneté) | K1: RDV | L1: Commerce | M1: E-commerce | N1: Restaurant | O1: Chantier | P1: B2B | Q1: Abonnement | R1: Location | S1: Sert à | T1: Calcul ou source | U1: Données utilisées | V1: Utilisée dans | W1: Changement du 20 oct. | X1: Métiers concernés
A2: ACQ-01.01 | B2: ACQ-01 | C2: =IFERROR(INDEX(Thèmes!$D$2:$D$190,MATCH(B2,Thèmes!$A$2:$A$190,0)),"") | D2: A01 · Vos types de clients (tableau) | E2: Types de clients (ex. particuliers, professionnels, collectivités), jusqu'à 4 — partagée avec Comm (COM-02.01, COM-09.03) : posée par le premier agent qui en a besoin | F2: Liste | G2: Demandée | H2: Essentiel | I2: — | J2: — | K2: ● | L2: ● | M2: ● | N2: ● | O2: ● | P2: ● | Q2: ● | R2: ● | S2: Parcours | T2: — | U2: — | V2: COM-09.07 | W2: Libellé (« Donnée »)
A3: ACQ-01.02 | B3: ACQ-01 | C3: =IFERROR(INDEX(Thèmes!$D$2:$D$190,MATCH(B3,Thèmes!$A$2:$A$190,0)),"") | D3: A01 · Vos types de clients (tableau) | E3: Part du CA par type de client | F3: % par ligne | G3: Demandée | H3: Essentiel | I3: — | J3: — | K3: ● | L3: ● | M3: ● | N3: ● | O3: ● | P3: ● | Q3: ● | R3: ● | S3: Risque, Levier | T3: — | U3: — | V3: ACQ-01.11
A4: ACQ-01.03 | B4: ACQ-01 | C4: =IFERROR(INDEX(Thèmes!$D$2:$D$190,MATCH(B4,Thèmes!$A$2:$A$190,0)),"") | D4: A01 · Vos types de clients (tableau) | E4: Nombre de clients par type sur 12 mois | F4: Nombre par ligne | G4: Demandée | H4: Essentiel | I4: — | J4: Période adaptée : depuis la création si moins de 12 mois | K4: ● | L4: ● | M4: ● | N4: ● | O4: ● | P4: ● | Q4: ● | R4: ● | S4: Potentiel CA | T4: — | U4: — | V4: ACQ-01.12
A5: ACQ-01.04 | B5: ACQ-01 | C5: =IFERROR(INDEX(Thèmes!$D$2:$D$190,MATCH(B5,Thèmes!$A$2:$A$190,0)),"") | D5: A01 · Vos types de clients (tableau) | E5: Achats par client et par an, par type | F5: Nombre par ligne | G5: Demandée | H5: Approfondi | I5: — | J5: Période adaptée : depuis la création si moins de 12 mois | K5: ● | L5: ● | M5: ● | N5: ● | O5: ● | P5: ● | Q5: ● | R5: ● | S5: Potentiel CA | T5: — | U5: — | V5: ACQ-01.13
A6: ACQ-01.05 | B6: ACQ-01 | C6: =IFERROR(INDEX(Thèmes!$D$2:$D$190,MATCH(B6,Thèmes!$A$2:$A$190,0)),"") | D6: A01 · Vos types de clients (tableau) | E6: Type de client que vous voulez développer en priorité | F6: Choix dans la liste | G6: Demandée | H6: Essentiel | I6: — | J6: — | K6: ● | L6: ● | M6: ● | N6: ● | O6: ● | P6: ● | Q6: ● | R6: ● | S6: Cible | T6: — | U6: — | V6: XA32
A7: ACQ-01.06 | B7: ACQ-01 | C7: =IFERROR(INDEX(Thèmes!$D$2:$D$190,MATCH(B7,Thèmes!$A$2:$A$190,0)),"") | D7: A02 · Votre zone | E7: Répartition des clients par distance : moins de 5 km, 5 à 10, 10 à 25, 25 à 50, plus de 50 km | F7: Tranches en % | G7: Demandée | H7: Essentiel | I7: — | J7: — | K7: ● | L7: ● | N7: ● | O7: ● | P7: ● | Q7: ● | R7: ● | S7: Cible, Levier | T7: — | U7: — | V7: ACQ-01.14, XA31
A8: ACQ-01.07 | B8: ACQ-01 | C8: =IFERROR(INDEX(Thèmes!$D$2:$D$190,MATCH(B8,Thèmes!$A$2:$A$190,0)),"") | D8: A02 · Votre zone | E8: Zone (commune ou quartier) qui génère le plus de CA | F8: Texte | G8: Demandée | H8: Essentiel | I8: — | J8: — | K8: ● | L8: ● | N8: ● | O8: ● | P8: ● | Q8: ● | R8: ● | S8: Levier | T8: — | U8: — | V8: XA31
A9: ACQ-01.08 | B9: ACQ-01 | C9: =IFERROR(INDEX(Thèmes!$D$2:$D$190,MATCH(B9,Thèmes!$A$2:$A$190,0)),"") | D9: A02 · Votre zone | E9: Part du CA faite dans cette zone | F9: % | G9: Demandée | H9: Approfondi | I9: — | J9: — | K9: ● | L9: ● | N9: ● | O9: ● | P9: ● | Q9: ● | R9: ● | S9: Risque, Levier | T9: — | U9: — | V9: XA31
A10: ACQ-01.09 | B10: ACQ-01 | C10: =IFERROR(INDEX(Thèmes!$D$2:$D$190,MATCH(B10,Thèmes!$A$2:$A$190,0)),"") | D10: A02 · Votre zone | E10: Distance maximale acceptée pour une intervention | F10: km | G10: Demandée | H10: Approfondi | I10: — | J10: — | O10: ● | S10: Capacité | T10: — | U10: — | V10: XA31
A11: ACQ-01.10 | B11: ACQ-01 | C11: =IFERROR(INDEX(Thèmes!$D$2:$D$190,MATCH(B11,Thèmes!$A$2:$A$190,0)),"") | D11: A02 · Votre zone | E11: Part des ventes hors de votre région et à l'étranger | F11: % | G11: Demandée | H11: Approfondi | I11: — | J11: — | M11: ● | S11: Opportunité | T11: — | U11: — | V11: Lue par l'IA pour adapter le conseil
A12: ACQ-01.11 | B12: ACQ-01 | C12: =IFERROR(INDEX(Thèmes!$D$2:$D$190,MATCH(B12,Thèmes!$A$2:$A$190,0)),"") | D12: — | E12: CA par type de client | F12: € | G12: Calculée | H12: — | I12: — | J12: — | K12: ● | L12: ● | M12: ● | N12: ● | O12: ● | P12: ● | Q12: ● | R12: ● | S12: Levier | T12: CA mensuel × 12 × part du CA du type | U12: Inscription · CA mensuel, ACQ-01.02 | V12: ACQ-01.12
A13: ACQ-01.12 | B13: ACQ-01 | C13: =IFERROR(INDEX(Thèmes!$D$2:$D$190,MATCH(B13,Thèmes!$A$2:$A$190,0)),"") | D13: — | E13: Valeur annuelle d'un client, par type | F13: € | G13: Calculée | H13: — | I13: — | J13: — | K13: ● | L13: ● | M13: ● | N13: ● | O13: ● | P13: ● | Q13: ● | R13: ● | S13: Levier | T13: CA du type ÷ clients du type | U13: ACQ-01.11, ACQ-01.03 | V13: ACQ-01.13, COM-02.02, XA32
A14: ACQ-01.13 | B14: ACQ-01 | C14: =IFERROR(INDEX(Thèmes!$D$2:$D$190,MATCH(B14,Thèmes!$A$2:$A$190,0)),"") | D14: — | E14: Panier moyen par type | F14: € | G14: Calculée | H14: — | I14: — | J14: — | K14: ● | L14: ● | M14: ● | N14: ● | O14: ● | P14: ● | Q14: ● | R14: ● | S14: Levier | T14: Valeur annuelle d'un client ÷ achats par an | U14: ACQ-01.12, ACQ-01.04 | V14: Affichée dans le rapport
A15: ACQ-01.14 | B15: ACQ-01 | C15: =IFERROR(INDEX(Thèmes!$D$2:$D$190,MATCH(B15,Thèmes!$A$2:$A$190,0)),"") | D15: — | E15: Distance médiane des clients | F15: Tranche de km | G15: Calculée | H15: — | I15: — | J15: — | K15: ● | L15: ● | N15: ● | O15: ● | P15: ● | Q15: ● | R15: ● | S15: Cible | T15: Tranche dans laquelle on atteint 50 % des clients | U15: ACQ-01.06 | V15: XA31
A16: ACQ-01.15 | B16: ACQ-01 | C16: =IFERROR(INDEX(Thèmes!$D$2:$D$190,MATCH(B16,Thèmes!$A$2:$A$190,0)),"") | D16: — | E16: Marge par type de client | F16: % | G16: Autre agent | H16: — | I16: — | J16: — | K16: ● | L16: ● | M16: ● | N16: ● | O16: ● | P16: ● | Q16: ● | R16: ● | S16: Levier | T16: Posée par l'agent Finance (FIN-02) ; lue ici si cet agent est souscrit | U16: FIN-02 | V16: Affichée dans le rapport
A17: ACQ-02.01 | B17: ACQ-02 | C17: =IFERROR(INDEX(Thèmes!$D$2:$D$190,MATCH(B17,Thèmes!$A$2:$A$190,0)),"") | D17: A03 · Vos demandes | E17: Demandes reçues par mois, moyenne des 3 derniers mois (mot adapté au métier : voir onglet Lexique) | F17: Nombre | G17: Demandée | H17: Essentiel | I17: — | J17: Période adaptée : depuis la création si moins de 3 mois | K17: ● | L17: ● | M17: ● | N17: ● | O17: ● | P17: ● | Q17: ● | R17: ● | S17: Parcours, Problème | T17: — | U17: — | V17: ACQ-02.06, ACQ-02.07, ACQ-02.08, ACQ-07.09, ACQ-08.08, ACQ-11.19, ACQ-11.24, ACQ-11.28, COM-13.07, COM-13.08, COM-13.09, XA03, XA38, XA41
A18: ACQ-02.02 | B18: ACQ-02 | C18: =IFERROR(INDEX(Thèmes!$D$2:$D$190,MATCH(B18,Thèmes!$A$2:$A$190,0)),"") | D18: A03 · Vos demandes | E18: Même chiffre il y a 6 mois | F18: Nombre | G18: Demandée | H18: Essentiel | I18: — | J18: 3 mois, 6 mois plus tôt (masquée avant 9 mois d'existence) | K18: ● | L18: ● | M18: ● | N18: ● | O18: ● | P18: ● | Q18: ● | R18: ● | S18: Problème | T18: — | U18: — | V18: ACQ-02.06
A19: ACQ-02.03 | B19: ACQ-02 | C19: =IFERROR(INDEX(Thèmes!$D$2:$D$190,MATCH(B19,Thèmes!$A$2:$A$190,0)),"") | D19: A03 · Vos demandes | E19: Même chiffre il y a 12 mois (même saison) | F19: Nombre | G19: Demandée | H19: Essentiel | I19: — | J19: Mêmes 3 mois, un an plus tôt (masquée avant 15 mois d'existence) | K19: ● | L19: ● | M19: ● | N19: ● | O19: ● | P19: ● | Q19: ● | R19: ● | S19: Problème | T19: — | U19: — | V19: ACQ-02.06
A20: ACQ-02.04 | B20: ACQ-02 | C20: =IFERROR(INDEX(Thèmes!$D$2:$D$190,MATCH(B20,Thèmes!$A$2:$A$190,0)),"") | D20: A03 · Vos demandes | E20: Demandes qualifiées par mois (dans votre zone, votre offre et votre gamme de prix) | F20: Nombre ou % | G20: Demandée | H20: Essentiel | I20: — | J20: — | K20: ● | O20: ● | P20: ● | Q20: ● | S20: Problème, Parcours | T20: — | U20: — | V20: ACQ-02.07, ACQ-11.21
A21: ACQ-02.05 | B21: ACQ-02 | C21: =IFERROR(INDEX(Thèmes!$D$2:$D$190,MATCH(B21,Thèmes!$A$2:$A$190,0)),"") | D21: A03 · Vos demandes | E21: Motif principal des demandes non qualifiées : hors zone, budget trop faible, hors offre, simple curiosité | F21: Choix | G21: Demandée | H21: Approfondi | I21: — | J21: — | K21: ● | O21: ● | P21: ● | Q21: ● | S21: Levier | T21: — | U21: — | V21: DC04
A22: ACQ-02.06 | B22: ACQ-02 | C22: =IFERROR(INDEX(Thèmes!$D$2:$D$190,MATCH(B22,Thèmes!$A$2:$A$190,0)),"") | D22: — | E22: Évolution des demandes sur 6 et 12 mois | F22: % | G22: Calculée | H22: — | I22: — | J22: — | K22: ● | L22: ● | M22: ● | N22: ● | O22: ● | P22: ● | Q22: ● | R22: ● | S22: Problème | T22: (Moyenne par mois des 3 derniers mois − moyenne par mois des mêmes 3 mois, 6 mois ou un an plus tôt) ÷ cette dernière. Non calculée si les deux réponses ne portent pas sur des mois alignés, ou si le périmètre de l'activité a changé entre les deux périodes (ACQ-23.13). | U22: ACQ-02.01, ACQ-02.02, ACQ-02.03, ACQ-23.13 | V22: COM-32.07, XA30, XC07
A23: ACQ-02.07 | B23: ACQ-02 | C23: =IFERROR(INDEX(Thèmes!$D$2:$D$190,MATCH(B23,Thèmes!$A$2:$A$190,0)),"") | D23: — | E23: Part des demandes qualifiées | F23: % | G23: Calculée | H23: — | I23: — | J23: — | K23: ● | O23: ● | P23: ● | Q23: ● | S23: Problème | T23: Demandes qualifiées ÷ demandes reçues | U23: ACQ-02.04, ACQ-02.01 | V23: XA02
A24: ACQ-02.08 | B24: ACQ-02 | C24: =IFERROR(INDEX(Thèmes!$D$2:$D$190,MATCH(B24,Thèmes!$A$2:$A$190,0)),"") | D24: — | E24: Taux demande → rendez-vous | F24: % | G24: Calculée | H24: — | I24: — | J24: — | K24: ● | O24: ● | P24: ● | S24: Parcours | T24: Rendez-vous obtenus ÷ demandes reçues | U24: ACQ-09.01, ACQ-02.01 | V24: XA02
A25: ACQ-02.09 | B25: ACQ-02 | C25: =IFERROR(INDEX(Thèmes!$D$2:$D$190,MATCH(B25,Thèmes!$A$2:$A$190,0)),"") | D25: — | E25: Valeur d'une demande reçue | F25: € | G25: Calculée | H25: — | I25: — | J25: — | K25: ● | L25: ● | M25: ● | N25: ● | O25: ● | P25: ● | Q25: ● | S25: Potentiel CA | T25: Taux de transformation × montant du premier achat (commerce, restaurant, e-commerce : taux de transformation × panier moyen) | U25: ACQ-11.19, ACQ-11.03, ACQ-11.24, ACQ-11.28, ACQ-15.06 | V25: ACQ-08.09, ACQ-22.15, ACQ-22.18, XA01, XA05
A26: ACQ-03.01 | B26: ACQ-03 | C26: =IFERROR(INDEX(Thèmes!$D$2:$D$190,MATCH(B26,Thèmes!$A$2:$A$190,0)),"") | D26: A04 · Vos canaux (tableau) | E26: Canaux qui amènent des clients : bouche-à-oreille, fiche Google, site, réseaux sociaux, publicité, plateformes, partenaires, prospection, passage, salons — partagée avec Comm (COM-12.01) : posée par le premier agent qui en a besoin | F26: Liste (une ligne par canal) | G26: Demandée | H26: Essentiel | I26: — | J26: — | K26: ● | L26: ● | M26: ● | N26: ● | O26: ● | P26: ● | Q26: ● | R26: ● | S26: Parcours | T26: — | U26: — | V26: COM-12.02 | W26: Libellé (« Donnée »)
A27: ACQ-03.02 | B27: ACQ-03 | C27: =IFERROR(INDEX(Thèmes!$D$2:$D$190,MATCH(B27,Thèmes!$A$2:$A$190,0)),"") | D27: A04 · Vos canaux (tableau) | E27: Part des demandes par canal (le nombre par canal est calculé : ACQ-02.01 × part) | F27: Nombre par ligne | G27: Demandée | H27: Essentiel | I27: D03 · une ligne par canal coché | J27: — | K27: ● | L27: ● | M27: ● | N27: ● | O27: ● | P27: ● | Q27: ● | R27: ● | S27: Parcours | T27: — | U27: — | V27: ACQ-03.07, ACQ-03.09, ACQ-03.12, ACQ-06.09, COM-12.02, COM-19.03, COM-22.02 | W27: Libellé (« Donnée »)
A28: ACQ-03.03 | B28: ACQ-03 | C28: =IFERROR(INDEX(Thèmes!$D$2:$D$190,MATCH(B28,Thèmes!$A$2:$A$190,0)),"") | D28: A04 · Vos canaux (tableau) | E28: Part des nouveaux clients par canal (le nombre par canal est calculé avec le total ACQ-11.01 quand il est posé) | F28: Nombre par ligne | G28: Demandée | H28: Essentiel | I28: D03 · une ligne par canal coché | J28: — | K28: ● | L28: ● | M28: ● | N28: ● | O28: ● | P28: ● | Q28: ● | R28: ● | S28: Parcours | T28: — | U28: — | V28: ACQ-03.07, ACQ-03.08, ACQ-03.10, ACQ-18.04, COM-22.02 | W28: Libellé (« Donnée »)
A29: ACQ-03.04 | B29: ACQ-03 | C29: =IFERROR(INDEX(Thèmes!$D$2:$D$190,MATCH(B29,Thèmes!$A$2:$A$190,0)),"") | D29: A04 · Vos canaux (tableau) | E29: Part du CA sur 12 mois, par canal | F29: % par ligne | G29: Demandée | H29: Essentiel | I29: D03 · une ligne par canal coché | J29: Période adaptée : depuis la création si moins de 12 mois | K29: ● | L29: ● | M29: ● | N29: ● | O29: ● | P29: ● | Q29: ● | R29: ● | S29: Levier | T29: — | U29: — | V29: ACQ-03.08, ACQ-03.11, ACQ-07.07, ACQ-07.12, COM-22.03, XA12
A30: ACQ-03.05 | B30: ACQ-03 | C30: =IFERROR(INDEX(Thèmes!$D$2:$D$190,MATCH(B30,Thèmes!$A$2:$A$190,0)),"") | D30: A04 · Vos canaux (tableau) | E30: Dépense fixe par mois, par canal : publicité, abonnement de plateforme (les commissions prélevées sur les ventes sont demandées à part, écran budget) | F30: € par ligne | G30: Demandée | H30: Essentiel | I30: D04 · seulement les canaux payants cochés | J30: Aujourd'hui | K30: ● | L30: ● | M30: ● | N30: ● | O30: ● | P30: ● | Q30: ● | R30: ● | S30: Perte, Levier | T30: — | U30: — | V30: ACQ-03.09, ACQ-03.10, ACQ-03.11, ACQ-07.06, ACQ-07.12, XA11, XA12
A31: ACQ-03.06 | B31: ACQ-03 | C31: =IFERROR(INDEX(Thèmes!$D$2:$D$190,MATCH(B31,Thèmes!$A$2:$A$190,0)),"") | D31: A04 · Vos canaux (tableau) | E31: Tendance de chaque canal sur 12 mois : en hausse, stable, en baisse | F31: Choix par ligne | G31: Demandée | H31: Approfondi | I31: D03 · une ligne par canal coché | J31: 12 mois précédents (masquée avant 24 mois d'existence) | K31: ● | L31: ● | M31: ● | N31: ● | O31: ● | P31: ● | Q31: ● | R31: ● | S31: Problème | T31: — | U31: — | V31: XA30
A32: ACQ-03.07 | B32: ACQ-03 | C32: =IFERROR(INDEX(Thèmes!$D$2:$D$190,MATCH(B32,Thèmes!$A$2:$A$190,0)),"") | D32: — | E32: Taux de transformation par canal | F32: % | G32: Calculée | H32: — | I32: — | J32: — | K32: ● | L32: ● | M32: ● | N32: ● | O32: ● | P32: ● | Q32: ● | R32: ● | S32: Levier | T32: Nouveaux clients du canal ÷ demandes du canal | U32: ACQ-03.03, ACQ-03.02 | V32: Affichée dans le rapport
A33: ACQ-03.08 | B33: ACQ-03 | C33: =IFERROR(INDEX(Thèmes!$D$2:$D$190,MATCH(B33,Thèmes!$A$2:$A$190,0)),"") | D33: — | E33: Panier moyen par canal | F33: € | G33: Calculée | H33: — | I33: — | J33: — | K33: ● | L33: ● | M33: ● | N33: ● | O33: ● | P33: ● | Q33: ● | R33: ● | S33: Levier | T33: CA du canal sur 12 mois ÷ nouveaux clients du canal sur 12 mois | U33: ACQ-03.04, Inscription · CA mensuel, ACQ-03.03 | V33: Affichée dans le rapport
A34: ACQ-03.09 | B34: ACQ-03 | C34: =IFERROR(INDEX(Thèmes!$D$2:$D$190,MATCH(B34,Thèmes!$A$2:$A$190,0)),"") | D34: — | E34: Coût par demande, par canal | F34: € | G34: Calculée | H34: — | I34: — | J34: — | K34: ● | L34: ● | M34: ● | N34: ● | O34: ● | P34: ● | Q34: ● | R34: ● | S34: Levier | T34: (Dépense du canal + commissions du canal) ÷ demandes du canal | U34: ACQ-03.05, ACQ-07.07, ACQ-03.02 | V34: Affichée dans le rapport
A35: ACQ-03.10 | B35: ACQ-03 | C35: =IFERROR(INDEX(Thèmes!$D$2:$D$190,MATCH(B35,Thèmes!$A$2:$A$190,0)),"") | D35: — | E35: Coût d'acquisition d'un client, par canal | F35: € | G35: Calculée | H35: — | I35: — | J35: — | K35: ● | L35: ● | M35: ● | N35: ● | O35: ● | P35: ● | Q35: ● | R35: ● | S35: Perte, Levier | T35: (Dépense du canal + commissions du canal) ÷ nouveaux clients du canal | U35: ACQ-03.05, ACQ-07.07, ACQ-03.03 | V35: XA10, XA11, XA39, XC32
A36: ACQ-03.11 | B36: ACQ-03 | C36: =IFERROR(INDEX(Thèmes!$D$2:$D$190,MATCH(B36,Thèmes!$A$2:$A$190,0)),"") | D36: — | E36: Rendement de chaque canal (CA rapporté pour 1 € dépensé) | F36: Ratio | G36: Calculée | H36: — | I36: — | J36: — | K36: ● | L36: ● | M36: ● | N36: ● | O36: ● | P36: ● | Q36: ● | R36: ● | S36: Levier | T36: CA du canal ÷ (dépense du canal + commissions du canal) | U36: ACQ-03.04, Inscription · CA mensuel, ACQ-03.05, ACQ-07.07 | V36: XA11
A37: ACQ-03.12 | B37: ACQ-03 | C37: =IFERROR(INDEX(Thèmes!$D$2:$D$190,MATCH(B37,Thèmes!$A$2:$A$190,0)),"") | D37: — | E37: Part des demandes venant du 1er canal | F37: % | G37: Calculée | H37: — | I37: — | J37: — | K37: ● | L37: ● | M37: ● | N37: ● | O37: ● | P37: ● | Q37: ● | R37: ● | S37: Risque | T37: Demandes du 1er canal ÷ total des demandes | U37: ACQ-03.02 | V37: XA13
A38: ACQ-04.01 | B38: ACQ-04 | C38: =IFERROR(INDEX(Thèmes!$D$2:$D$190,MATCH(B38,Thèmes!$A$2:$A$190,0)),"") | D38: A05 · Votre prospection | E38: Heures de prospection par semaine | F38: Heures | G38: Demandée | H38: Essentiel | I38: D03 · si « prospection » est cochée | J38: — | K38: ● | O38: ● | P38: ● | Q38: ● | S38: Capacité | T38: — | U38: — | V38: ACQ-04.09
A39: ACQ-04.02 | B39: ACQ-04 | C39: =IFERROR(INDEX(Thèmes!$D$2:$D$190,MATCH(B39,Thèmes!$A$2:$A$190,0)),"") | D39: A05 · Votre prospection | E39: Actions par semaine : appels, emails, messages, visites, salons | F39: Tableau par type d'action | G39: Demandée | H39: Essentiel | I39: D03 · si « prospection » est cochée | J39: — | K39: ● | O39: ● | P39: ● | Q39: ● | S39: Parcours | T39: — | U39: — | V39: ACQ-04.07, ACQ-04.08, ACQ-04.10
A40: ACQ-04.03 | B40: ACQ-04 | C40: =IFERROR(INDEX(Thèmes!$D$2:$D$190,MATCH(B40,Thèmes!$A$2:$A$190,0)),"") | D40: A05 · Votre prospection | E40: Réponses positives obtenues par mois | F40: Nombre | G40: Demandée | H40: Approfondi | I40: D03 · si « prospection » est cochée | J40: — | K40: ● | O40: ● | P40: ● | Q40: ● | S40: Parcours | T40: — | U40: — | V40: ACQ-04.07
A41: ACQ-04.04 | B41: ACQ-04 | C41: =IFERROR(INDEX(Thèmes!$D$2:$D$190,MATCH(B41,Thèmes!$A$2:$A$190,0)),"") | D41: A05 · Votre prospection | E41: Rendez-vous obtenus grâce à la prospection, par mois | F41: Nombre | G41: Demandée | H41: Essentiel | I41: D03 · si « prospection » est cochée | J41: — | K41: ● | O41: ● | P41: ● | Q41: ● | S41: Parcours | T41: — | U41: — | V41: ACQ-04.08
A42: ACQ-04.05 | B42: ACQ-04 | C42: =IFERROR(INDEX(Thèmes!$D$2:$D$190,MATCH(B42,Thèmes!$A$2:$A$190,0)),"") | D42: A05 · Votre prospection | E42: Clients signés grâce à la prospection sur 12 mois | F42: Nombre | G42: Demandée | H42: Essentiel | I42: D03 · si « prospection » est cochée | J42: Période adaptée : depuis la création si moins de 12 mois | K42: ● | O42: ● | P42: ● | Q42: ● | S42: Potentiel CA | T42: — | U42: — | V42: ACQ-04.09
A43: ACQ-04.06 | B43: ACQ-04 | C43: =IFERROR(INDEX(Thèmes!$D$2:$D$190,MATCH(B43,Thèmes!$A$2:$A$190,0)),"") | D43: A05 · Votre prospection | E43: Contacts jamais sollicités dans votre fichier de prospects | F43: Nombre | G43: Demandée | H43: Approfondi | I43: D03 · si « prospection » est cochée | J43: — | O43: ● | P43: ● | S43: Opportunité | T43: — | U43: — | V43: ACQ-04.10
A44: ACQ-04.07 | B44: ACQ-04 | C44: =IFERROR(INDEX(Thèmes!$D$2:$D$190,MATCH(B44,Thèmes!$A$2:$A$190,0)),"") | D44: — | E44: Taux de réponse de la prospection | F44: % | G44: Calculée | H44: — | I44: — | J44: — | K44: ● | O44: ● | P44: ● | Q44: ● | S44: Problème | T44: Réponses positives ÷ actions du mois | U44: ACQ-04.03, ACQ-04.02 | V44: Affichée dans le rapport
A45: ACQ-04.08 | B45: ACQ-04 | C45: =IFERROR(INDEX(Thèmes!$D$2:$D$190,MATCH(B45,Thèmes!$A$2:$A$190,0)),"") | D45: — | E45: Actions nécessaires pour obtenir un rendez-vous | F45: Nombre | G45: Calculée | H45: — | I45: — | J45: — | K45: ● | O45: ● | P45: ● | Q45: ● | S45: Levier | T45: Actions du mois ÷ rendez-vous obtenus | U45: ACQ-04.02, ACQ-04.04 | V45: Affichée dans le rapport
A46: ACQ-04.09 | B46: ACQ-04 | C46: =IFERROR(INDEX(Thèmes!$D$2:$D$190,MATCH(B46,Thèmes!$A$2:$A$190,0)),"") | D46: — | E46: Valeur d'une heure de prospection | F46: € | G46: Calculée | H46: — | I46: — | J46: — | K46: ● | O46: ● | P46: ● | Q46: ● | S46: Potentiel CA | T46: (Clients prospection × montant du premier achat) ÷ heures de prospection sur 12 mois | U46: ACQ-04.05, ACQ-11.03, ACQ-04.01 | V46: XA28
A47: ACQ-04.10 | B47: ACQ-04 | C47: =IFERROR(INDEX(Thèmes!$D$2:$D$190,MATCH(B47,Thèmes!$A$2:$A$190,0)),"") | D47: — | E47: Semaines de prospection restantes dans le fichier | F47: Semaines | G47: Calculée | H47: — | I47: — | J47: — | O47: ● | P47: ● | S47: Opportunité | T47: Contacts jamais sollicités ÷ actions par semaine | U47: ACQ-04.06, ACQ-04.02 | V47: Affichée dans le rapport
A48: ACQ-05.01 | B48: ACQ-05 | C48: =IFERROR(INDEX(Thèmes!$D$2:$D$190,MATCH(B48,Thèmes!$A$2:$A$190,0)),"") | D48: A06 · Vos partenaires (tableau) | E48: Partenaires au total : prescripteurs, apporteurs d'affaires, affiliés | F48: Nombre | G48: Demandée | H48: Essentiel | I48: D03 · si « partenaires » est coché | J48: — | K48: ● | L48: ● | M48: ● | N48: ● | O48: ● | P48: ● | Q48: ● | R48: ● | S48: Parcours | T48: — | U48: — | V48: ACQ-05.05
A49: ACQ-05.02 | B49: ACQ-05 | C49: =IFERROR(INDEX(Thèmes!$D$2:$D$190,MATCH(B49,Thèmes!$A$2:$A$190,0)),"") | D49: A06 · Vos partenaires (tableau) | E49: Partenaires qui vous ont apporté au moins un client sur 12 mois | F49: Nombre | G49: Demandée | H49: Essentiel | I49: D03 · si « partenaires » est coché | J49: Période adaptée : depuis la création si moins de 12 mois | K49: ● | L49: ● | M49: ● | N49: ● | O49: ● | P49: ● | Q49: ● | R49: ● | S49: Levier | T49: — | U49: — | V49: ACQ-05.05
A50: ACQ-05.03 | B50: ACQ-05 | C50: =IFERROR(INDEX(Thèmes!$D$2:$D$190,MATCH(B50,Thèmes!$A$2:$A$190,0)),"") | D50: A06 · Vos partenaires (tableau) | E50: Pour vos 3 principaux partenaires : contacts apportés par mois, clients signés sur 12 mois, CA généré sur 12 mois (le total remplit la ligne « Partenaires » du tableau des canaux) | F50: Tableau 3 × 3 | G50: Demandée | H50: Essentiel | I50: D03 · si « partenaires » est coché | J50: Période adaptée : depuis la création si moins de 12 mois | K50: ● | L50: ● | M50: ● | N50: ● | O50: ● | P50: ● | Q50: ● | R50: ● | S50: Potentiel CA, Risque | T50: — | U50: — | V50: ACQ-05.06, ACQ-05.07, ACQ-05.08, ACQ-05.09
A51: ACQ-05.04 | B51: ACQ-05 | C51: =IFERROR(INDEX(Thèmes!$D$2:$D$190,MATCH(B51,Thèmes!$A$2:$A$190,0)),"") | D51: A06 · Vos partenaires (tableau) | E51: Commission ou contrepartie versée | F51: % ou € par client | G51: Demandée | H51: Approfondi | I51: D03 · si « partenaires » est coché | J51: — | K51: ● | L51: ● | M51: ● | N51: ● | O51: ● | P51: ● | Q51: ● | R51: ● | S51: Perte | T51: — | U51: — | V51: ACQ-05.09
A52: ACQ-05.05 | B52: ACQ-05 | C52: =IFERROR(INDEX(Thèmes!$D$2:$D$190,MATCH(B52,Thèmes!$A$2:$A$190,0)),"") | D52: — | E52: Part des partenaires réellement actifs | F52: % | G52: Calculée | H52: — | I52: — | J52: — | K52: ● | L52: ● | M52: ● | N52: ● | O52: ● | P52: ● | Q52: ● | R52: ● | S52: Opportunité | T52: Partenaires actifs ÷ partenaires au total | U52: ACQ-05.02, ACQ-05.01 | V52: Affichée dans le rapport
A53: ACQ-05.06 | B53: ACQ-05 | C53: =IFERROR(INDEX(Thèmes!$D$2:$D$190,MATCH(B53,Thèmes!$A$2:$A$190,0)),"") | D53: — | E53: Taux de transformation des contacts apportés | F53: % | G53: Calculée | H53: — | I53: — | J53: — | K53: ● | L53: ● | M53: ● | N53: ● | O53: ● | P53: ● | Q53: ● | R53: ● | S53: Levier | T53: Clients signés ÷ (contacts apportés par mois × 12) | U53: ACQ-05.03 | V53: Affichée dans le rapport
A54: ACQ-05.07 | B54: ACQ-05 | C54: =IFERROR(INDEX(Thèmes!$D$2:$D$190,MATCH(B54,Thèmes!$A$2:$A$190,0)),"") | D54: — | E54: Panier moyen des clients apportés par les partenaires | F54: € | G54: Calculée | H54: — | I54: — | J54: — | K54: ● | L54: ● | M54: ● | N54: ● | O54: ● | P54: ● | Q54: ● | R54: ● | S54: Levier | T54: CA des partenaires ÷ clients des partenaires | U54: ACQ-05.03 | V54: Affichée dans le rapport
A55: ACQ-05.08 | B55: ACQ-05 | C55: =IFERROR(INDEX(Thèmes!$D$2:$D$190,MATCH(B55,Thèmes!$A$2:$A$190,0)),"") | D55: — | E55: Part du CA partenaires faite par le 1er partenaire | F55: % | G55: Calculée | H55: — | I55: — | J55: — | K55: ● | L55: ● | M55: ● | N55: ● | O55: ● | P55: ● | Q55: ● | R55: ● | S55: Risque | T55: CA du 1er partenaire ÷ CA de tous les partenaires | U55: ACQ-05.03 | V55: XA15
A56: ACQ-05.09 | B56: ACQ-05 | C56: =IFERROR(INDEX(Thèmes!$D$2:$D$190,MATCH(B56,Thèmes!$A$2:$A$190,0)),"") | D56: — | E56: Valeur nette des partenariats sur 12 mois | F56: € | G56: Calculée | H56: — | I56: — | J56: — | K56: ● | L56: ● | M56: ● | N56: ● | O56: ● | P56: ● | Q56: ● | R56: ● | S56: Potentiel CA | T56: CA généré par les partenaires − commissions versées | U56: ACQ-05.03, ACQ-05.04 | V56: XA15
A57: ACQ-06.01 | B57: ACQ-06 | C57: =IFERROR(INDEX(Thèmes!$D$2:$D$190,MATCH(B57,Thèmes!$A$2:$A$190,0)),"") | D57: A07 · Votre présence en ligne | E57: Avis Google : nombre, note, avis des 6 derniers mois (regroupe ACQ-06.01, 06.02 et 06.03) — partagée avec COM-44.01 | F57: Plusieurs champs : Avis au total · Note sur 5 · Avis reçus sur les 6 derniers mois | G57: Demandée | H57: Essentiel | I57: D03 · si « fiche Google » est cochée | J57: — | K57: ● | L57: ● | N57: ● | O57: ● | P57: ● | Q57: ● | R57: ● | S57: Cible | T57: Saisie par le dirigeant tant qu'aucune connexion n'existe. Quand la connexion existera : Lu sur la fiche Google si elle est connectée | U57: — | V57: ACQ-06.11, COM-08.02, COM-09.06, COM-44.05, COM-46.03 | W57: Mode : Importée → Demandée (le dirigeant la saisit) · Format de réponse · Libellé (« Donnée »)
A58: ACQ-06.02 | B58: ACQ-06 | C58: =IFERROR(INDEX(Thèmes!$D$2:$D$190,MATCH(B58,Thèmes!$A$2:$A$190,0)),"") | D58: A07 · Votre présence en ligne | E58: Note Google moyenne | F58: Note sur 5 | G58: Calculée | H58: — | I58: D03 · si « fiche Google » est cochée | J58: — | K58: ● | L58: ● | N58: ● | O58: ● | P58: ● | Q58: ● | R58: ● | S58: Cible | T58: Lue dans la réponse à ACQ-06.01 (champ « Note sur 5 ») | U58: ACQ-06.01 | V58: ACQ-06.11 | W58: Mode : Calculée (plus de question : la banque la lit dans une autre réponse)
A59: ACQ-06.03 | B59: ACQ-06 | C59: =IFERROR(INDEX(Thèmes!$D$2:$D$190,MATCH(B59,Thèmes!$A$2:$A$190,0)),"") | D59: A07 · Votre présence en ligne | E59: Avis reçus sur les 6 derniers mois | F59: Nombre | G59: Calculée | H59: — | I59: D03 · si « fiche Google » est cochée | J59: Période adaptée : depuis la création si moins de 6 mois | K59: ● | L59: ● | N59: ● | O59: ● | P59: ● | Q59: ● | R59: ● | S59: Problème | T59: Lue dans la réponse à ACQ-06.01 (champ « Avis reçus sur les 6 derniers mois ») | U59: ACQ-06.01 | V59: COM-44.06, XA43 | W59: Mode : Calculée (plus de question : la banque la lit dans une autre réponse)
A60: ACQ-06.04 | B60: ACQ-06 | C60: =IFERROR(INDEX(Thèmes!$D$2:$D$190,MATCH(B60,Thèmes!$A$2:$A$190,0)),"") | D60: A07 · Votre présence en ligne | E60: Vues de la fiche Google et actions (appels, itinéraires, clics vers le site), en totaux sur 3 mois : le moteur divise par 3 pour avoir le mois. Le passage des vues aux actions est la conversion de la fiche. Regroupe ACQ-06.04 et 06.05 — partagée avec COM-14.02 | F60: Plusieurs champs : Vues de votre fiche · Appels · Demandes d'itinéraire · Clics vers votre site | G60: Demandée | H60: Essentiel | I60: D03 · si « fiche Google » est cochée | J60: — | K60: ● | L60: ● | N60: ● | O60: ● | P60: ● | Q60: ● | R60: ● | S60: Parcours | T60: Saisie par le dirigeant tant qu'aucune connexion n'existe. Quand la connexion existera : Statistiques de la fiche Google | U60: — | V60: ACQ-06.10, COM-22.02, XC29 | W60: Mode : Importée → Demandée (le dirigeant la saisit) · Format de réponse · Libellé (« Donnée »)
A61: ACQ-06.05 | B61: ACQ-06 | C61: =IFERROR(INDEX(Thèmes!$D$2:$D$190,MATCH(B61,Thèmes!$A$2:$A$190,0)),"") | D61: A07 · Votre présence en ligne | E61: Vues de la fiche Google par mois | F61: Nombre | G61: Calculée | H61: — | I61: D03 · si « fiche Google » est cochée | J61: — | K61: ● | L61: ● | N61: ● | O61: ● | P61: ● | Q61: ● | R61: ● | S61: Parcours | T61: Lue dans la réponse à ACQ-06.04 (champ « Vues de votre fiche », total sur 3 mois) ÷ 3 | U61: ACQ-06.04 | V61: ACQ-06.10 | W61: Mode : Calculée (plus de question : la banque la lit dans une autre réponse)
A62: ACQ-06.06 | B62: ACQ-06 | C62: =IFERROR(INDEX(Thèmes!$D$2:$D$190,MATCH(B62,Thèmes!$A$2:$A$190,0)),"") | D62: A07 · Votre présence en ligne | E62: Avis et note des 2 concurrents qui apparaissent en premier sur « métier + ville » : repère local pour l'objectif d'avis (plus parlant qu'une moyenne nationale) | F62: Tableau : Nom · Avis · Note sur 5 (lignes fixe: Concurrent 1 / Concurrent 2) | G62: Demandée | H62: Approfondi | I62: D03 · si « fiche Google » est cochée | J62: — | K62: ● | L62: ● | N62: ● | O62: ● | P62: ● | Q62: ● | R62: ● | S62: Cible | T62: Saisie par le dirigeant tant qu'aucune connexion n'existe. Quand la connexion existera : Recherche locale automatique | U62: — | V62: ACQ-06.11 | W62: Mode : Importée → Demandée (le dirigeant la saisit) · Format de réponse · Libellé (« Donnée »)
A63: ACQ-06.07 | B63: ACQ-06 | C63: =IFERROR(INDEX(Thèmes!$D$2:$D$190,MATCH(B63,Thèmes!$A$2:$A$190,0)),"") | D63: A07 · Votre présence en ligne | E63: Visites du site par mois — partagée avec COM-13.01 | F63: Nombre | G63: Demandée | H63: Essentiel | I63: D03 · si « site » est coché | J63: Période adaptée : depuis la création si moins de 3 mois | K63: ● | L63: ● | N63: ● | O63: ● | P63: ● | Q63: ● | R63: ● | S63: Parcours | T63: Saisie par le dirigeant tant qu'aucune connexion n'existe. Quand la connexion existera : Statistiques du site si connecté | U63: — | V63: ACQ-06.09, COM-13.07, COM-13.08, COM-13.09 | W63: Mode : Importée → Demandée (le dirigeant la saisit) · Libellé (« Donnée »)
A64: ACQ-06.08 | B64: ACQ-06 | C64: =IFERROR(INDEX(Thèmes!$D$2:$D$190,MATCH(B64,Thèmes!$A$2:$A$190,0)),"") | D64: A07 · Votre présence en ligne | E64: Note et nombre d'avis sur votre plateforme principale (TheFork, Doctolib, Trustpilot, marketplace…) | F64: Nombre et note | G64: Demandée | H64: Essentiel | I64: D03 · si « plateformes » est coché | J64: — | K64: ● | M64: ● | N64: ● | R64: ● | S64: Cible | T64: — | U64: — | V64: XA43
A65: ACQ-06.09 | B65: ACQ-06 | C65: =IFERROR(INDEX(Thèmes!$D$2:$D$190,MATCH(B65,Thèmes!$A$2:$A$190,0)),"") | D65: — | E65: Part des visites du site qui deviennent une demande | F65: % | G65: Calculée | H65: — | I65: — | J65: — | K65: ● | L65: ● | N65: ● | O65: ● | P65: ● | Q65: ● | R65: ● | S65: Levier | T65: Demandes du canal « site » (détail par type à l'écran site de l'agent Comm) ÷ visites du site. Seul calcul de ce taux, relu par l'agent Comm (COM-13) | U65: ACQ-03.02, ACQ-06.07 | V65: COM-13.08, XC08, DC07
A66: ACQ-06.10 | B66: ACQ-06 | C66: =IFERROR(INDEX(Thèmes!$D$2:$D$190,MATCH(B66,Thèmes!$A$2:$A$190,0)),"") | D66: — | E66: Part des vues de la fiche qui deviennent une action | F66: % | G66: Calculée | H66: — | I66: — | J66: — | K66: ● | L66: ● | N66: ● | O66: ● | P66: ● | Q66: ● | R66: ● | S66: Levier | T66: Actions ÷ vues | U66: ACQ-06.04, ACQ-06.05 | V66: Affichée dans le rapport
A67: ACQ-06.11 | B67: ACQ-06 | C67: =IFERROR(INDEX(Thèmes!$D$2:$D$190,MATCH(B67,Thèmes!$A$2:$A$190,0)),"") | D67: — | E67: Écart d'avis et de note avec les concurrents | F67: Nombre et note | G67: Calculée | H67: — | I67: — | J67: — | K67: ● | L67: ● | N67: ● | O67: ● | P67: ● | Q67: ● | R67: ● | S67: Cible | T67: Vos avis et votre note − ceux des concurrents | U67: ACQ-06.01, ACQ-06.02, ACQ-06.06 | V67: XA43
A68: ACQ-06.12 | B68: ACQ-06 | C68: =IFERROR(INDEX(Thèmes!$D$2:$D$190,MATCH(B68,Thèmes!$A$2:$A$190,0)),"") | D68: — | E68: Actions possibles directement depuis la fiche Google — explique un faible passage des vues aux contacts (taux calculé avec ACQ-06.04) | F68: Cases à cocher | G68: Demandée | H68: Approfondi | I68: D03 · si « fiche Google » est cochée | J68: — | K68: ● | L68: ● | N68: ● | O68: ● | P68: ● | Q68: ● | R68: ● | S68: — | T68: — | U68: — | V68: — | W68: Nouveau
A69: ACQ-06.13 | B69: ACQ-06 | C69: =IFERROR(INDEX(Thèmes!$D$2:$D$190,MATCH(B69,Thèmes!$A$2:$A$190,0)),"") | D69: — | E69: Mots tapés sur Google pour trouver la fiche, avec leur nombre de recherches sur 3 mois — montre si l'entreprise est trouvée sur ses prestations qui rapportent le plus ; repris aussi par l'agent de création (sujets de contenus) | F69: Tableau : Nombre de recherches (lignes libre: 5) | G69: Demandée | H69: Approfondi | I69: D03 · si « fiche Google » est cochée | J69: Période adaptée : depuis la création si moins de 3 mois | K69: ● | L69: ● | N69: ● | O69: ● | P69: ● | Q69: ● | R69: ● | S69: — | T69: — | U69: — | V69: — | W69: Nouveau
A70: ACQ-07.01 | B70: ACQ-07 | C70: =IFERROR(INDEX(Thèmes!$D$2:$D$190,MATCH(B70,Thèmes!$A$2:$A$190,0)),"") | D70: A08 · Votre budget marketing | E70: Agence ou prestataire marketing, par mois | F70: € | G70: Demandée | H70: Essentiel | I70: D04 · si publicité ou agence | J70: Aujourd'hui | K70: ● | L70: ● | M70: ● | N70: ● | O70: ● | P70: ● | Q70: ● | R70: ● | S70: Perte | T70: — | U70: — | V70: ACQ-07.06, COM-32.04
A71: ACQ-07.02 | B71: ACQ-07 | C71: =IFERROR(INDEX(Thèmes!$D$2:$D$190,MATCH(B71,Thèmes!$A$2:$A$190,0)),"") | D71: A08 · Votre budget marketing | E71: Taux de commission prélevé par chaque plateforme sur les ventes qu'elle apporte (TheFork, Uber Eats, Doctolib, marketplace…) | F71: % par plateforme | G71: Demandée | H71: Essentiel | I71: D03 · si « plateformes » est coché | J71: — | K71: ● | L71: ● | M71: ● | N71: ● | R71: ● | S71: Perte | T71: — | U71: — | V71: ACQ-07.07, ACQ-07.12, XA39
A72: ACQ-07.03 | B72: ACQ-07 | C72: =IFERROR(INDEX(Thèmes!$D$2:$D$190,MATCH(B72,Thèmes!$A$2:$A$190,0)),"") | D72: A08 · Votre budget marketing | E72: Création de contenu par mois : photographe, vidéaste, graphiste | F72: € | G72: Demandée | H72: Essentiel | I72: — | J72: Aujourd'hui | K72: ● | L72: ● | M72: ● | N72: ● | O72: ● | P72: ● | Q72: ● | R72: ● | S72: Levier | T72: — | U72: — | V72: ACQ-07.06, COM-32.04
A73: ACQ-07.04 | B73: ACQ-07 | C73: =IFERROR(INDEX(Thèmes!$D$2:$D$190,MATCH(B73,Thèmes!$A$2:$A$190,0)),"") | D73: A08 · Votre budget marketing | E73: Outils marketing par mois : emailing, logiciel de réservation ou de suivi, banque d'images (comptés ici, pas dans les abonnements de l'agent Finance) | F73: € | G73: Demandée | H73: Essentiel | I73: — | J73: Aujourd'hui | K73: ● | L73: ● | M73: ● | N73: ● | O73: ● | P73: ● | Q73: ● | R73: ● | S73: Perte | T73: — | U73: — | V73: ACQ-07.06, COM-32.04
A74: ACQ-07.05 | B74: ACQ-07 | C74: =IFERROR(INDEX(Thèmes!$D$2:$D$190,MATCH(B74,Thèmes!$A$2:$A$190,0)),"") | D74: A08 · Votre budget marketing | E74: Budget marketing total il y a 12 mois, même périmètre qu'aujourd'hui : publicité, agence, contenu, outils (hors commissions) — partagée avec Comm (COM-32.07) : posée par le premier agent qui en a besoin | F74: € | G74: Demandée | H74: Approfondi | I74: D04 · si publicité ou agence | J74: Il y a 12 mois (masquée avant 12 mois d'existence) | K74: ● | L74: ● | M74: ● | N74: ● | O74: ● | P74: ● | Q74: ● | R74: ● | S74: Problème | T74: — | U74: — | V74: ACQ-07.14 | W74: Libellé (« Donnée »)
A75: ACQ-07.06 | B75: ACQ-07 | C75: =IFERROR(INDEX(Thèmes!$D$2:$D$190,MATCH(B75,Thèmes!$A$2:$A$190,0)),"") | D75: — | E75: Budget marketing total par mois, hors commissions | F75: € | G75: Calculée | H75: — | I75: — | J75: — | K75: ● | L75: ● | M75: ● | N75: ● | O75: ● | P75: ● | Q75: ● | R75: ● | S75: Mesure | T75: Dépenses par canal + agence + contenu + outils. Les commissions, proportionnelles aux ventes, sont comptées à part, en charges variables | U75: ACQ-03.05, ACQ-07.01, ACQ-07.03, ACQ-07.04 | V75: ACQ-07.08, ACQ-07.09, ACQ-07.10, ACQ-07.11, ACQ-07.13, ACQ-07.14
A76: ACQ-07.07 | B76: ACQ-07 | C76: =IFERROR(INDEX(Thèmes!$D$2:$D$190,MATCH(B76,Thèmes!$A$2:$A$190,0)),"") | D76: — | E76: Commissions versées aux plateformes par mois | F76: € | G76: Calculée | H76: — | I76: — | J76: — | K76: ● | L76: ● | M76: ● | N76: ● | R76: ● | S76: Perte | T76: Taux de commission × CA du canal « plateformes ». Charge variable (agent Finance), jamais ajoutée au budget marketing | U76: ACQ-07.02, ACQ-03.04, Inscription · CA mensuel | V76: ACQ-03.09, ACQ-03.10, ACQ-03.11, ACQ-07.11, ACQ-07.13, FIN-06.05
A77: ACQ-07.08 | B77: ACQ-07 | C77: =IFERROR(INDEX(Thèmes!$D$2:$D$190,MATCH(B77,Thèmes!$A$2:$A$190,0)),"") | D77: — | E77: Budget marketing rapporté au CA | F77: % | G77: Calculée | H77: — | I77: — | J77: — | K77: ● | L77: ● | M77: ● | N77: ● | O77: ● | P77: ● | Q77: ● | R77: ● | S77: Cible | T77: Budget total ÷ CA mensuel | U77: ACQ-07.06, Inscription · CA mensuel | V77: Affichée dans le rapport
A78: ACQ-07.09 | B78: ACQ-07 | C78: =IFERROR(INDEX(Thèmes!$D$2:$D$190,MATCH(B78,Thèmes!$A$2:$A$190,0)),"") | D78: — | E78: Coût par demande | F78: € | G78: Calculée | H78: — | I78: — | J78: — | K78: ● | L78: ● | M78: ● | N78: ● | O78: ● | P78: ● | Q78: ● | R78: ● | S78: Levier | T78: Budget total ÷ demandes reçues | U78: ACQ-07.06, ACQ-02.01 | V78: Affichée dans le rapport
A79: ACQ-07.10 | B79: ACQ-07 | C79: =IFERROR(INDEX(Thèmes!$D$2:$D$190,MATCH(B79,Thèmes!$A$2:$A$190,0)),"") | D79: — | E79: Coût par rendez-vous | F79: € | G79: Calculée | H79: — | I79: — | J79: — | K79: ● | O79: ● | P79: ● | S79: Levier | T79: Budget total ÷ rendez-vous obtenus | U79: ACQ-07.06, ACQ-09.01 | V79: Affichée dans le rapport
A80: ACQ-07.11 | B80: ACQ-07 | C80: =IFERROR(INDEX(Thèmes!$D$2:$D$190,MATCH(B80,Thèmes!$A$2:$A$190,0)),"") | D80: — | E80: Coût d'acquisition d'un client (global) | F80: € | G80: Calculée | H80: — | I80: — | J80: — | K80: ● | M80: ● | O80: ● | P80: ● | Q80: ● | S80: Perte | T80: (Budget total + commissions) ÷ nouveaux clients du mois | U80: ACQ-07.06, ACQ-07.07, ACQ-11.01 | V80: ACQ-18.05, FIN-32.01, XA18, XF48
A81: ACQ-07.12 | B81: ACQ-07 | C81: =IFERROR(INDEX(Thèmes!$D$2:$D$190,MATCH(B81,Thèmes!$A$2:$A$190,0)),"") | D81: — | E81: CA venant des canaux payants | F81: € | G81: Calculée | H81: — | I81: — | J81: — | K81: ● | L81: ● | M81: ● | N81: ● | O81: ● | P81: ● | Q81: ● | R81: ● | S81: Mesure | T81: Somme du CA des canaux qui ont une dépense ou une commission | U81: ACQ-03.04, ACQ-03.05, ACQ-07.02, Inscription · CA mensuel | V81: ACQ-07.13
A82: ACQ-07.13 | B82: ACQ-07 | C82: =IFERROR(INDEX(Thèmes!$D$2:$D$190,MATCH(B82,Thèmes!$A$2:$A$190,0)),"") | D82: — | E82: Rendement global du marketing | F82: Ratio | G82: Calculée | H82: — | I82: — | J82: — | K82: ● | L82: ● | M82: ● | N82: ● | O82: ● | P82: ● | Q82: ● | R82: ● | S82: Levier | T82: CA des canaux payants ÷ (budget total + commissions) | U82: ACQ-07.12, ACQ-07.06, ACQ-07.07 | V82: Affichée dans le rapport
A83: ACQ-07.14 | B83: ACQ-07 | C83: =IFERROR(INDEX(Thèmes!$D$2:$D$190,MATCH(B83,Thèmes!$A$2:$A$190,0)),"") | D83: — | E83: Évolution du budget comparée à celle des nouveaux clients | F83: % | G83: Calculée | H83: — | I83: — | J83: — | K83: ● | M83: ● | O83: ● | P83: ● | Q83: ● | S83: Problème | T83: Budget marketing par mois aujourd'hui (ACQ-07.06) comparé au budget d'il y a 12 mois (ACQ-07.05, même périmètre), à côté de l'évolution des nouveaux clients (ACQ-11.18) : deux chiffres, sans conclusion automatique. | U83: ACQ-07.06, ACQ-07.05, ACQ-11.18 | V83: Affichée dans le rapport
A84: ACQ-07.15 | B84: ACQ-07 | C84: =IFERROR(INDEX(Thèmes!$D$2:$D$190,MATCH(B84,Thèmes!$A$2:$A$190,0)),"") | D84: A08 · Votre budget marketing | E84: Parmi les clients venus par une plateforme, quelle part revient ensuite vous voir sans passer par elle ? | F84: % | G84: Demandée | H84: Approfondi | I84: D03 · si « plateformes » est coché | J84: — | K84: ● | L84: ● | M84: ● | N84: ● | R84: ● | S84: — | T84: — | U84: — | V84: Lue par l'IA pour adapter le conseil | W84: Nouveau : profils et condition proposés, à valider
A85: ACQ-08.01 | B85: ACQ-08 | C85: =IFERROR(INDEX(Thèmes!$D$2:$D$190,MATCH(B85,Thèmes!$A$2:$A$190,0)),"") | D85: A09 · Votre réactivité | E85: Répartition de vos réponses à toutes les demandes — appels décrochés, emails, formulaires, messages : moins de 5 min, moins d'1 h, moins de 24 h, plus d'un jour, jamais (les appels manqués sont comptés juste après) | F85: Tranches en % | G85: Demandée | H85: Essentiel | I85: — | J85: — | K85: ● | L85: ● | M85: ● | N85: ● | O85: ● | P85: ● | Q85: ● | R85: ● | S85: Problème, Perte | T85: — | U85: — | V85: ACQ-08.07, ACQ-08.08
A86: ACQ-08.02 | B86: ACQ-08 | C86: =IFERROR(INDEX(Thèmes!$D$2:$D$190,MATCH(B86,Thèmes!$A$2:$A$190,0)),"") | D86: A09 · Votre réactivité | E86: Appels manqués par semaine — déclencheur D37 | F86: Nombre | G86: Demandée | H86: Essentiel | I86: — | J86: — | K86: ● | L86: ● | N86: ● | O86: ● | P86: ● | Q86: ● | R86: ● | S86: Perte | T86: — | U86: — | V86: ACQ-08.09 | W86: Libellé (« Donnée »)
A87: ACQ-08.03 | B87: ACQ-08 | C87: =IFERROR(INDEX(Thèmes!$D$2:$D$190,MATCH(B87,Thèmes!$A$2:$A$190,0)),"") | D87: A09 · Votre réactivité | E87: Part des appels manqués que vous rappelez | F87: % | G87: Demandée | H87: Essentiel | I87: D37 · si vous manquez des appels | J87: — | K87: ● | L87: ● | N87: ● | O87: ● | P87: ● | Q87: ● | R87: ● | S87: Perte | T87: — | U87: — | V87: ACQ-08.09 | W87: Condition d'affichage
A88: ACQ-08.04 | B88: ACQ-08 | C88: =IFERROR(INDEX(Thèmes!$D$2:$D$190,MATCH(B88,Thèmes!$A$2:$A$190,0)),"") | D88: A09 · Votre réactivité | E88: Canal sur lequel vous répondez le plus lentement : téléphone, email, formulaire, messages | F88: Choix | G88: Demandée | H88: Approfondi | I88: — | J88: — | K88: ● | L88: ● | M88: ● | N88: ● | O88: ● | P88: ● | Q88: ● | R88: ● | S88: Levier | T88: — | U88: — | V88: Lue par l'IA pour adapter le conseil
A89: ACQ-08.05 | B89: ACQ-08 | C89: =IFERROR(INDEX(Thèmes!$D$2:$D$190,MATCH(B89,Thèmes!$A$2:$A$190,0)),"") | D89: A09 · Votre réactivité | E89: Délai de réponse à une demande reçue hors horaires : dans l'heure, le lendemain, plus tard | F89: Choix | G89: Demandée | H89: Approfondi | I89: — | J89: — | K89: ● | L89: ● | M89: ● | N89: ● | O89: ● | P89: ● | Q89: ● | R89: ● | S89: Problème | T89: — | U89: — | V89: XA41
A90: ACQ-08.06 | B90: ACQ-08 | C90: =IFERROR(INDEX(Thèmes!$D$2:$D$190,MATCH(B90,Thèmes!$A$2:$A$190,0)),"") | D90: A09 · Votre réactivité | E90: Taux de transformation selon le délai de réponse | F90: % | G90: Importée | H90: Approfondi | I90: — | J90: — | K90: ● | L90: ● | M90: ● | N90: ● | O90: ● | P90: ● | Q90: ● | R90: ● | S90: Levier | T90: Disponible seulement si un outil de suivi des contacts est connecté ; jamais demandé au dirigeant | U90: — | V90: Lue par l'IA pour adapter le conseil
A91: ACQ-08.07 | B91: ACQ-08 | C91: =IFERROR(INDEX(Thèmes!$D$2:$D$190,MATCH(B91,Thèmes!$A$2:$A$190,0)),"") | D91: — | E91: Délai médian de réponse | F91: Tranche | G91: Calculée | H91: — | I91: — | J91: — | K91: ● | L91: ● | M91: ● | N91: ● | O91: ● | P91: ● | Q91: ● | R91: ● | S91: Cible | T91: Tranche dans laquelle on atteint 50 % des réponses | U91: ACQ-08.01 | V91: Affichée dans le rapport
A92: ACQ-08.08 | B92: ACQ-08 | C92: =IFERROR(INDEX(Thèmes!$D$2:$D$190,MATCH(B92,Thèmes!$A$2:$A$190,0)),"") | D92: — | E92: Demandes restées sans réponse par mois | F92: Nombre | G92: Calculée | H92: — | I92: — | J92: — | K92: ● | L92: ● | M92: ● | N92: ● | O92: ● | P92: ● | Q92: ● | R92: ● | S92: Perte | T92: Demandes reçues × part « jamais » | U92: ACQ-02.01, ACQ-08.01 | V92: ACQ-08.09
A93: ACQ-08.09 | B93: ACQ-08 | C93: =IFERROR(INDEX(Thèmes!$D$2:$D$190,MATCH(B93,Thèmes!$A$2:$A$190,0)),"") | D93: — | E93: CA perdu par an sur les demandes sans réponse et les appels non rappelés | F93: € | G93: Calculée | H93: — | I93: — | J93: — | K93: ● | L93: ● | M93: ● | N93: ● | O93: ● | P93: ● | Q93: ● | S93: Perte | T93: (Demandes sans réponse + appels non rappelés × 4,33) × valeur d'une demande × 12 | U93: ACQ-08.08, ACQ-08.02, ACQ-08.03, ACQ-02.09 | V93: XA04
A94: ACQ-09.01 | B94: ACQ-09 | C94: =IFERROR(INDEX(Thèmes!$D$2:$D$190,MATCH(B94,Thèmes!$A$2:$A$190,0)),"") | D94: A10 · Vos rendez-vous | E94: Rendez-vous obtenus par mois | F94: Nombre | G94: Demandée | H94: Essentiel | I94: D05 · si activité sur rendez-vous | J94: — | K94: ● | O94: ● | P94: ● | S94: Parcours | T94: — | U94: — | V94: ACQ-02.08, ACQ-07.10, ACQ-09.08, ACQ-09.09, ACQ-09.10
A95: ACQ-09.02 | B95: ACQ-09 | C95: =IFERROR(INDEX(Thèmes!$D$2:$D$190,MATCH(B95,Thèmes!$A$2:$A$190,0)),"") | D95: A10 · Vos rendez-vous | E95: Rendez-vous annulés avec prévenance et absences sans prévenir, par mois (regroupe les anciennes ACQ-09.02 et ACQ-09.03) | F95: Plusieurs champs : Annulés en vous prévenant · Absents sans prévenir | G95: Demandée | H95: Essentiel | I95: D05 · si activité sur rendez-vous | J95: — | K95: ● | O95: ● | P95: ● | S95: Perte | T95: — | U95: — | V95: ACQ-09.08 | W95: Format de réponse (la banque l'emporte) · Libellé (« Donnée »)
A96: ACQ-09.03 | B96: ACQ-09 | C96: =IFERROR(INDEX(Thèmes!$D$2:$D$190,MATCH(B96,Thèmes!$A$2:$A$190,0)),"") | D96: A10 · Vos rendez-vous | E96: Absences sans prévenir par mois | F96: Nombre | G96: Calculée | H96: — | I96: D05 · si activité sur rendez-vous | J96: — | K96: ● | O96: ● | P96: ● | S96: Perte | T96: Lue dans la réponse à ACQ-09.02 (champ « Absents sans prévenir ») | U96: ACQ-09.02 | V96: ACQ-09.08, ACQ-09.10, ACQ-09.13 | W96: Mode : Calculée (plus de question : la banque la lit dans une autre réponse)
A97: ACQ-09.05 | B97: ACQ-09 | C97: =IFERROR(INDEX(Thèmes!$D$2:$D$190,MATCH(B97,Thèmes!$A$2:$A$190,0)),"") | D97: A10 · Vos rendez-vous | E97: Rendez-vous nécessaires pour signer un client | F97: Nombre | G97: Demandée | H97: Essentiel | I97: D05 · si activité sur rendez-vous | J97: — | O97: ● | P97: ● | S97: Parcours | T97: — | U97: — | V97: Notée directement (couleur du thème)
A98: ACQ-09.06 | B98: ACQ-09 | C98: =IFERROR(INDEX(Thèmes!$D$2:$D$190,MATCH(B98,Thèmes!$A$2:$A$190,0)),"") | D98: A10 · Vos rendez-vous | E98: Rappel envoyé la veille du rendez-vous | F98: Toujours / parfois / jamais | G98: Demandée | H98: Approfondi | I98: D05 · si activité sur rendez-vous | J98: — | K98: ● | O98: ● | P98: ● | S98: Levier | T98: — | U98: — | V98: Notée directement (couleur du thème)
A99: ACQ-09.07 | B99: ACQ-09 | C99: =IFERROR(INDEX(Thèmes!$D$2:$D$190,MATCH(B99,Thèmes!$A$2:$A$190,0)),"") | D99: A10 · Vos rendez-vous | E99: Part des rendez-vous pris en ligne | F99: % | G99: Demandée | H99: Approfondi | I99: D05 · si activité sur rendez-vous | J99: — | K99: ● | S99: Levier | T99: — | U99: — | V99: XA41
A100: ACQ-09.08 | B100: ACQ-09 | C100: =IFERROR(INDEX(Thèmes!$D$2:$D$190,MATCH(B100,Thèmes!$A$2:$A$190,0)),"") | D100: — | E100: Rendez-vous honorés | F100: Nombre | G100: Calculée | H100: — | I100: — | J100: — | K100: ● | O100: ● | P100: ● | S100: Mesure | T100: Obtenus − annulations − absences | U100: ACQ-09.01, ACQ-09.02, ACQ-09.03 | V100: ACQ-09.09, ACQ-09.11, ACQ-09.12
...

Sheet Finance — données
A1: Code | B1: Thème | C1: Nom du thème | D1: Écran | E1: Donnée | F1: Format de réponse | G1: Mode | H1: Niveau | I1: Condition d'affichage | J1: Période (selon l'ancienneté) | K1: RDV | L1: Commerce | M1: E-commerce | N1: Restaurant | O1: Chantier | P1: B2B | Q1: Abonnement | R1: Location | S1: Sert à | T1: Calcul ou source | U1: Données utilisées | V1: Utilisée dans | W1: Changement du 20 oct.
A2: FIN-01.01 | B2: FIN-01 | C2: =IFERROR(INDEX(Thèmes!$D$2:$D$190,MATCH(B2,Thèmes!$A$2:$A$190,0)),"") | D2: A14 · Vos prix et remises | E2: Prix de vos 3 offres principales | F2: € (3 lignes) | G2: Partagée | H2: Essentiel | I2: — | J2: — | K2: ● | L2: ● | M2: ● | N2: ● | O2: ● | P2: ● | Q2: ● | R2: ● | S2: Cible | T2: Posée une seule fois, par le premier agent souscrit qui en a besoin (ACQ-13.01), sinon ici | U2: ACQ-13.01 | V2: FIN-01.04, FIN-03.03
A3: FIN-01.02 | B3: FIN-01 | C3: =IFERROR(INDEX(Thèmes!$D$2:$D$190,MATCH(B3,Thèmes!$A$2:$A$190,0)),"") | D3: A14 · Vos prix et remises | E3: Part du CA de chacune de ces offres | F3: % (3 lignes) | G3: Partagée | H3: Essentiel | I3: — | J3: — | K3: ● | L3: ● | M3: ● | N3: ● | O3: ● | P3: ● | Q3: ● | R3: ● | S3: Levier | T3: Posée une seule fois, par le premier agent souscrit qui en a besoin (ACQ-13.02), sinon ici | U3: ACQ-13.02 | V3: FIN-01.06, XF34
A4: FIN-01.03 | B4: FIN-01 | C4: =IFERROR(INDEX(Thèmes!$D$2:$D$190,MATCH(B4,Thèmes!$A$2:$A$190,0)),"") | D4: F06 · Vos marges (tableau par offre) | E4: Coût direct de chacune de ces 3 offres (matières ou marchandises, sous-traitance, temps passé) — mot adapté au métier : voir Lexique | F4: € (3 lignes) | G4: Demandée | H4: Essentiel | I4: — | J4: — | K4: ● | L4: ● | M4: ● | N4: ● | O4: ● | P4: ● | Q4: ● | R4: ● | S4: Levier | T4: — | U4: — | V4: FIN-01.04, FIN-03.02
A5: FIN-01.04 | B5: FIN-01 | C5: =IFERROR(INDEX(Thèmes!$D$2:$D$190,MATCH(B5,Thèmes!$A$2:$A$190,0)),"") | D5: — | E5: Marge par offre, en € et en % | F5: € et % | G5: Calculée | H5: — | I5: — | J5: — | K5: ● | L5: ● | M5: ● | N5: ● | O5: ● | P5: ● | Q5: ● | R5: ● | S5: Levier | T5: Prix − coût direct, puis ÷ prix | U5: ACQ-13.01, FIN-01.03 | V5: FIN-01.05, FIN-01.06, XF34
A6: FIN-01.05 | B6: FIN-01 | C6: =IFERROR(INDEX(Thèmes!$D$2:$D$190,MATCH(B6,Thèmes!$A$2:$A$190,0)),"") | D6: — | E6: Écart de marge entre l'offre la plus et la moins rentable | F6: Points de % | G6: Calculée | H6: — | I6: — | J6: — | K6: ● | L6: ● | M6: ● | N6: ● | O6: ● | P6: ● | Q6: ● | R6: ● | S6: Problème | T6: Marge la plus haute − marge la plus basse | U6: FIN-01.04 | V6: Affichée dans le rapport
A7: FIN-01.06 | B7: FIN-01 | C7: =IFERROR(INDEX(Thèmes!$D$2:$D$190,MATCH(B7,Thèmes!$A$2:$A$190,0)),"") | D7: — | E7: Marge moyenne pondérée par le poids de chaque offre dans le CA | F7: % | G7: Calculée | H7: — | I7: — | J7: — | K7: ● | L7: ● | M7: ● | N7: ● | O7: ● | P7: ● | Q7: ● | R7: ● | S7: Mesure | T7: Somme (marge de l'offre × part du CA de l'offre) | U7: FIN-01.04, ACQ-13.02 | V7: XF34
A8: FIN-02.01 | B8: FIN-02 | C8: =IFERROR(INDEX(Thèmes!$D$2:$D$190,MATCH(B8,Thèmes!$A$2:$A$190,0)),"") | D8: A16 · Vos plus gros clients (tableau) | E8: Temps passé par mois sur chacun de vos 5 plus gros clients (colonne ajoutée au tableau des gros clients) | F8: Heures (5 lignes) | G8: Demandée | H8: Essentiel | I8: D15 · si clients professionnels réguliers | J8: — | P8: ● | Q8: ● | S8: Levier | T8: — | U8: — | V8: FIN-02.02
A9: FIN-02.02 | B9: FIN-02 | C9: =IFERROR(INDEX(Thèmes!$D$2:$D$190,MATCH(B9,Thèmes!$A$2:$A$190,0)),"") | D9: — | E9: Marge réelle de chacun des 5 plus gros clients | F9: € | G9: Calculée | H9: — | I9: — | J9: — | P9: ● | Q9: ● | S9: Levier | T9: CA mensuel du client − heures passées × coût d'une heure de travail | U9: ACQ-16.01, FIN-02.01, FIN-07.12 | V9: FIN-02.03, XF36
A10: FIN-02.03 | B10: FIN-02 | C10: =IFERROR(INDEX(Thèmes!$D$2:$D$190,MATCH(B10,Thèmes!$A$2:$A$190,0)),"") | D10: — | E10: Clients dont la marge réelle est faible ou négative | F10: Liste | G10: Calculée | H10: — | I10: — | J10: — | P10: ● | Q10: ● | S10: Perte | T10: Clients dont la marge réelle est inférieure à la marge moyenne de l'entreprise | U10: FIN-02.02, FIN-06.08 | V10: XF36
A11: FIN-03.01 | B11: FIN-03 | C11: =IFERROR(INDEX(Thèmes!$D$2:$D$190,MATCH(B11,Thèmes!$A$2:$A$190,0)),"") | D11: F06 · Vos marges (tableau par offre) | E11: Connaissez-vous le coût complet de votre offre principale (y compris sa part de loyer, salaires, frais) ? | F11: Oui chiffré / estimation / non | G11: Demandée | H11: Essentiel | I11: — | J11: — | K11: ● | L11: ● | M11: ● | N11: ● | O11: ● | P11: ● | Q11: ● | R11: ● | S11: Problème | T11: — | U11: — | V11: Notée directement (couleur du thème)
A12: FIN-03.02 | B12: FIN-03 | C12: =IFERROR(INDEX(Thèmes!$D$2:$D$190,MATCH(B12,Thèmes!$A$2:$A$190,0)),"") | D12: — | E12: Coût complet de chaque offre | F12: € | G12: Calculée | H12: — | I12: — | J12: — | K12: ● | L12: ● | M12: ● | N12: ● | O12: ● | P12: ● | Q12: ● | R12: ● | S12: Levier | T12: Coût direct + charges fixes mensuelles ÷ ventes du mois | U12: FIN-01.03, FIN-05.08, FIN-06.02 | V12: FIN-03.03, XF35
A13: FIN-03.03 | B13: FIN-03 | C13: =IFERROR(INDEX(Thèmes!$D$2:$D$190,MATCH(B13,Thèmes!$A$2:$A$190,0)),"") | D13: — | E13: Offres vendues sous leur coût complet | F13: Liste | G13: Calculée | H13: — | I13: — | J13: — | K13: ● | L13: ● | M13: ● | N13: ● | O13: ● | P13: ● | Q13: ● | R13: ● | S13: Perte | T13: Offres dont le prix est inférieur au coût complet | U13: ACQ-13.01, FIN-03.02 | V13: XF35
A14: FIN-04.01 | B14: FIN-04 | C14: =IFERROR(INDEX(Thèmes!$D$2:$D$190,MATCH(B14,Thèmes!$A$2:$A$190,0)),"") | D14: A14 · Vos prix et remises | E14: Date et ampleur de votre dernière hausse de prix | F14: Mois et % | G14: Partagée | H14: Essentiel | I14: — | J14: — | K14: ● | L14: ● | M14: ● | N14: ● | O14: ● | P14: ● | Q14: ● | R14: ● | S14: Problème | T14: Posée une seule fois, par le premier agent souscrit qui en a besoin (ACQ-13.04, ACQ-13.06), sinon ici | U14: ACQ-13.04, ACQ-13.06 | V14: XF09, FIN-04.04
A15: FIN-04.02 | B15: FIN-04 | C15: =IFERROR(INDEX(Thèmes!$D$2:$D$190,MATCH(B15,Thèmes!$A$2:$A$190,0)),"") | D15: — | E15: Taux de marge sur coûts variables il y a 12 mois | F15: % | G15: Calculée | H15: — | I15: — | J15: — | K15: ● | L15: ● | M15: ● | N15: ● | O15: ● | P15: ● | Q15: ● | R15: ● | S15: Problème | T15: (CA des mêmes 3 mois un an plus tôt − 3 × charges variables par mois de ces mois) ÷ CA de ces 3 mois. Avant : le CA d'un seul mois, 11 mois avant le dernier, avec les charges d'une autre période. | U15: FIN-14.03, FIN-06.03 | V15: FIN-04.03
A16: FIN-04.03 | B16: FIN-04 | C16: =IFERROR(INDEX(Thèmes!$D$2:$D$190,MATCH(B16,Thèmes!$A$2:$A$190,0)),"") | D16: — | E16: Évolution de la marge sur 12 mois | F16: Points de % | G16: Calculée | H16: — | I16: — | J16: — | K16: ● | L16: ● | M16: ● | N16: ● | O16: ● | P16: ● | Q16: ● | R16: ● | S16: Problème | T16: Taux de marge des 3 derniers mois (CA de FIN-14.01, charges variables FIN-06.05) − taux de marge des mêmes 3 mois un an plus tôt (FIN-04.02), en points de pourcentage. | U16: FIN-14.01, FIN-06.05, FIN-04.02, FIN-14.04 | V16: Affichée dans le rapport
A17: FIN-04.04 | B17: FIN-04 | C17: =IFERROR(INDEX(Thèmes!$D$2:$D$190,MATCH(B17,Thèmes!$A$2:$A$190,0)),"") | D17: — | E17: Hausse de coûts non répercutée dans les prix | F17: € par an | G17: Calculée | H17: — | I17: — | J17: — | K17: ● | L17: ● | M17: ● | N17: ● | O17: ● | P17: ● | Q17: ● | R17: ● | S17: Perte | T17: (Hausse des achats et des charges sur 12 mois − hausse de prix appliquée) en € | U17: FIN-08.11, FIN-05.10, FIN-07.15, ACQ-13.06 | V17: XF09
A18: FIN-05.01 | B18: FIN-05 | C18: =IFERROR(INDEX(Thèmes!$D$2:$D$190,MATCH(B18,Thèmes!$A$2:$A$190,0)),"") | D18: F01 · Vos charges fixes (tableau par poste) | E18: Charges fixes par mois, par poste : loyer, énergie, assurances, véhicules (carburant, entretien ; le leasing est déclaré avec les crédits), frais bancaires (hors agios), honoraires (comptable, avocat), rémunération du dirigeant, autres. Repris d'autres écrans, à ne pas recompter ici : abonnements et contrats (télécoms compris), masse salariale, budget marketing et communication | F18: Tableau par poste (€) | G18: Demandée | H18: Essentiel | I18: — | J18: Aujourd'hui | K18: ● | L18: ● | M18: ● | N18: ● | O18: ● | P18: ● | Q18: ● | R18: ● | S18: Perte, Levier | T18: — | U18: — | V18: FIN-05.08, XF03, XF06, XF38
A19: FIN-05.02 | B19: FIN-05 | C19: =IFERROR(INDEX(Thèmes!$D$2:$D$190,MATCH(B19,Thèmes!$A$2:$A$190,0)),"") | D19: A08 · Votre budget marketing | E19: Budget marketing et communication par mois, hors commissions sur ventes : publicité, agence, création de contenu, outils marketing, community manager, impression | F19: € | G19: Partagée | H19: Essentiel | I19: Pas posée si les agents Acquisition et Comm sont faits : calculée | J19: — | K19: ● | L19: ● | M19: ● | N19: ● | O19: ● | P19: ● | Q19: ● | R19: ● | S19: Perte, Levier | T19: Posée une seule fois, par le premier agent souscrit qui en a besoin (ACQ-07.06, COM-32.02), sinon ici | U19: ACQ-07.06, COM-32.02 | V19: FIN-05.08 | W19: Condition d'affichage
A20: FIN-05.03 | B20: FIN-05 | C20: =IFERROR(INDEX(Thèmes!$D$2:$D$190,MATCH(B20,Thèmes!$A$2:$A$190,0)),"") | D20: F01 · Vos charges fixes (tableau par poste) | E20: Total des charges fixes il y a 12 mois | F20: € | G20: Demandée | H20: Essentiel | I20: — | J20: Il y a 12 mois (masquée avant 12 mois d'existence) | K20: ● | L20: ● | M20: ● | N20: ● | O20: ● | P20: ● | Q20: ● | R20: ● | S20: Problème | T20: — | U20: — | V20: FIN-05.10
A21: FIN-05.04 | B21: FIN-05 | C21: =IFERROR(INDEX(Thèmes!$D$2:$D$190,MATCH(B21,Thèmes!$A$2:$A$190,0)),"") | D21: F01 · Vos charges fixes (tableau par poste) | E21: Résultat de la dernière année : bénéfice ou perte | F21: € | G21: Demandée | H21: Essentiel | I21: D31 · sauf micro-entreprise | J21: Si un premier exercice est clos (sinon masquée) | K21: ● | L21: ● | M21: ● | N21: ● | O21: ● | P21: ● | Q21: ● | R21: ● | S21: Mesure | T21: — | U21: — | V21: FIN-05.15, FIN-12.07 | W21: Condition d'affichage
A22: FIN-05.05 | B22: FIN-05 | C22: =IFERROR(INDEX(Thèmes!$D$2:$D$190,MATCH(B22,Thèmes!$A$2:$A$190,0)),"") | D22: F01 · Vos charges fixes (tableau par poste) | E22: Taux de marge que vous pensez faire | F22: % | G22: Demandée | H22: Essentiel | I22: — | J22: — | K22: ● | L22: ● | M22: ● | N22: ● | O22: ● | P22: ● | Q22: ● | R22: ● | S22: Problème | T22: — | U22: — | V22: FIN-05.16
A23: FIN-05.06 | B23: FIN-05 | C23: =IFERROR(INDEX(Thèmes!$D$2:$D$190,MATCH(B23,Thèmes!$A$2:$A$190,0)),"") | D23: F01 · Vos charges fixes (tableau par poste) | E23: Poste de charges qui a le plus augmenté sur 12 mois, et de combien | F23: Poste et € | G23: Demandée | H23: Approfondi | I23: — | J23: Période adaptée : depuis la création si moins de 12 mois | K23: ● | L23: ● | M23: ● | N23: ● | O23: ● | P23: ● | Q23: ● | R23: ● | S23: Levier | T23: — | U23: — | V23: XF06
A24: FIN-05.07 | B24: FIN-05 | C24: =IFERROR(INDEX(Thèmes!$D$2:$D$190,MATCH(B24,Thèmes!$A$2:$A$190,0)),"") | D24: A17 · Vos clients fidèles | E24: Revenu récurrent mensuel (abonnements) et nombre d'abonnés actifs | F24: € et nombre | G24: Partagée | H24: Essentiel | I24: — | J24: — | Q24: ● | S24: Mesure | T24: Posée une seule fois, par le premier agent souscrit qui en a besoin (ACQ-17.11, ACQ-17.10), sinon ici | U24: ACQ-17.11, ACQ-17.10 | V24: XF47
A25: FIN-05.08 | B25: FIN-05 | C25: =IFERROR(INDEX(Thèmes!$D$2:$D$190,MATCH(B25,Thèmes!$A$2:$A$190,0)),"") | D25: — | E25: Charges fixes totales par mois | F25: € | G25: Calculée | H25: — | I25: — | J25: — | K25: ● | L25: ● | M25: ● | N25: ● | O25: ● | P25: ● | Q25: ● | R25: ● | S25: Mesure | T25: Postes du tableau + abonnements et contrats + masse salariale + budget marketing et communication. Les commissions sur ventes sont des charges variables (FIN-06), jamais comptées ici | U25: FIN-05.01, FIN-09.05, FIN-07.01, FIN-05.02 | V25: FIN-03.02, FIN-05.09, FIN-05.10, FIN-05.11, FIN-05.12, FIN-11.05, FIN-11.06, FIN-13.04, FIN-14.02, FIN-15.03, FIN-23.02, FIN-31.01, XF04, XF33, XF47, S01, S05, S06, S10
A26: FIN-05.09 | B26: FIN-05 | C26: =IFERROR(INDEX(Thèmes!$D$2:$D$190,MATCH(B26,Thèmes!$A$2:$A$190,0)),"") | D26: — | E26: Charges fixes annuelles | F26: € | G26: Calculée | H26: — | I26: — | J26: — | K26: ● | L26: ● | M26: ● | N26: ● | O26: ● | P26: ● | Q26: ● | R26: ● | S26: Mesure | T26: Charges fixes mensuelles × 12 | U26: FIN-05.08 | V26: Affichée dans le rapport
A27: FIN-05.10 | B27: FIN-05 | C27: =IFERROR(INDEX(Thèmes!$D$2:$D$190,MATCH(B27,Thèmes!$A$2:$A$190,0)),"") | D27: — | E27: Évolution des charges fixes sur 12 mois | F27: € et % | G27: Calculée | H27: — | I27: — | J27: — | K27: ● | L27: ● | M27: ● | N27: ● | O27: ● | P27: ● | Q27: ● | R27: ● | S27: Problème | T27: Charges actuelles − charges il y a 12 mois, puis ÷ charges il y a 12 mois | U27: FIN-05.08, FIN-05.03 | V27: FIN-04.04, XF07
A28: FIN-05.11 | B28: FIN-05 | C28: =IFERROR(INDEX(Thèmes!$D$2:$D$190,MATCH(B28,Thèmes!$A$2:$A$190,0)),"") | D28: — | E28: Poids des charges fixes dans le CA | F28: % | G28: Calculée | H28: — | I28: — | J28: — | K28: ● | L28: ● | M28: ● | N28: ● | O28: ● | P28: ● | Q28: ● | R28: ● | S28: Cible | T28: Charges fixes ÷ CA mensuel | U28: FIN-05.08, Inscription · CA mensuel | V28: XF01, XF05
A29: FIN-05.12 | B29: FIN-05 | C29: =IFERROR(INDEX(Thèmes!$D$2:$D$190,MATCH(B29,Thèmes!$A$2:$A$190,0)),"") | D29: — | E29: Seuil de rentabilité mensuel | F29: € | G29: Calculée | H29: — | I29: — | J29: — | K29: ● | L29: ● | M29: ● | N29: ● | O29: ● | P29: ● | Q29: ● | R29: ● | S29: Cible | T29: Charges fixes ÷ taux de marge sur coûts variables | U29: FIN-05.08, FIN-06.08 | V29: FIN-05.13, XF01, XF03
A30: FIN-05.13 | B30: FIN-05 | C30: =IFERROR(INDEX(Thèmes!$D$2:$D$190,MATCH(B30,Thèmes!$A$2:$A$190,0)),"") | D30: — | E30: Marge de sécurité : CA au-dessus du seuil | F30: € et % | G30: Calculée | H30: — | I30: — | J30: — | K30: ● | L30: ● | M30: ● | N30: ● | O30: ● | P30: ● | Q30: ● | R30: ● | S30: Risque | T30: CA mensuel − seuil, puis ÷ CA mensuel | U30: Inscription · CA mensuel, FIN-05.12 | V30: XF02, XF38
A31: FIN-05.14 | B31: FIN-05 | C31: =IFERROR(INDEX(Thèmes!$D$2:$D$190,MATCH(B31,Thèmes!$A$2:$A$190,0)),"") | D31: — | E31: Marge moyenne par vente | F31: € | G31: Calculée | H31: — | I31: — | J31: — | K31: ● | L31: ● | M31: ● | N31: ● | O31: ● | P31: ● | Q31: ● | S31: Levier | T31: Panier moyen × taux de marge sur coûts variables | U31: ACQ-15.06, FIN-06.08 | V31: XF49
A32: FIN-05.15 | B32: FIN-05 | C32: =IFERROR(INDEX(Thèmes!$D$2:$D$190,MATCH(B32,Thèmes!$A$2:$A$190,0)),"") | D32: — | E32: Taux de marge nette | F32: % | G32: Calculée | H32: — | I32: — | J32: — | K32: ● | L32: ● | M32: ● | N32: ● | O32: ● | P32: ● | Q32: ● | R32: ● | S32: Mesure | T32: Résultat ÷ (CA mensuel × 12) | U32: FIN-05.04, Inscription · CA mensuel | V32: Affichée dans le rapport
A33: FIN-05.16 | B33: FIN-05 | C33: =IFERROR(INDEX(Thèmes!$D$2:$D$190,MATCH(B33,Thèmes!$A$2:$A$190,0)),"") | D33: — | E33: Écart entre la marge pensée et la marge réelle | F33: Points de % | G33: Calculée | H33: — | I33: — | J33: — | K33: ● | L33: ● | M33: ● | N33: ● | O33: ● | P33: ● | Q33: ● | R33: ● | S33: Problème | T33: Marge pensée − taux de marge calculé | U33: FIN-05.05, FIN-06.08 | V33: XF39
A34: FIN-06.01 | B34: FIN-06 | C34: =IFERROR(INDEX(Thèmes!$D$2:$D$190,MATCH(B34,Thèmes!$A$2:$A$190,0)),"") | D34: F02 · Vos charges variables (tableau par poste) | E34: Charges variables par mois, par poste : commissions (plateformes, apporteurs d'affaires), livraison, frais de paiement (carte, plateformes), consommables, intérim, extras et freelances. Achats et sous-traitance sont repris de l'écran fournisseurs ; les commissions des plateformes sont reprises du calcul de l'agent Acquisition s'il est souscrit | F34: Tableau par poste (€) | G34: Demandée | H34: Essentiel | I34: — | J34: Période adaptée : depuis la création si moins de 3 mois | K34: ● | L34: ● | M34: ● | N34: ● | O34: ● | P34: ● | Q34: ● | R34: ● | S34: Perte, Levier | T34: — | U34: — | V34: FIN-06.05, XF06
A35: FIN-06.02 | B35: FIN-06 | C35: =IFERROR(INDEX(Thèmes!$D$2:$D$190,MATCH(B35,Thèmes!$A$2:$A$190,0)),"") | D35: A12 · Vos ventes | E35: Ventes par mois : prestations, tickets, couverts, commandes ou chantiers selon le métier | F35: Nombre | G35: Partagée | H35: Essentiel | I35: — | J35: — | K35: ● | L35: ● | M35: ● | N35: ● | O35: ● | P35: ● | R35: ● | S35: Mesure | T35: Posée une seule fois, par le premier agent souscrit qui en a besoin (ACQ-21.02, ACQ-11.06, ACQ-11.07, ACQ-11.14), sinon ici | U35: ACQ-21.02, ACQ-11.06, ACQ-11.07, ACQ-11.14 | V35: FIN-03.02, FIN-06.07, FIN-10.08, FIN-19.03, FIN-19.04
A36: FIN-06.03 | B36: FIN-06 | C36: =IFERROR(INDEX(Thèmes!$D$2:$D$190,MATCH(B36,Thèmes!$A$2:$A$190,0)),"") | D36: F02 · Vos charges variables (tableau par poste) | E36: Total des charges variables il y a 12 mois (achats compris) | F36: € | G36: Demandée | H36: Essentiel | I36: — | J36: Mêmes 3 mois, un an plus tôt (masquée avant 15 mois d'existence) | K36: ● | L36: ● | M36: ● | N36: ● | O36: ● | P36: ● | Q36: ● | R36: ● | S36: Problème | T36: — | U36: — | V36: FIN-04.02 | W36: Niveau
A37: FIN-06.04 | B37: FIN-06 | C37: =IFERROR(INDEX(Thèmes!$D$2:$D$190,MATCH(B37,Thèmes!$A$2:$A$190,0)),"") | D37: F02 · Vos charges variables (tableau par poste) | E37: Charges variables de votre mois le plus fort et de votre mois le plus faible (achats compris) | F37: € (2 colonnes) | G37: Demandée | H37: Approfondi | I37: — | J37: — | K37: ● | L37: ● | M37: ● | N37: ● | O37: ● | P37: ● | Q37: ● | R37: ● | S37: Problème | T37: — | U37: — | V37: FIN-06.09
A38: FIN-06.05 | B38: FIN-06 | C38: =IFERROR(INDEX(Thèmes!$D$2:$D$190,MATCH(B38,Thèmes!$A$2:$A$190,0)),"") | D38: — | E38: Charges variables totales par mois | F38: € | G38: Calculée | H38: — | I38: — | J38: — | K38: ● | L38: ● | M38: ● | N38: ● | O38: ● | P38: ● | Q38: ● | R38: ● | S38: Mesure | T38: Postes du tableau + achats + sous-traitance. Commissions des plateformes : calcul de l'agent Acquisition (ACQ-07) s'il est souscrit, sinon ligne du tableau | U38: FIN-06.01, FIN-08.01, FIN-08.02, ACQ-07.07 | V38: FIN-06.06, FIN-06.07, FIN-06.08, FIN-07.14, FIN-11.06
A39: FIN-06.06 | B39: FIN-06 | C39: =IFERROR(INDEX(Thèmes!$D$2:$D$190,MATCH(B39,Thèmes!$A$2:$A$190,0)),"") | D39: — | E39: Charges variables en % du CA | F39: % | G39: Calculée | H39: — | I39: — | J39: — | K39: ● | L39: ● | M39: ● | N39: ● | O39: ● | P39: ● | Q39: ● | R39: ● | S39: Cible | T39: Charges variables ÷ CA mensuel | U39: FIN-06.05, Inscription · CA mensuel | V39: Affichée dans le rapport
A40: FIN-06.07 | B40: FIN-06 | C40: =IFERROR(INDEX(Thèmes!$D$2:$D$190,MATCH(B40,Thèmes!$A$2:$A$190,0)),"") | D40: — | E40: Coût variable moyen par vente | F40: € | G40: Calculée | H40: — | I40: — | J40: — | K40: ● | L40: ● | M40: ● | N40: ● | O40: ● | P40: ● | Q40: ● | R40: ● | S40: Levier | T40: Charges variables ÷ ventes du mois | U40: FIN-06.05, FIN-06.02 | V40: XF48, XF50
A41: FIN-06.08 | B41: FIN-06 | C41: =IFERROR(INDEX(Thèmes!$D$2:$D$190,MATCH(B41,Thèmes!$A$2:$A$190,0)),"") | D41: — | E41: Taux de marge sur coûts variables | F41: % | G41: Calculée | H41: — | I41: — | J41: — | K41: ● | L41: ● | M41: ● | N41: ● | O41: ● | P41: ● | Q41: ● | R41: ● | S41: Mesure | T41: (CA − charges variables) ÷ CA | U41: Inscription · CA mensuel, FIN-06.05 | V41: FIN-02.03, FIN-04.03, FIN-05.12, FIN-05.14, FIN-05.16, FIN-07.11, FIN-14.02, FIN-22.05, FIN-27.02, FIN-28.03, FIN-31.01, FIN-41.03, XF04, XF08, XF47, S01, S03, S04, S06, S09, S10
A42: FIN-06.09 | B42: FIN-06 | C42: =IFERROR(INDEX(Thèmes!$D$2:$D$190,MATCH(B42,Thèmes!$A$2:$A$190,0)),"") | D42: — | E42: Les coûts variables suivent-ils le CA ? (croissance rentable) | F42: Ratio | G42: Calculée | H42: — | I42: — | J42: — | K42: ● | L42: ● | M42: ● | N42: ● | O42: ● | P42: ● | Q42: ● | R42: ● | S42: Problème | T42: Écart de charges variables entre mois fort et mois faible ÷ écart de CA entre ces deux mois | U42: FIN-06.04, ACQ-23.05, ACQ-23.06 | V42: XF08
A43: FIN-07.01 | B43: FIN-07 | C43: =IFERROR(INDEX(Thèmes!$D$2:$D$190,MATCH(B43,Thèmes!$A$2:$A$190,0)),"") | D43: F03 · Votre masse salariale | E43: Masse salariale chargée par mois (salaires + charges patronales, hors dirigeant) | F43: € | G43: Demandée | H43: Essentiel | I43: D02 · si au moins un salarié | J43: Période adaptée : depuis la création si moins de 3 mois | K43: ● | L43: ● | M43: ● | N43: ● | O43: ● | P43: ● | Q43: ● | R43: ● | S43: Perte | T43: — | U43: — | V43: FIN-05.08, FIN-07.08, FIN-07.09, FIN-07.12, FIN-07.15
A44: FIN-07.02 | B44: FIN-07 | C44: =IFERROR(INDEX(Thèmes!$D$2:$D$190,MATCH(B44,Thèmes!$A$2:$A$190,0)),"") | D44: F03 · Votre masse salariale | E44: Masse salariale chargée il y a 12 mois | F44: € | G44: Demandée | H44: Essentiel | I44: D02 · si au moins un salarié | J44: Mêmes 3 mois, un an plus tôt (masquée avant 15 mois d'existence) | K44: ● | L44: ● | M44: ● | N44: ● | O44: ● | P44: ● | Q44: ● | R44: ● | S44: Problème | T44: — | U44: — | V44: FIN-07.15
A45: FIN-07.17 | B45: FIN-07 | C45: =IFERROR(INDEX(Thèmes!$D$2:$D$190,MATCH(B45,Thèmes!$A$2:$A$190,0)),"") | D45: F03 · Votre masse salariale | E45: Nombre de personnes dans l'entreprise il y a 12 mois, vous compris (même définition que le dossier d'entreprise) | F45: Nombre | G45: Demandée | H45: Essentiel | I45: D02 · si au moins un salarié | J45: Il y a 12 mois (masquée avant 12 mois d'existence) | K45: ● | L45: ● | M45: ● | N45: ● | O45: ● | P45: ● | Q45: ● | R45: ● | S45: Problème | T45: — | U45: — | V45: FIN-07.15 | W45: Nouveau (28 oct.) : vérification de l'historique
A46: FIN-07.03 | B46: FIN-07 | C46: =IFERROR(INDEX(Thèmes!$D$2:$D$190,MATCH(B46,Thèmes!$A$2:$A$190,0)),"") | D46: A20 · Votre équipe et sa capacité | E46: Heures travaillées et heures facturées par mois | F46: Heures (2 colonnes) | G46: Partagée | H46: Essentiel | I46: D18 · si facturation au temps | J46: — | K46: ● | O46: ● | P46: ● | S46: Capacité | T46: Posée une seule fois, par le premier agent souscrit qui en a besoin (ACQ-21.04, ACQ-21.05), sinon ici | U46: ACQ-21.04, ACQ-21.05 | V46: FIN-07.12, FIN-07.13, FIN-07.14
A47: FIN-07.04 | B47: FIN-07 | C47: =IFERROR(INDEX(Thèmes!$D$2:$D$190,MATCH(B47,Thèmes!$A$2:$A$190,0)),"") | D47: A14 · Vos prix et remises | E47: Taux horaire ou journalier facturé | F47: Plusieurs champs : Tarif · Par | G47: Partagée | H47: Essentiel | I47: D18 · si facturation au temps | J47: — | K47: ● | O47: ● | P47: ● | S47: Cible | T47: Posée une seule fois, par le premier agent souscrit qui en a besoin (ACQ-13.03), sinon ici | U47: ACQ-13.03 | V47: FIN-07.14 | W47: Format de réponse (la banque l'emporte)
A48: FIN-07.05 | B48: FIN-07 | C48: =IFERROR(INDEX(Thèmes!$D$2:$D$190,MATCH(B48,Thèmes!$A$2:$A$190,0)),"") | D48: F03 · Votre masse salariale | E48: Heures supplémentaires payées par mois, et leur coût | F48: Heures et € | G48: Demandée | H48: Essentiel | I48: D02 · si au moins un salarié | J48: — | K48: ● | L48: ● | M48: ● | N48: ● | O48: ● | P48: ● | Q48: ● | R48: ● | S48: Capacité | T48: — | U48: — | V48: FIN-07.07
A49: FIN-07.06 | B49: FIN-07 | C49: =IFERROR(INDEX(Thèmes!$D$2:$D$190,MATCH(B49,Thèmes!$A$2:$A$190,0)),"") | D49: F03 · Votre masse salariale | E49: Coût des remplacements (absences, congés) sur 12 mois | F49: € | G49: Demandée | H49: Approfondi | I49: D02 · si au moins un salarié | J49: Période adaptée : depuis la création si moins de 12 mois | K49: ● | L49: ● | M49: ● | N49: ● | O49: ● | P49: ● | Q49: ● | R49: ● | S49: Perte | T49: — | U49: — | V49: XR26
A50: FIN-07.07 | B50: FIN-07 | C50: =IFERROR(INDEX(Thèmes!$D$2:$D$190,MATCH(B50,Thèmes!$A$2:$A$190,0)),"") | D50: — | E50: Heures supplémentaires converties en équivalent temps plein, et leur coût annuel | F50: ETP et € | G50: Calculée | H50: — | I50: — | J50: — | K50: ● | L50: ● | M50: ● | N50: ● | O50: ● | P50: ● | Q50: ● | R50: ● | S50: Capacité | T50: Heures supplémentaires par mois ÷ 151,67 ; coût × 12 | U50: FIN-07.05 | V50: XR28, S04
A51: FIN-07.08 | B51: FIN-07 | C51: =IFERROR(INDEX(Thèmes!$D$2:$D$190,MATCH(B51,Thèmes!$A$2:$A$190,0)),"") | D51: — | E51: Poids de la masse salariale dans le CA | F51: % | G51: Calculée | H51: — | I51: — | J51: — | K51: ● | L51: ● | M51: ● | N51: ● | O51: ● | P51: ● | Q51: ● | R51: ● | S51: Cible | T51: Masse salariale ÷ CA mensuel | U51: FIN-07.01, Inscription · CA mensuel | V51: XF05
A52: FIN-07.09 | B52: FIN-07 | C52: =IFERROR(INDEX(Thèmes!$D$2:$D$190,MATCH(B52,Thèmes!$A$2:$A$190,0)),"") | D52: — | E52: Coût moyen chargé par salarié | F52: € | G52: Calculée | H52: — | I52: — | J52: — | K52: ● | L52: ● | M52: ● | N52: ● | O52: ● | P52: ● | Q52: ● | R52: ● | S52: Mesure | T52: Masse salariale ÷ salariés (effectif hors dirigeant) | U52: FIN-07.01, Inscription · effectif | V52: RH-31.05, XR28, S04
A53: FIN-07.10 | B53: FIN-07 | C53: =IFERROR(INDEX(Thèmes!$D$2:$D$190,MATCH(B53,Thèmes!$A$2:$A$190,0)),"") | D53: — | E53: CA par personne de l'effectif total | F53: € | G53: Calculée | H53: — | I53: — | J53: — | K53: ● | L53: ● | M53: ● | N53: ● | O53: ● | P53: ● | Q53: ● | R53: ● | S53: Cible | T53: CA mensuel ÷ effectif total (inscription). Différent du CA par personne en production (ACQ-21) | U53: Inscription · CA mensuel, Inscription · effectif | V53: Affichée dans le rapport
A54: FIN-07.11 | B54: FIN-07 | C54: =IFERROR(INDEX(Thèmes!$D$2:$D$190,MATCH(B54,Thèmes!$A$2:$A$190,0)),"") | D54: — | E54: Marge générée par personne de l'effectif total | F54: € | G54: Calculée | H54: — | I54: — | J54: — | K54: ● | L54: ● | M54: ● | N54: ● | O54: ● | P54: ● | Q54: ● | R54: ● | S54: Levier | T54: CA × taux de marge sur coûts variables ÷ effectif total | U54: Inscription · CA mensuel, FIN-06.08, Inscription · effectif | V54: Affichée dans le rapport
A55: FIN-07.12 | B55: FIN-07 | C55: =IFERROR(INDEX(Thèmes!$D$2:$D$190,MATCH(B55,Thèmes!$A$2:$A$190,0)),"") | D55: — | E55: Coût d'une heure de travail | F55: € | G55: Calculée | H55: — | I55: — | J55: — | K55: ● | L55: ● | M55: ● | N55: ● | O55: ● | P55: ● | Q55: ● | S55: Mesure | T55: Masse salariale ÷ heures travaillées ; sans heures déclarées : masse salariale ÷ (salariés × 151,67 h) | U55: FIN-07.01, ACQ-21.04, Inscription · effectif | V55: COM-31.08, FIN-02.02, FIN-07.14, FIN-10.06, FIN-27.02, FIN-28.03, RH-28.08, RH-31.05, XF37, XF50, XR29
A56: FIN-07.13 | B56: FIN-07 | C56: =IFERROR(INDEX(Thèmes!$D$2:$D$190,MATCH(B56,Thèmes!$A$2:$A$190,0)),"") | D56: — | E56: CA par heure travaillée | F56: € | G56: Calculée | H56: — | I56: — | J56: — | K56: ● | O56: ● | P56: ● | S56: Cible | T56: CA mensuel ÷ heures travaillées | U56: Inscription · CA mensuel, ACQ-21.04 | V56: COM-31.08, XF37
A57: FIN-07.14 | B57: FIN-07 | C57: =IFERROR(INDEX(Thèmes!$D$2:$D$190,MATCH(B57,Thèmes!$A$2:$A$190,0)),"") | D57: — | E57: Marge par heure facturée | F57: € | G57: Calculée | H57: — | I57: — | J57: — | K57: ● | O57: ● | P57: ● | S57: Levier | T57: Taux horaire − coût d'une heure − coût variable par heure | U57: ACQ-13.03, FIN-07.12, FIN-06.05, ACQ-21.05 | V57: XF37, XF50
A58: FIN-07.15 | B58: FIN-07 | C58: =IFERROR(INDEX(Thèmes!$D$2:$D$190,MATCH(B58,Thèmes!$A$2:$A$190,0)),"") | D58: — | E58: Évolution de la masse salariale comparée à celle du CA | F58: Points de % | G58: Calculée | H58: — | I58: — | J58: — | K58: ● | L58: ● | M58: ● | N58: ● | O58: ● | P58: ● | Q58: ● | R58: ● | S58: Problème | T58: Évolution de la masse salariale (3 derniers mois contre les mêmes 3 mois un an plus tôt) à côté de l'évolution du CA sur 12 mois (ACQ-23.10) et de l'effectif (FIN-07.17 il y a 12 mois, dossier aujourd'hui). | U58: FIN-07.01, FIN-07.02, FIN-07.17, ACQ-23.10 | V58: FIN-04.04, XF07
A59: FIN-07.16 | B59: FIN-07 | C59: =IFERROR(INDEX(Thèmes!$D$2:$D$190,MATCH(B59,Thèmes!$A$2:$A$190,0)),"") | D59: — | E59: Capacité restante avant de devoir recruter | F59: Nombre et € | G59: Autre agent | H59: — | I59: — | J59: — | K59: ● | L59: ● | M59: ● | N59: ● | O59: ● | P59: ● | Q59: ● | S59: Capacité | T59: Capacité inutilisée de l'agent Acquisition (ACQ-21) et capacité disponible de l'agent RH (RH-07) | U59: ACQ-21.14, RH-07 | V59: Affichée dans le rapport
A60: FIN-08.01 | B60: FIN-08 | C60: =IFERROR(INDEX(Thèmes!$D$2:$D$190,MATCH(B60,Thèmes!$A$2:$A$190,0)),"") | D60: F04 · Vos achats et fournisseurs (tableau) | E60: Achats de marchandises ou de matières par mois | F60: € | G60: Demandée | H60: Essentiel | I60: D08 · si achats | J60: Période adaptée : depuis la création si moins de 3 mois | K60: ● | L60: ● | M60: ● | N60: ● | O60: ● | P60: ● | Q60: ● | R60: ● | S60: Perte | T60: — | U60: — | V60: FIN-06.05, FIN-08.07, FIN-08.09, FIN-08.10, FIN-20.05, FIN-38.01, FIN-40.04, FIN-44.02, XF06, S03, S07, S11
A61: FIN-08.02 | B61: FIN-08 | C61: =IFERROR(INDEX(Thèmes!$D$2:$D$190,MATCH(B61,Thèmes!$A$2:$A$190,0)),"") | D61: F04 · Vos achats et fournisseurs (tableau) | E61: Sous-traitance par mois | F61: € | G61: Demandée | H61: Essentiel | I61: D08 · si sous-traitance | J61: Période adaptée : depuis la création si moins de 3 mois | K61: ● | L61: ● | M61: ● | N61: ● | O61: ● | P61: ● | Q61: ● | R61: ● | S61: Perte | T61: — | U61: — | V61: FIN-06.05, FIN-08.08, FIN-08.09, FIN-08.10, FIN-20.05, S07, S11
A62: FIN-08.03 | B62: FIN-08 | C62: =IFERROR(INDEX(Thèmes!$D$2:$D$190,MATCH(B62,Thèmes!$A$2:$A$190,0)),"") | D62: F04 · Vos achats et fournisseurs (tableau) | E62: Vos 3 principaux fournisseurs : achats par mois, hausse de prix sur 12 mois, date de la dernière renégociation, fournisseur de remplacement identifié (oui / non) | F62: Tableau 3 × 4 | G62: Demandée | H62: Approfondi | I62: D08 · si fournisseurs réguliers | J62: Période adaptée : depuis la création si moins de 12 mois | K62: ● | L62: ● | M62: ● | N62: ● | O62: ● | P62: ● | Q62: ● | R62: ● | S62: Risque, Levier | T62: — | U62: — | V62: FIN-08.09, FIN-08.10, FIN-08.11, FIN-08.12, FIN-08.13, FIN-30.01 | W62: Niveau
A63: FIN-08.04 | B63: FIN-08 | C63: =IFERROR(INDEX(Thèmes!$D$2:$D$190,MATCH(B63,Thèmes!$A$2:$A$190,0)),"") | D63: F04 · Vos achats et fournisseurs (tableau) | E63: Nombre total de fournisseurs réguliers | F63: Nombre | G63: Demandée | H63: Approfondi | I63: D08 · si fournisseurs réguliers | J63: — | K63: ● | L63: ● | M63: ● | N63: ● | O63: ● | P63: ● | Q63: ● | R63: ● | S63: Risque | T63: — | U63: — | V63: XF11
A64: FIN-08.05 | B64: FIN-08 | C64: =IFERROR(INDEX(Thèmes!$D$2:$D$190,MATCH(B64,Thèmes!$A$2:$A$190,0)),"") | D64: F04 · Vos achats et fournisseurs (tableau) | E64: Économie obtenue lors de votre dernière renégociation | F64: % | G64: Demandée | H64: Approfondi | I64: D08 · si fournisseurs réguliers | J64: — | K64: ● | L64: ● | M64: ● | N64: ● | O64: ● | P64: ● | Q64: ● | R64: ● | S64: Levier | T64: — | U64: — | V64: XF10
A65: FIN-08.06 | B65: FIN-08 | C65: =IFERROR(INDEX(Thèmes!$D$2:$D$190,MATCH(B65,Thèmes!$A$2:$A$190,0)),"") | D65: F04 · Vos achats et fournisseurs (tableau) | E65: Délai de livraison de votre fournisseur principal | F65: Jours | G65: Demandée | H65: Approfondi | I65: D07 · si stock | J65: — | K65: ● | L65: ● | M65: ● | N65: ● | O65: ● | P65: ● | Q65: ● | R65: ● | S65: Risque | T65: — | U65: — | V65: FIN-41.05 | W65: Profils ou tailles concernés
A66: FIN-08.07 | B66: FIN-08 | C66: =IFERROR(INDEX(Thèmes!$D$2:$D$190,MATCH(B66,Thèmes!$A$2:$A$190,0)),"") | D66: — | E66: Achats en % du CA (restaurant : coût matière) | F66: % | G66: Calculée | H66: — | I66: — | J66: — | K66: ● | L66: ● | M66: ● | N66: ● | O66: ● | P66: ● | Q66: ● | R66: ● | S66: Cible | T66: Achats ÷ CA mensuel | U66: FIN-08.01, Inscription · CA mensuel | V66: FIN-32.01, XF05, XF49
A67: FIN-08.08 | B67: FIN-08 | C67: =IFERROR(INDEX(Thèmes!$D$2:$D$190,MATCH(B67,Thèmes!$A$2:$A$190,0)),"") | D67: — | E67: Sous-traitance en % du CA | F67: % | G67: Calculée | H67: — | I67: — | J67: — | K67: ● | L67: ● | M67: ● | N67: ● | O67: ● | P67: ● | Q67: ● | R67: ● | S67: Cible | T67: Sous-traitance ÷ CA mensuel | U67: FIN-08.02, Inscription · CA mensuel | V67: XF05
A68: FIN-08.09 | B68: FIN-08 | C68: =IFERROR(INDEX(Thèmes!$D$2:$D$190,MATCH(B68,Thèmes!$A$2:$A$190,0)),"") | D68: — | E68: Part du 1er fournisseur dans les achats | F68: % | G68: Calculée | H68: — | I68: — | J68: — | K68: ● | L68: ● | M68: ● | N68: ● | O68: ● | P68: ● | Q68: ● | R68: ● | S68: Risque | T68: Achats du 1er fournisseur ÷ (achats + sous-traitance) | U68: FIN-08.03, FIN-08.01, FIN-08.02 | V68: FIN-30.01, XF10
A69: FIN-08.10 | B69: FIN-08 | C69: =IFERROR(INDEX(Thèmes!$D$2:$D$190,MATCH(B69,Thèmes!$A$2:$A$190,0)),"") | D69: — | E69: Part des 3 principaux fournisseurs | F69: % | G69: Calculée | H69: — | I69: — | J69: — | K69: ● | L69: ● | M69: ● | N69: ● | O69: ● | P69: ● | Q69: ● | R69: ● | S69: Risque | T69: Achats des 3 premiers ÷ (achats + sous-traitance) | U69: FIN-08.03, FIN-08.01, FIN-08.02 | V69: XF11
A70: FIN-08.11 | B70: FIN-08 | C70: =IFERROR(INDEX(Thèmes!$D$2:$D$190,MATCH(B70,Thèmes!$A$2:$A$190,0)),"") | D70: — | E70: Hausse moyenne des prix fournisseurs sur 12 mois | F70: % et € | G70: Calculée | H70: — | I70: — | J70: — | K70: ● | L70: ● | M70: ● | N70: ● | O70: ● | P70: ● | Q70: ● | R70: ● | S70: Problème | T70: Hausse de chaque fournisseur pondérée par ses achats | U70: FIN-08.03 | V70: FIN-04.04, XF07, XF09
A71: FIN-08.12 | B71: FIN-08 | C71: =IFERROR(INDEX(Thèmes!$D$2:$D$190,MATCH(B71,Thèmes!$A$2:$A$190,0)),"") | D71: — | E71: Mois depuis la dernière renégociation du 1er fournisseur | F71: Mois | G71: Calculée | H71: — | I71: — | J71: — | K71: ● | L71: ● | M71: ● | N71: ● | O71: ● | P71: ● | Q71: ● | R71: ● | S71: Levier | T71: Date du jour − date de la dernière renégociation | U71: FIN-08.03 | V71: XF10
A72: FIN-08.13 | B72: FIN-08 | C72: =IFERROR(INDEX(Thèmes!$D$2:$D$190,MATCH(B72,Thèmes!$A$2:$A$190,0)),"") | D72: — | E72: Économie annuelle d'une baisse de 5 % chez le 1er fournisseur | F72: € | G72: Calculée | H72: — | I72: — | J72: — | K72: ● | L72: ● | M72: ● | N72: ● | O72: ● | P72: ● | Q72: ● | R72: ● | S72: Potentiel CA | T72: Achats du 1er fournisseur × 5 % × 12 | U72: FIN-08.03 | V72: XF10
A73: FIN-09.01 | B73: FIN-09 | C73: =IFERROR(INDEX(Thèmes!$D$2:$D$190,MATCH(B73,Thèmes!$A$2:$A$190,0)),"") | D73: F05 · Vos abonnements et contrats (tableau) | E73: Vos abonnements et contrats (logiciels, télécoms, maintenance, location de matériel…) : coût par mois, nombre d'utilisateurs, date de renouvellement, résiliable ou engagé, peu ou pas utilisé. Sans les outils marketing (budget marketing) ni les leasings (déclarés avec les crédits) | F73: Tableau (une ligne par contrat) | G73: Demandée | H73: Approfondi | I73: — | J73: — | K73: ● | L73: ● | M73: ● | N73: ● | O73: ● | P73: ● | Q73: ● | R73: ● | S73: Perte, Levier | T73: — | U73: — | V73: FIN-09.04, FIN-09.05, FIN-09.06, FIN-09.07, FIN-09.08, FIN-09.09 | W73: Niveau
A74: FIN-09.02 | B74: FIN-09 | C74: =IFERROR(INDEX(Thèmes!$D$2:$D$190,MATCH(B74,Thèmes!$A$2:$A$190,0)),"") | D74: F05 · Vos abonnements et contrats (tableau) | E74: Nombre de contrats dont le prix a augmenté sur 12 mois | F74: Case par ligne | G74: Demandée | H74: Approfondi | I74: — | J74: Période adaptée : depuis la création si moins de 12 mois | K74: ● | L74: ● | M74: ● | N74: ● | O74: ● | P74: ● | Q74: ● | R74: ● | S74: Problème | T74: — | U74: — | V74: XF12 | W74: Libellé (« Donnée »)
A75: FIN-09.03 | B75: FIN-09 | C75: =IFERROR(INDEX(Thèmes!$D$2:$D$190,MATCH(B75,Thèmes!$A$2:$A$190,0)),"") | D75: F05 · Vos abonnements et contrats (tableau) | E75: Contrats renégociés ou remis en concurrence sur 12 mois | F75: Nombre | G75: Demandée | H75: Approfondi | I75: — | J75: Période adaptée : depuis la création si moins de 12 mois | K75: ● | L75: ● | M75: ● | N75: ● | O75: ● | P75: ● | Q75: ● | R75: ● | S75: Levier | T75: — | U75: — | V75: Notée directement (couleur du thème)
A76: FIN-09.04 | B76: FIN-09 | C76: =IFERROR(INDEX(Thèmes!$D$2:$D$190,MATCH(B76,Thèmes!$A$2:$A$190,0)),"") | D76: — | E76: Nombre d'abonnements et de contrats | F76: Nombre | G76: Calculée | H76: — | I76: — | J76: — | K76: ● | L76: ● | M76: ● | N76: ● | O76: ● | P76: ● | Q76: ● | R76: ● | S76: Mesure | T76: Lignes du tableau | U76: FIN-09.01 | V76: Affichée dans le rapport
A77: FIN-09.05 | B77: FIN-09 | C77: =IFERROR(INDEX(Thèmes!$D$2:$D$190,MATCH(B77,Thèmes!$A$2:$A$190,0)),"") | D77: — | E77: Coût total des abonnements, par mois et par an | F77: € | G77: Calculée | H77: — | I77: — | J77: — | K77: ● | L77: ● | M77: ● | N77: ● | O77: ● | P77: ● | Q77: ● | R77: ● | S77: Mesure | T77: Somme des coûts mensuels, puis × 12 | U77: FIN-09.01 | V77: FIN-05.08, XF12
A78: FIN-09.06 | B78: FIN-09 | C78: =IFERROR(INDEX(Thèmes!$D$2:$D$190,MATCH(B78,Thèmes!$A$2:$A$190,0)),"") | D78: — | E78: Coût par utilisateur de chaque logiciel | F78: € | G78: Calculée | H78: — | I78: — | J78: — | K78: ● | L78: ● | M78: ● | N78: ● | O78: ● | P78: ● | Q78: ● | R78: ● | S78: Levier | T78: Coût mensuel ÷ utilisateurs | U78: FIN-09.01 | V78: Affichée dans le rapport
A79: FIN-09.07 | B79: FIN-09 | C79: =IFERROR(INDEX(Thèmes!$D$2:$D$190,MATCH(B79,Thèmes!$A$2:$A$190,0)),"") | D79: — | E79: Coût annuel des contrats peu ou pas utilisés | F79: € | G79: Calculée | H79: — | I79: — | J79: — | K79: ● | L79: ● | M79: ● | N79: ● | O79: ● | P79: ● | Q79: ● | R79: ● | S79: Perte | T79: Somme des contrats cochés « peu utilisé » × 12 | U79: FIN-09.01 | V79: XF12
A80: FIN-09.08 | B80: FIN-09 | C80: =IFERROR(INDEX(Thèmes!$D$2:$D$190,MATCH(B80,Thèmes!$A$2:$A$190,0)),"") | D80: — | E80: Doublons possibles (deux outils pour le même usage) | F80: Liste | G80: Calculée | H80: — | I80: — | J80: — | K80: ● | L80: ● | M80: ● | N80: ● | O80: ● | P80: ● | Q80: ● | R80: ● | S80: Perte | T80: Repérés par l'IA à partir des noms et des usages déclarés | U80: FIN-09.01 | V80: XF12
A81: FIN-09.09 | B81: FIN-09 | C81: =IFERROR(INDEX(Thèmes!$D$2:$D$190,MATCH(B81,Thèmes!$A$2:$A$190,0)),"") | D81: — | E81: Contrats renouvelés dans les 90 prochains jours | F81: Liste et € | G81: Calculée | H81: — | I81: — | J81: — | K81: ● | L81: ● | M81: ● | N81: ● | O81: ● | P81: ● | Q81: ● | R81: ● | S81: Levier | T81: Contrats dont la date de renouvellement tombe dans les 3 mois | U81: FIN-09.01 | V81: XF12
A82: FIN-09.10 | B82: FIN-09 | C82: =IFERROR(INDEX(Thèmes!$D$2:$D$190,MATCH(B82,Thèmes!$A$2:$A$190,0)),"") | D82: — | E82: Coût total des abonnements et contrats par mois (le détail FIN-09.01 n'est demandé que si le thème ressort en difficulté ; FIN-09.05 = ce total tant que le détail manque) | F82: € | G82: Demandée | H82: Essentiel | I82: — | J82: — | K82: ● | L82: ● | M82: ● | N82: ● | O82: ● | P82: ● | Q82: ● | R82: ● | S82: — | T82: — | U82: — | V82: — | W82: Nouveau
A83: FIN-10.01 | B83: FIN-10 | C83: =IFERROR(INDEX(Thèmes!$D$2:$D$190,MATCH(B83,Thèmes!$A$2:$A$190,0)),"") | D83: F07 · Vos erreurs et gestes commerciaux | E83: Par mois : nombre de reprises, de retours et de gestes commerciaux ; coût direct moyen d'une reprise (matière, déplacement) et d'un geste commercial (le nombre de reprises est partagé avec RH-16) — déclencheur D40 | F83: Tableau (3 nombres, 2 coûts) | G83: Demandée | H83: Essentiel | I83: — | J83: — | K83: ● | L83: ● | M83: ● | N83: ● | O83: ● | P83: ● | Q83: ● | R83: ● | S83: Perte | T83: — | U83: — | V83: FIN-10.06, FIN-10.07, FIN-10.08, RH-16.05 | W83: Libellé (« Donnée »)
A84: FIN-10.02 | B84: FIN-10 | C84: =IFERROR(INDEX(Thèmes!$D$2:$D$190,MATCH(B84,Thèmes!$A$2:$A$190,0)),"") | D84: F07 · Vos erreurs et gestes commerciaux | E84: Cause principale : erreur de réalisation, défaut produit, retard, besoin mal compris, livraison | F84: Choix | G84: Demandée | H84: Approfondi | I84: D40 · si reprises, retours ou gestes | J84: — | K84: ● | L84: ● | M84: ● | N84: ● | O84: ● | P84: ● | Q84: ● | R84: ● | S84: Levier | T84: — | U84: — | V84: XF13 | W84: Condition d'affichage · Niveau
A85: FIN-10.03 | B85: FIN-10 | C85: =IFERROR(INDEX(Thèmes!$D$2:$D$190,MATCH(B85,Thèmes!$A$2:$A$190,0)),"") | D85: F07 · Vos erreurs et gestes commerciaux | E85: Temps moyen passé sur une reprise (partagé avec RH-16) | F85: Heures | G85: Demandée | H85: Approfondi | I85: D48 · si vous avez des reprises | J85: — | K85: ● | L85: ● | M85: ● | N85: ● | O85: ● | P85: ● | Q85: ● | R85: ● | S85: Perte | T85: — | U85: — | V85: FIN-10.06, RH-16.05 | W85: Condition d'affichage · Niveau
A86: FIN-10.04 | B86: FIN-10 | C86: =IFERROR(INDEX(Thèmes!$D$2:$D$190,MATCH(B86,Thèmes!$A$2:$A$190,0)),"") | D86: F07 · Vos erreurs et gestes commerciaux | E86: Coût moyen de traitement d'un retour : port, emballage, temps. La marchandise non revendable est comptée dans les pertes de stock (FIN-40) | F86: € | G86: Demandée | H86: Essentiel | I86: D41 · si vous avez des retours | J86: — | L86: ● | M86: ● | S86: Perte | T86: — | U86: — | V86: FIN-10.07, XF48 | W86: Condition d'affichage
A87: FIN-10.05 | B87: FIN-10 | C87: =IFERROR(INDEX(Thèmes!$D$2:$D$190,MATCH(B87,Thèmes!$A$2:$A$190,0)),"") | D87: F07 · Vos erreurs et gestes commerciaux | E87: Ces coûts sur 12 mois : en hausse, stables, en baisse | F87: Choix | G87: Demandée | H87: Approfondi | I87: D40 · si reprises, retours ou gestes | J87: Il y a 12 mois (masquée avant 12 mois d'existence) | K87: ● | L87: ● | M87: ● | N87: ● | O87: ● | P87: ● | Q87: ● | R87: ● | S87: Problème | T87: — | U87: — | V87: XF13 | W87: Condition d'affichage
A88: FIN-10.06 | B88: FIN-10 | C88: =IFERROR(INDEX(Thèmes!$D$2:$D$190,MATCH(B88,Thèmes!$A$2:$A$190,0)),"") | D88: — | E88: Coût mensuel des reprises | F88: € | G88: Calculée | H88: — | I88: — | J88: — | K88: ● | L88: ● | M88: ● | N88: ● | O88: ● | P88: ● | Q88: ● | S88: Perte | T88: Reprises × (coût direct moyen + temps moyen × coût d'une heure). Seul montant affiché pour les reprises : l'agent RH en donne les heures (RH-16), jamais un second coût | U88: FIN-10.01, FIN-10.03, FIN-07.12 | V88: FIN-10.07, XR14
A89: FIN-10.07 | B89: FIN-10 | C89: =IFERROR(INDEX(Thèmes!$D$2:$D$190,MATCH(B89,Thèmes!$A$2:$A$190,0)),"") | D89: — | E89: Coût mensuel des erreurs, retours et gestes commerciaux | F89: € | G89: Calculée | H89: — | I89: — | J89: — | K89: ● | L89: ● | M89: ● | N89: ● | O89: ● | P89: ● | Q89: ● | S89: Perte | T89: Coût des reprises + gestes × coût moyen + retours × coût de traitement d'un retour (la marchandise perdue est dans FIN-40) | U89: FIN-10.06, FIN-10.01, FIN-10.04 | V89: FIN-10.09, XF13
A90: FIN-10.08 | B90: FIN-10 | C90: =IFERROR(INDEX(Thèmes!$D$2:$D$190,MATCH(B90,Thèmes!$A$2:$A$190,0)),"") | D90: — | E90: Part des ventes concernées | F90: % | G90: Calculée | H90: — | I90: — | J90: — | K90: ● | L90: ● | M90: ● | N90: ● | O90: ● | P90: ● | Q90: ● | R90: ● | S90: Problème | T90: (Reprises + retours + gestes) ÷ ventes du mois | U90: FIN-10.01, FIN-06.02 | V90: XF13
A91: FIN-10.09 | B91: FIN-10 | C91: =IFERROR(INDEX(Thèmes!$D$2:$D$190,MATCH(B91,Thèmes!$A$2:$A$190,0)),"") | D91: — | E91: Coût des erreurs en % du CA | F91: % | G91: Calculée | H91: — | I91: — | J91: — | K91: ● | L91: ● | M91: ● | N91: ● | O91: ● | P91: ● | Q91: ● | S91: Cible | T91: Coût mensuel ÷ CA mensuel | U91: FIN-10.07, Inscription · CA mensuel | V91: Affichée dans le rapport
A92: FIN-11.01 | B92: FIN-11 | C92: =IFERROR(INDEX(Thèmes!$D$2:$D$190,MATCH(B92,Thèmes!$A$2:$A$190,0)),"") | D92: F08 · Votre trésorerie aujourd'hui | E92: Trésorerie disponible aujourd'hui sur vos comptes, caisse comprise | F92: € | G92: Demandée | H92: Essentiel | I92: — | J92: — | K92: ● | L92: ● | M92: ● | N92: ● | O92: ● | P92: ● | Q92: ● | R92: ● | S92: Risque | T92: — | U92: — | V92: FIN-11.04, FIN-37.05
A93: FIN-11.02 | B93: FIN-11 | C93: =IFERROR(INDEX(Thèmes!$D$2:$D$190,MATCH(B93,Thèmes!$A$2:$A$190,0)),"") | D93: F08 · Votre trésorerie aujourd'hui | E93: Dont somme déjà réservée : TVA et impôts à payer, acomptes reçus pour des travaux pas encore faits, placement bloqué | F93: € | G93: Demandée | H93: Essentiel | I93: — | J93: — | K93: ● | L93: ● | M93: ● | N93: ● | O93: ● | P93: ● | Q93: ● | R93: ● | S93: Risque | T93: — | U93: — | V93: FIN-11.04
A94: FIN-11.03 | B94: FIN-11 | C94: =IFERROR(INDEX(Thèmes!$D$2:$D$190,MATCH(B94,Thèmes!$A$2:$A$190,0)),"") | D94: F08 · Votre trésorerie aujourd'hui | E94: Découvert autorisé et autres lignes de crédit disponibles | F94: € | G94: Demandée | H94: Essentiel | I94: — | J94: — | K94: ● | L94: ● | M94: ● | N94: ● | O94: ● | P94: ● | Q94: ● | R94: ● | S94: Risque | T94: — | U94: — | V94: FIN-24.08
A95: FIN-11.04 | B95: FIN-11 | C95: =IFERROR(INDEX(Thèmes!$D$2:$D$190,MATCH(B95,Thèmes!$A$2:$A$190,0)),"") | D95: — | E95: Trésorerie réellement mobilisable | F95: € | G95: Calculée | H95: — | I95: — | J95: — | K95: ● | L95: ● | M95: ● | N95: ● | O95: ● | P95: ● | Q95: ● | R95: ● | S95: Mesure | T95: Trésorerie disponible − somme réservée | U95: FIN-11.01, FIN-11.02 | V95: FIN-11.05, FIN-11.06, FIN-12.05, FIN-13.03, FIN-15.02, FIN-23.02, FIN-31.01, XF33, S01, S05, S06, S08
A96: FIN-11.05 | B96: FIN-11 | C96: =IFERROR(INDEX(Thèmes!$D$2:$D$190,MATCH(B96,Thèmes!$A$2:$A$190,0)),"") | D96: — | E96: Mois de charges fixes couverts | F96: Mois | G96: Calculée | H96: — | I96: — | J96: — | K96: ● | L96: ● | M96: ● | N96: ● | O96: ● | P96: ● | Q96: ● | R96: ● | S96: Risque | T96: Trésorerie mobilisable ÷ charges fixes mensuelles | U96: FIN-11.04, FIN-05.08 | V96: XF14, XF26, S13
A97: FIN-11.06 | B97: FIN-11 | C97: =IFERROR(INDEX(Thèmes!$D$2:$D$190,MATCH(B97,Thèmes!$A$2:$A$190,0)),"") | D97: — | E97: Jours de fonctionnement couverts sans aucune nouvelle entrée | F97: Jours | G97: Calculée | H97: — | I97: — | J97: — | K97: ● | L97: ● | M97: ● | N97: ● | O97: ● | P97: ● | Q97: ● | R97: ● | S97: Risque | T97: Trésorerie mobilisable ÷ ((charges fixes + charges variables) ÷ 30) | U97: FIN-11.04, FIN-05.08, FIN-06.05 | V97: XF14
A98: FIN-12.01 | B98: FIN-12 | C98: =IFERROR(INDEX(Thèmes!$D$2:$D$190,MATCH(B98,Thèmes!$A$2:$A$190,0)),"") | D98: F09 · Vos 3 derniers mois (tableau) | E98: Pour chacun des 3 derniers mois : total des entrées et total des sorties sur vos comptes | F98: Tableau 3 × 2 | G98: Demandée | H98: Essentiel | I98: — | J98: Période adaptée : depuis la création si moins de 3 mois | K98: ● | L98: ● | M98: ● | N98: ● | O98: ● | P98: ● | Q98: ● | R98: ● | S98: Problème | T98: — | U98: — | V98: FIN-12.02, FIN-12.03, FIN-12.04, FIN-12.06
A99: FIN-12.02 | B99: FIN-12 | C99: =IFERROR(INDEX(Thèmes!$D$2:$D$190,MATCH(B99,Thèmes!$A$2:$A$190,0)),"") | D99: — | E99: Solde de chaque mois et solde moyen | F99: € | G99: Calculée | H99: — | I99: — | J99: — | K99: ● | L99: ● | M99: ● | N99: ● | O99: ● | P99: ● | Q99: ● | R99: ● | S99: Mesure | T99: Entrées − sorties | U99: FIN-12.01 | V99: FIN-12.07, FIN-13.03
A100: FIN-12.03 | B100: FIN-12 | C100: =IFERROR(INDEX(Thèmes!$D$2:$D$190,MATCH(B100,Thèmes!$A$2:$A$190,0)),"") | D100: — | E100: Mois négatifs sur les 3 derniers | F100: Nombre | G100: Calculée | H100: — | I100: — | J100: — | K100: ● | L100: ● | M100: ● | N100: ● | O100: ● | P100: ● | Q100: ● | R100: ● | S100: Problème | T100: Mois où les sorties dépassent les entrées | U100: FIN-12.01 | V100: Affichée dans le rapport
...

Sheet RH — données
A1: Code | B1: Thème | C1: Nom du thème | D1: Écran | E1: Donnée | F1: Format de réponse | G1: Mode | H1: Niveau | I1: Condition d'affichage | J1: Période (selon l'ancienneté) | K1: Seul | L1: 2 à 5 | M1: 6 et + | N1: Sert à | O1: Calcul ou source | P1: Données utilisées | Q1: Utilisée dans | R1: Changement du 20 oct.
A2: RH-01.01 | B2: RH-01 | C2: =IFERROR(INDEX(Thèmes!$D$2:$D$190,MATCH(B2,Thèmes!$A$2:$A$190,0)),"") | D2: R01 · Rôles et responsabilités | E2: Les missions de chaque personne sont écrites (fiche de poste ou simple liste) : pour tous, pour une partie, pour personne | F2: Choix | G2: Demandée | H2: Essentiel | I2: — | J2: — | L2: ● | M2: ● | N2: Problème | O2: — | P2: — | Q2: Notée directement (couleur du thème)
A3: RH-01.02 | B3: RH-01 | C3: =IFERROR(INDEX(Thèmes!$D$2:$D$190,MATCH(B3,Thèmes!$A$2:$A$190,0)),"") | D3: R01 · Rôles et responsabilités | E3: Tâches dont personne ne sait vraiment qui doit s'en occuper | F3: Tranches : 0 · 1-2 · 3-5 · plus de 5 · je ne sais pas | G3: Demandée | H3: Approfondi | I3: — | J3: — | M3: ● | N3: Problème | O3: — | P3: — | Q3: Lue par l'IA pour adapter le conseil
A4: RH-02.01 | B4: RH-02 | C4: =IFERROR(INDEX(Thèmes!$D$2:$D$190,MATCH(B4,Thèmes!$A$2:$A$190,0)),"") | D4: R01 · Rôles et responsabilités | E4: Décisions courantes confiées à quelqu'un d'autre que vous : devis et prix, achats, planning, réclamations clients, recrutement | F4: Cases à cocher | G4: Demandée | H4: Essentiel | I4: — | J4: — | L4: ● | M4: ● | N4: Levier | O4: — | P4: — | Q4: Notée directement (couleur du thème)
A5: RH-02.02 | B5: RH-02 | C5: =IFERROR(INDEX(Thèmes!$D$2:$D$190,MATCH(B5,Thèmes!$A$2:$A$190,0)),"") | D5: R01 · Rôles et responsabilités | E5: Ce que vous confiez à l'extérieur, et heures par mois : comptabilité, administratif, contenu, production sous-traitée, assistant ou freelance | F5: Cases + heures par mois | G5: Demandée | H5: Essentiel | I5: — | J5: — | K5: ● | N5: Levier | O5: — | P5: — | Q5: XR23
A6: RH-03.01 | B6: RH-03 | C6: =IFERROR(INDEX(Thèmes!$D$2:$D$190,MATCH(B6,Thèmes!$A$2:$A$190,0)),"") | D6: R02 · Les sollicitations que vous recevez | E6: Sollicitations par jour. Définition : un collaborateur vient vous demander une validation, une décision, une autorisation, une priorité, la réponse à une question courante ou comment faire | F6: Tranches : 0-2 · 3-5 · 6-10 · 11-20 · plus de 20 · je ne sais pas | G6: Demandée | H6: Essentiel | I6: — | J6: — | L6: ● | M6: ● | N6: Problème | O6: — | P6: — | Q6: RH-03.06, XR01
A7: RH-03.02 | B7: RH-03 | C7: =IFERROR(INDEX(Thèmes!$D$2:$D$190,MATCH(B7,Thèmes!$A$2:$A$190,0)),"") | D7: R02 · Les sollicitations que vous recevez | E7: Temps moyen d'une sollicitation | F7: Tranches : moins de 2 min · 2-5 · 5-15 · plus de 15 min · je ne sais pas | G7: Demandée | H7: Essentiel | I7: — | J7: — | L7: ● | M7: ● | N7: Capacité | O7: — | P7: — | Q7: RH-03.06, XR01
A8: RH-03.03 | B8: RH-03 | C8: =IFERROR(INDEX(Thèmes!$D$2:$D$190,MATCH(B8,Thèmes!$A$2:$A$190,0)),"") | D8: R02 · Les sollicitations que vous recevez | E8: Sujets les plus fréquents (3 au plus) : prix ou devis, question client, fournisseur, planning, manière de faire, problème technique | F8: Cases à cocher | G8: Demandée | H8: Approfondi | I8: — | J8: — | L8: ● | M8: ● | N8: Levier | O8: — | P8: — | Q8: XR02 | R8: Niveau
A9: RH-03.04 | B9: RH-03 | C9: =IFERROR(INDEX(Thèmes!$D$2:$D$190,MATCH(B9,Thèmes!$A$2:$A$190,0)),"") | D9: R02 · Les sollicitations que vous recevez | E9: Sur 10 sollicitations, combien auraient pu être réglées sans vous, avec une règle écrite ou une délégation ? | F9: Sur 10 : 0-2 · 3-5 · 6-8 · 9-10 · je ne sais pas | G9: Demandée | H9: Approfondi | I9: — | J9: — | L9: ● | M9: ● | N9: Levier | O9: — | P9: — | Q9: RH-03.07 | R9: Niveau
A10: RH-03.05 | B10: RH-03 | C10: =IFERROR(INDEX(Thèmes!$D$2:$D$190,MATCH(B10,Thèmes!$A$2:$A$190,0)),"") | D10: R02 · Les sollicitations que vous recevez | E10: Fonction qui vous sollicite le plus | F10: Choix | G10: Demandée | H10: Approfondi | I10: — | J10: — | L10: ● | M10: ● | N10: Levier | O10: — | P10: — | Q10: XR02
A11: RH-03.06 | B11: RH-03 | C11: =IFERROR(INDEX(Thèmes!$D$2:$D$190,MATCH(B11,Thèmes!$A$2:$A$190,0)),"") | D11: — | E11: Temps du dirigeant consommé par les sollicitations, par semaine | F11: Heures | G11: Calculée | H11: — | I11: — | J11: — | L11: ● | M11: ● | N11: Capacité | O11: Sollicitations par jour × temps moyen × jours travaillés | P11: RH-03.01, RH-03.02, ACQ-22.01 | Q11: RH-03.07, XR01
A12: RH-03.07 | B12: RH-03 | C12: =IFERROR(INDEX(Thèmes!$D$2:$D$190,MATCH(B12,Thèmes!$A$2:$A$190,0)),"") | D12: — | E12: Heures récupérables avec des règles écrites ou une délégation | F12: Heures | G12: Calculée | H12: — | I12: — | J12: — | L12: ● | M12: ● | N12: Levier | O12: Temps consommé × part évitable | P12: RH-03.06, RH-03.04 | Q12: RH-05.08, XR02
A13: RH-04.01 | B13: RH-04 | C13: =IFERROR(INDEX(Thèmes!$D$2:$D$190,MATCH(B13,Thèmes!$A$2:$A$190,0)),"") | D13: R03 · Ce que vous déléguez | E13: Tâches confiées à quelqu'un d'autre sur les 3 derniers mois — déclencheur D44 | F13: Nombre | G13: Demandée | H13: Essentiel | I13: — | J13: Période adaptée : depuis la création si moins de 3 mois | L13: ● | M13: ● | N13: Mesure | O13: — | P13: — | Q13: RH-04.06 | R13: Format de réponse (la banque l'emporte) · Libellé (« Donnée »)
A14: RH-04.02 | B14: RH-04 | C14: =IFERROR(INDEX(Thèmes!$D$2:$D$190,MATCH(B14,Thèmes!$A$2:$A$190,0)),"") | D14: R03 · Ce que vous déléguez | E14: Parmi elles, tâches reprises. Définition : vous avez dû la refaire, la corriger fortement, la terminer, reprendre le client ou annuler la délégation — déclencheur D45 | F14: Nombre ou tranche | G14: Demandée | H14: Essentiel | I14: D44 · si vous avez confié des tâches | J14: — | L14: ● | M14: ● | N14: Problème | O14: — | P14: — | Q14: RH-04.06 | R14: Libellé (« Donnée ») · Condition d'affichage
A15: RH-04.03 | B15: RH-04 | C15: =IFERROR(INDEX(Thèmes!$D$2:$D$190,MATCH(B15,Thèmes!$A$2:$A$190,0)),"") | D15: R03 · Ce que vous déléguez | E15: Raison principale des reprises : manque de compétence, consignes insuffisantes, pas de procédure, pas le temps de former, qualité insuffisante, urgence, « ça va plus vite si je le fais » | F15: Choix | G15: Demandée | H15: Approfondi | I15: D45 · si vous avez dû reprendre des tâches en main | J15: — | L15: ● | M15: ● | N15: Levier | O15: — | P15: — | Q15: RH-04.07 | R15: Condition d'affichage · Niveau
A16: RH-04.04 | B16: RH-04 | C16: =IFERROR(INDEX(Thèmes!$D$2:$D$190,MATCH(B16,Thèmes!$A$2:$A$190,0)),"") | D16: R03 · Ce que vous déléguez | E16: Tâches les plus souvent reprises (3 au plus) | F16: Texte court | G16: Demandée | H16: Approfondi | I16: D45 · si vous avez dû reprendre des tâches en main | J16: — | L16: ● | M16: ● | N16: Levier | O16: — | P16: — | Q16: XR06 | R16: Condition d'affichage
A17: RH-04.05 | B17: RH-04 | C17: =IFERROR(INDEX(Thèmes!$D$2:$D$190,MATCH(B17,Thèmes!$A$2:$A$190,0)),"") | D17: R03 · Ce que vous déléguez | E17: Temps passé par semaine à corriger ou reprendre ce qui a été délégué | F17: Tranches : 0 · 1-3 h · 3-6 h · 6-10 h · plus de 10 h · je ne sais pas | G17: Demandée | H17: Approfondi | I17: D45 · si vous avez dû reprendre des tâches en main | J17: — | L17: ● | M17: ● | N17: Capacité | O17: — | P17: — | Q17: XR06 | R17: Condition d'affichage
A18: RH-04.06 | B18: RH-04 | C18: =IFERROR(INDEX(Thèmes!$D$2:$D$190,MATCH(B18,Thèmes!$A$2:$A$190,0)),"") | D18: — | E18: Taux de délégation réussie | F18: % | G18: Calculée | H18: — | I18: — | J18: — | L18: ● | M18: ● | N18: Cible | O18: (Tâches confiées − tâches reprises) ÷ tâches confiées | P18: RH-04.01, RH-04.02 | Q18: RH-04.07, XR06
A19: RH-04.07 | B19: RH-04 | C19: =IFERROR(INDEX(Thèmes!$D$2:$D$190,MATCH(B19,Thèmes!$A$2:$A$190,0)),"") | D19: — | E19: Origine probable du problème de délégation | F19: Choix | G19: Calculée | H19: — | I19: — | J19: — | L19: ● | M19: ● | N19: Levier | O19: Compétence → la personne ; « plus vite si je le fais » → le dirigeant ; consignes, temps de formation → la méthode ; pas de procédure → les procédures | P19: RH-04.03, RH-04.06 | Q19: XR06
A20: RH-05.01 | B20: RH-05 | C20: =IFERROR(INDEX(Thèmes!$D$2:$D$190,MATCH(B20,Thèmes!$A$2:$A$190,0)),"") | D20: R04 · Votre semaine | E20: Jours et heures travaillés par semaine par le dirigeant (regroupe les anciennes RH-05.01 et RH-05.09) — mini-bloc « temps du dirigeant », partagé : posé par le premier agent qui en a besoin (Acquisition, Finance, Comm ou RH), jamais redemandé | F20: Plusieurs champs : Jours · Heures | G20: Demandée | H20: Essentiel | I20: — | J20: — | K20: ● | L20: ● | M20: ● | N20: Capacité | O20: — | P20: — | Q20: RH-05.06, RH-05.07, RH-08.07, RH-09.05, RH-17.05, XR04 | R20: Format de réponse (la banque l'emporte) · Libellé (« Donnée »)
A21: RH-05.02 | B21: RH-05 | C21: =IFERROR(INDEX(Thèmes!$D$2:$D$190,MATCH(B21,Thèmes!$A$2:$A$190,0)),"") | D21: R04 · Votre semaine | E21: Répartition de votre semaine : production, commercial, administratif, management (si équipe), développement et stratégie — mini-bloc « temps du dirigeant », partagé : posé par le premier agent qui en a besoin (Acquisition, Finance, Comm ou RH), jamais redemandé | F21: % (total 100) | G21: Demandée | H21: Essentiel | I21: — | J21: — | K21: ● | L21: ● | M21: ● | N21: Levier | O21: — | P21: — | Q21: RH-05.07, XR07 | R21: Libellé (« Donnée »)
A22: RH-05.03 | B22: RH-05 | C22: =IFERROR(INDEX(Thèmes!$D$2:$D$190,MATCH(B22,Thèmes!$A$2:$A$190,0)),"") | D22: R04 · Votre semaine | E22: Heures par semaine sur des tâches qu'une autre personne ou un outil pourrait faire | F22: Tranches : 0 · 1-3 h · 3-6 h · 6-10 h · plus de 10 h · je ne sais pas | G22: Demandée | H22: Essentiel | I22: — | J22: — | K22: ● | L22: ● | M22: ● | N22: Levier | O22: — | P22: — | Q22: RH-05.06, RH-05.08, XR04, XR07
A23: RH-05.04 | B23: RH-05 | C23: =IFERROR(INDEX(Thèmes!$D$2:$D$190,MATCH(B23,Thèmes!$A$2:$A$190,0)),"") | D23: R04 · Votre semaine | E23: Soirs et jours de week-end travaillés par semaine | F23: Plusieurs champs : Soirs · Jours de week-end | G23: Demandée | H23: Approfondi | I23: — | J23: — | K23: ● | L23: ● | M23: ● | N23: Risque | O23: — | P23: — | Q23: XR05 | R23: Format de réponse (la banque l'emporte)
A24: RH-05.05 | B24: RH-05 | C24: =IFERROR(INDEX(Thèmes!$D$2:$D$190,MATCH(B24,Thèmes!$A$2:$A$190,0)),"") | D24: R04 · Votre semaine | E24: Vos heures par rapport à il y a 12 mois : moins, autant, plus | F24: Choix | G24: Demandée | H24: Approfondi | I24: — | J24: Il y a 12 mois (masquée avant 12 mois d'existence) | K24: ● | L24: ● | M24: ● | N24: Problème | O24: — | P24: — | Q24: Lue par l'IA pour adapter le conseil
A25: RH-05.06 | B25: RH-05 | C25: =IFERROR(INDEX(Thèmes!$D$2:$D$190,MATCH(B25,Thèmes!$A$2:$A$190,0)),"") | D25: — | E25: Part du temps du dirigeant sur des tâches à faible valeur ajoutée | F25: % | G25: Calculée | H25: — | I25: — | J25: — | K25: ● | L25: ● | M25: ● | N25: Problème | O25: Heures délégables ou automatisables ÷ heures travaillées | P25: RH-05.03, RH-05.01 | Q25: XR05
A26: RH-05.07 | B26: RH-05 | C26: =IFERROR(INDEX(Thèmes!$D$2:$D$190,MATCH(B26,Thèmes!$A$2:$A$190,0)),"") | D26: — | E26: Heures réellement consacrées au développement de l'entreprise | F26: Heures | G26: Calculée | H26: — | I26: — | J26: — | K26: ● | L26: ● | M26: ● | N26: Problème | O26: Heures travaillées × part « développement et stratégie » | P26: RH-05.01, RH-05.02 | Q26: XR05
A27: RH-05.08 | B27: RH-05 | C27: =IFERROR(INDEX(Thèmes!$D$2:$D$190,MATCH(B27,Thèmes!$A$2:$A$190,0)),"") | D27: — | E27: Heures du dirigeant récupérables par semaine | F27: Heures | G27: Calculée | H27: — | I27: — | J27: — | K27: ● | L27: ● | M27: ● | N27: Levier | O27: Tâches délégables + sollicitations évitables + interruptions évitables, sans double compte (les sollicitations font partie des interruptions) | P27: RH-05.03, RH-03.07, RH-10.08 | Q27: XR04, XR27
A28: RH-05.10 | B28: RH-05 | C28: =IFERROR(INDEX(Thèmes!$D$2:$D$190,MATCH(B28,Thèmes!$A$2:$A$190,0)),"") | D28: — | E28: Durée d'absence possible du dirigeant sans retard pour les clients (ligne « vous » de RH-38.01) — mini-bloc « temps du dirigeant », partagé : posé par le premier agent qui en a besoin (Acquisition, Finance, Comm ou RH), jamais redemandé | F28: Choix | G28: Demandée | H28: Essentiel | I28: — | J28: — | K28: ● | L28: ● | M28: ● | N28: — | O28: — | P28: — | Q28: — | R28: Nouveau
A29: RH-05.11 | B29: RH-05 | C29: =IFERROR(INDEX(Thèmes!$D$2:$D$190,MATCH(B29,Thèmes!$A$2:$A$190,0)),"") | D29: — | E29: Semaines de congés réellement prises par le dirigeant sur 12 mois (lu avec RH-05.10 : capacité à s'absenter) | F29: Semaines | G29: Demandée | H29: Essentiel | I29: — | J29: Période adaptée : depuis la création si moins de 12 mois | K29: ● | L29: ● | M29: ● | N29: — | O29: — | P29: — | Q29: — | R29: Nouveau
A30: RH-06.01 | B30: RH-06 | C30: =IFERROR(INDEX(Thèmes!$D$2:$D$190,MATCH(B30,Thèmes!$A$2:$A$190,0)),"") | D30: R05 · La charge de l'équipe | E30: Heures prévues au contrat par semaine, en moyenne | F30: Heures | G30: Demandée | H30: Essentiel | I30: — | J30: — | L30: ● | M30: ● | N30: Mesure | O30: — | P30: — | Q30: RH-06.08, RH-08.07, RH-28.07
A31: RH-06.02 | B31: RH-06 | C31: =IFERROR(INDEX(Thèmes!$D$2:$D$190,MATCH(B31,Thèmes!$A$2:$A$190,0)),"") | D31: R05 · La charge de l'équipe | E31: Heures réellement travaillées par semaine et par personne, en moyenne | F31: Heures | G31: Demandée | H31: Essentiel | I31: — | J31: — | L31: ● | M31: ● | N31: Capacité | O31: — | P31: — | Q31: RH-06.08, RH-09.05, RH-17.05, RH-19.06
A32: RH-06.03 | B32: RH-06 | C32: =IFERROR(INDEX(Thèmes!$D$2:$D$190,MATCH(B32,Thèmes!$A$2:$A$190,0)),"") | D32: F03 · Votre masse salariale | E32: Heures supplémentaires par mois et leur coût | F32: Heures et € | G32: Partagée | H32: Essentiel | I32: — | J32: — | L32: ● | M32: ● | N32: Capacité | O32: Posée une seule fois, par le premier agent souscrit qui en a besoin (FIN-07.05), sinon ici | P32: FIN-07.05 | Q32: XR08, XR28
A33: RH-06.04 | B33: RH-06 | C33: =IFERROR(INDEX(Thèmes!$D$2:$D$190,MATCH(B33,Thèmes!$A$2:$A$190,0)),"") | D33: F03 · Votre masse salariale | E33: Masse salariale chargée par mois (salaires + charges patronales, hors dirigeant) | F33: € | G33: Partagée | H33: Essentiel | I33: — | J33: — | L33: ● | M33: ● | N33: Mesure | O33: Posée une seule fois, par le premier agent souscrit qui en a besoin (FIN-07.01), sinon ici | P33: FIN-07.01 | Q33: XR14, XR28
A34: RH-06.05 | B34: RH-06 | C34: =IFERROR(INDEX(Thèmes!$D$2:$D$190,MATCH(B34,Thèmes!$A$2:$A$190,0)),"") | D34: R05 · La charge de l'équipe | E34: Semaines avec des heures supplémentaires sur les 3 derniers mois — déclencheur D46 | F34: Choix : aucune · 1-3 · 4-8 · presque toutes | G34: Demandée | H34: Essentiel | I34: — | J34: Période adaptée : depuis la création si moins de 3 mois | L34: ● | M34: ● | N34: Problème | O34: — | P34: — | Q34: RH-06.09, RH-11.03, XR08 | R34: Libellé (« Donnée »)
A35: RH-06.06 | B35: RH-06 | C35: =IFERROR(INDEX(Thèmes!$D$2:$D$190,MATCH(B35,Thèmes!$A$2:$A$190,0)),"") | D35: R05 · La charge de l'équipe | E35: Les heures supplémentaires sont : payées, récupérées, ni l'un ni l'autre | F35: Choix | G35: Demandée | H35: Approfondi | I35: D46 · s'il y a des heures supplémentaires | J35: — | L35: ● | M35: ● | N35: Risque | O35: — | P35: — | Q35: Lue par l'IA pour adapter le conseil | R35: Condition d'affichage
A36: RH-06.07 | B36: RH-06 | C36: =IFERROR(INDEX(Thèmes!$D$2:$D$190,MATCH(B36,Thèmes!$A$2:$A$190,0)),"") | D36: R05 · La charge de l'équipe | E36: Fonctions qui font le plus d'heures supplémentaires | F36: Choix | G36: Demandée | H36: Approfondi | I36: D46 · s'il y a des heures supplémentaires | J36: — | L36: ● | M36: ● | N36: Levier | O36: — | P36: — | Q36: Lue par l'IA pour adapter le conseil | R36: Condition d'affichage
A37: RH-06.08 | B37: RH-06 | C37: =IFERROR(INDEX(Thèmes!$D$2:$D$190,MATCH(B37,Thèmes!$A$2:$A$190,0)),"") | D37: — | E37: Écart entre heures réelles et heures prévues | F37: Heures et % | G37: Calculée | H37: — | I37: — | J37: — | L37: ● | M37: ● | N37: Problème | O37: Heures réelles − heures du contrat, puis ÷ heures du contrat | P37: RH-06.02, RH-06.01 | Q37: RH-06.09, XR08
A38: RH-06.09 | B38: RH-06 | C38: =IFERROR(INDEX(Thèmes!$D$2:$D$190,MATCH(B38,Thèmes!$A$2:$A$190,0)),"") | D38: — | E38: Surcharge ponctuelle ou structurelle | F38: Choix | G38: Calculée | H38: — | I38: — | J38: — | L38: ● | M38: ● | N38: Risque | O38: Structurelle si des heures supplémentaires plus d'une semaine sur deux, ou heures réelles supérieures de 10 % au contrat | P38: RH-06.05, RH-06.08 | Q38: XR08
A39: RH-07.01 | B39: RH-07 | C39: =IFERROR(INDEX(Thèmes!$D$2:$D$190,MATCH(B39,Thèmes!$A$2:$A$190,0)),"") | D39: R06 · La capacité disponible (tableau par fonction) | E39: Heures que l'équipe (ou vous seul) pourrait consacrer à du travail en plus chaque semaine, sans heures supplémentaires, par fonction : production, commercial, administratif | F39: Tableau 3 lignes (heures) | G39: Demandée | H39: Essentiel | I39: — | J39: — | K39: ● | L39: ● | M39: ● | N39: Capacité | O39: — | P39: — | Q39: RH-07.03, RH-07.04
A40: RH-07.02 | B40: RH-07 | C40: =IFERROR(INDEX(Thèmes!$D$2:$D$190,MATCH(B40,Thèmes!$A$2:$A$190,0)),"") | D40: R06 · La capacité disponible (tableau par fonction) | E40: Heures en plus acceptables ponctuellement par semaine, sans surcharge | F40: Heures | G40: Demandée | H40: Approfondi | I40: — | J40: — | L40: ● | M40: ● | N40: Capacité | O40: — | P40: — | Q40: Lue par l'IA pour adapter le conseil
A41: RH-07.03 | B41: RH-07 | C41: =IFERROR(INDEX(Thèmes!$D$2:$D$190,MATCH(B41,Thèmes!$A$2:$A$190,0)),"") | D41: — | E41: Capacité disponible totale | F41: Heures | G41: Calculée | H41: — | I41: — | J41: — | K41: ● | L41: ● | M41: ● | N41: Capacité | O41: Somme des trois fonctions | P41: RH-07.01 | Q41: RH-07.04, XR09
A42: RH-07.04 | B42: RH-07 | C42: =IFERROR(INDEX(Thèmes!$D$2:$D$190,MATCH(B42,Thèmes!$A$2:$A$190,0)),"") | D42: — | E42: Capacité réellement utile pour vendre plus | F42: Heures et % | G42: Calculée | H42: — | I42: — | J42: — | K42: ● | L42: ● | M42: ● | N42: Capacité | O42: Heures disponibles sur la fonction qui produit ce que vous vendez, puis ÷ capacité totale | P42: RH-07.01, RH-07.03 | Q42: RH-07.05, XR09
A43: RH-07.05 | B43: RH-07 | C43: =IFERROR(INDEX(Thèmes!$D$2:$D$190,MATCH(B43,Thèmes!$A$2:$A$190,0)),"") | D43: — | E43: Ventes, dossiers ou chantiers absorbables sans recruter | F43: Nombre par mois | G43: Calculée | H43: — | I43: — | J43: — | K43: ● | L43: ● | M43: ● | N43: Potentiel CA | O43: Heures utiles × 4,33 ÷ temps moyen par vente (heures travaillées ÷ ventes du mois) | P43: RH-07.04, ACQ-21.04, ACQ-21.02, ACQ-21.06 | Q43: RH-07.06, XR10
A44: RH-07.06 | B44: RH-07 | C44: =IFERROR(INDEX(Thèmes!$D$2:$D$190,MATCH(B44,Thèmes!$A$2:$A$190,0)),"") | D44: — | E44: Part de l'objectif absorbable avec la capacité actuelle | F44: % | G44: Calculée | H44: — | I44: — | J44: — | K44: ● | L44: ● | M44: ● | N44: Cible | O44: Ventes absorbables ÷ ventes supplémentaires nécessaires pour l'objectif | P44: RH-07.05, Inscription · objectif chiffré, Inscription · CA mensuel, ACQ-15.06 | Q44: XR11, XR27
A45: RH-08.01 | B45: RH-08 | C45: =IFERROR(INDEX(Thèmes!$D$2:$D$190,MATCH(B45,Thèmes!$A$2:$A$190,0)),"") | D45: R07 · La personne la plus chargée | E45: Fonction de la personne la plus chargée, vous compris. Définition : celle dont le retard bloque le plus souvent les autres | F45: Choix | G45: Demandée | H45: Essentiel | I45: — | J45: — | L45: ● | M45: ● | N45: Risque | O45: — | P45: — | Q45: XR12
A46: RH-08.02 | B46: RH-08 | C46: =IFERROR(INDEX(Thèmes!$D$2:$D$190,MATCH(B46,Thèmes!$A$2:$A$190,0)),"") | D46: R07 · La personne la plus chargée | E46: Ses heures réelles par semaine | F46: Heures | G46: Demandée | H46: Essentiel | I46: D27 · si ce n'est pas vous (sinon RH-05) | J46: — | L46: ● | M46: ● | N46: Capacité | O46: — | P46: — | Q46: RH-08.07
A47: RH-08.03 | B47: RH-08 | C47: =IFERROR(INDEX(Thèmes!$D$2:$D$190,MATCH(B47,Thèmes!$A$2:$A$190,0)),"") | D47: R07 · La personne la plus chargée | E47: Personnes qui attendent son travail pour avancer | F47: Nombre | G47: Demandée | H47: Essentiel | I47: — | J47: — | L47: ● | M47: ● | N47: Risque | O47: — | P47: — | Q47: RH-08.08, XR12
A48: RH-08.04 | B48: RH-08 | C48: =IFERROR(INDEX(Thèmes!$D$2:$D$190,MATCH(B48,Thèmes!$A$2:$A$190,0)),"") | D48: R07 · La personne la plus chargée | E48: Heures par semaine de ses tâches qu'une autre personne pourrait reprendre | F48: Tranches : 0 · 1-3 h · 3-6 h · 6-10 h · plus de 10 h · je ne sais pas | G48: Demandée | H48: Essentiel | I48: D27 · si ce n'est pas vous (sinon RH-05) | J48: — | L48: ● | M48: ● | N48: Levier | O48: — | P48: — | Q48: XR07, XR12
A49: RH-08.05 | B49: RH-08 | C49: =IFERROR(INDEX(Thèmes!$D$2:$D$190,MATCH(B49,Thèmes!$A$2:$A$190,0)),"") | D49: R07 · La personne la plus chargée | E49: Cette surcharge est : liée à un pic, permanente | F49: Choix | G49: Demandée | H49: Approfondi | I49: — | J49: — | L49: ● | M49: ● | N49: Risque | O49: — | P49: — | Q49: XR12 | R49: Niveau
A50: RH-08.06 | B50: RH-08 | C50: =IFERROR(INDEX(Thèmes!$D$2:$D$190,MATCH(B50,Thèmes!$A$2:$A$190,0)),"") | D50: R07 · La personne la plus chargée | E50: Travail en attente chez elle : aucun, quelques jours, plus d'une semaine | F50: Choix | G50: Demandée | H50: Approfondi | I50: — | J50: — | L50: ● | M50: ● | N50: Problème | O50: — | P50: — | Q50: Lue par l'IA pour adapter le conseil
A51: RH-08.07 | B51: RH-08 | C51: =IFERROR(INDEX(Thèmes!$D$2:$D$190,MATCH(B51,Thèmes!$A$2:$A$190,0)),"") | D51: — | E51: Charge de la personne la plus chargée par rapport à un temps plein | F51: % | G51: Calculée | H51: — | I51: — | J51: — | L51: ● | M51: ● | N51: Problème | O51: Heures réelles ÷ heures prévues au contrat (si c'est vous : vos heures, RH-05, ÷ 35 h) | P51: RH-08.02, RH-06.01, RH-05.01 | Q51: RH-08.08, XR12
A52: RH-08.08 | B52: RH-08 | C52: =IFERROR(INDEX(Thèmes!$D$2:$D$190,MATCH(B52,Thèmes!$A$2:$A$190,0)),"") | D52: — | E52: Goulot d'étranglement humain | F52: Oui / non | G52: Calculée | H52: — | I52: — | J52: — | L52: ● | M52: ● | N52: Risque | O52: Oui si charge supérieure à 120 % et au moins 2 personnes qui attendent son travail | P52: RH-08.07, RH-08.03 | Q52: XR12
A53: RH-09.01 | B53: RH-09 | C53: =IFERROR(INDEX(Thèmes!$D$2:$D$190,MATCH(B53,Thèmes!$A$2:$A$190,0)),"") | D53: R08 · Urgences et interruptions | E53: Part du temps passée dans l'urgence. Définition : tâche non prévue à traiter tout de suite (problème client, retard, erreur, oubli, commande de dernière minute, rupture, incident, demande interne bloquante) | F53: Tranches : moins de 10 % · 10-25 % · 25-50 % · plus de 50 % · je ne sais pas | G53: Demandée | H53: Essentiel | I53: — | J53: — | K53: ● | L53: ● | M53: ● | N53: Problème | O53: — | P53: — | Q53: RH-09.05, RH-09.07
A54: RH-09.02 | B54: RH-09 | C54: =IFERROR(INDEX(Thèmes!$D$2:$D$190,MATCH(B54,Thèmes!$A$2:$A$190,0)),"") | D54: R08 · Urgences et interruptions | E54: Causes les plus fréquentes (3 au plus) : demande client de dernière minute, erreur ou oubli interne, retard fournisseur, panne ou incident, manque de planification, absence imprévue | F54: Cases à cocher | G54: Demandée | H54: Approfondi | I54: — | J54: — | K54: ● | L54: ● | M54: ● | N54: Levier | O54: — | P54: — | Q54: XR13 | R54: Niveau
A55: RH-09.03 | B55: RH-09 | C55: =IFERROR(INDEX(Thèmes!$D$2:$D$190,MATCH(B55,Thèmes!$A$2:$A$190,0)),"") | D55: R08 · Urgences et interruptions | E55: Sur 10 urgences, combien auraient pu être anticipées ? | F55: Sur 10 : 0-2 · 3-5 · 6-8 · 9-10 · je ne sais pas | G55: Demandée | H55: Approfondi | I55: — | J55: — | K55: ● | L55: ● | M55: ● | N55: Levier | O55: — | P55: — | Q55: RH-09.06, RH-09.07 | R55: Niveau
A56: RH-09.04 | B56: RH-09 | C56: =IFERROR(INDEX(Thèmes!$D$2:$D$190,MATCH(B56,Thèmes!$A$2:$A$190,0)),"") | D56: R08 · Urgences et interruptions | E56: Effet le plus fréquent sur le travail prévu : décalé de quelques heures, de plusieurs jours, abandonné | F56: Choix | G56: Demandée | H56: Approfondi | I56: — | J56: — | K56: ● | L56: ● | M56: ● | N56: Problème | O56: — | P56: — | Q56: Lue par l'IA pour adapter le conseil
A57: RH-09.05 | B57: RH-09 | C57: =IFERROR(INDEX(Thèmes!$D$2:$D$190,MATCH(B57,Thèmes!$A$2:$A$190,0)),"") | D57: — | E57: Heures par semaine passées dans l'urgence | F57: Heures | G57: Calculée | H57: — | I57: — | J57: — | K57: ● | L57: ● | M57: ● | N57: Capacité | O57: Part dans l'urgence × heures travaillées de l'équipe (dirigeant seul : ses heures) | P57: RH-09.01, RH-06.02, Inscription · effectif, RH-05.01 | Q57: RH-09.06, XR13
A58: RH-09.06 | B58: RH-09 | C58: =IFERROR(INDEX(Thèmes!$D$2:$D$190,MATCH(B58,Thèmes!$A$2:$A$190,0)),"") | D58: — | E58: Heures d'urgence évitables par semaine | F58: Heures | G58: Calculée | H58: — | I58: — | J58: — | K58: ● | L58: ● | M58: ● | N58: Levier | O58: Heures dans l'urgence × part anticipable | P58: RH-09.05, RH-09.03 | Q58: XR13, XR27
A59: RH-09.07 | B59: RH-09 | C59: =IFERROR(INDEX(Thèmes!$D$2:$D$190,MATCH(B59,Thèmes!$A$2:$A$190,0)),"") | D59: — | E59: Fonctionnement en anticipation ou en réaction permanente | F59: Choix | G59: Calculée | H59: — | I59: — | J59: — | K59: ● | L59: ● | M59: ● | N59: Risque | O59: Réaction permanente si plus de 25 % du temps dans l'urgence et plus de la moitié des urgences anticipables (seuils à valider) | P59: RH-09.01, RH-09.03 | Q59: XR13
A60: RH-10.01 | B60: RH-10 | C60: =IFERROR(INDEX(Thèmes!$D$2:$D$190,MATCH(B60,Thèmes!$A$2:$A$190,0)),"") | D60: R08 · Urgences et interruptions | E60: Interruptions par jour, pour vous. Définition : arrêt non prévu d'une tâche en cours (appel, message, collègue, client, fournisseur, notification, demande de validation) | F60: Tranches : 0-2 · 3-5 · 6-10 · 11-20 · plus de 20 · je ne sais pas | G60: Demandée | H60: Essentiel | I60: — | J60: — | K60: ● | L60: ● | M60: ● | N60: Problème | O60: — | P60: — | Q60: RH-10.07
A61: RH-10.02 | B61: RH-10 | C61: =IFERROR(INDEX(Thèmes!$D$2:$D$190,MATCH(B61,Thèmes!$A$2:$A$190,0)),"") | D61: R08 · Urgences et interruptions | E61: Temps moyen perdu par interruption, reprise du fil comprise | F61: Tranches : moins de 2 min · 2-5 · 5-15 · plus de 15 min · je ne sais pas | G61: Demandée | H61: Essentiel | I61: — | J61: — | K61: ● | L61: ● | M61: ● | N61: Capacité | O61: — | P61: — | Q61: RH-10.07
A62: RH-10.03 | B62: RH-10 | C62: =IFERROR(INDEX(Thèmes!$D$2:$D$190,MATCH(B62,Thèmes!$A$2:$A$190,0)),"") | D62: R08 · Urgences et interruptions | E62: Source principale : téléphone, messages, collègues, clients, notifications | F62: Choix | G62: Demandée | H62: Approfondi | I62: — | J62: — | K62: ● | L62: ● | M62: ● | N62: Levier | O62: — | P62: — | Q62: XR03 | R62: Niveau
A63: RH-10.04 | B63: RH-10 | C63: =IFERROR(INDEX(Thèmes!$D$2:$D$190,MATCH(B63,Thèmes!$A$2:$A$190,0)),"") | D63: R08 · Urgences et interruptions | E63: Interruptions par jour pour un membre de l'équipe | F63: Tranches : 0-2 · 3-5 · 6-10 · 11-20 · plus de 20 · je ne sais pas | G63: Demandée | H63: Approfondi | I63: — | J63: — | L63: ● | M63: ● | N63: Problème | O63: — | P63: — | Q63: Lue par l'IA pour adapter le conseil
A64: RH-10.05 | B64: RH-10 | C64: =IFERROR(INDEX(Thèmes!$D$2:$D$190,MATCH(B64,Thèmes!$A$2:$A$190,0)),"") | D64: R08 · Urgences et interruptions | E64: Sur 10 interruptions, combien auraient pu attendre un moment prévu ? | F64: Sur 10 : 0-2 · 3-5 · 6-8 · 9-10 · je ne sais pas | G64: Demandée | H64: Approfondi | I64: — | J64: — | K64: ● | L64: ● | M64: ● | N64: Levier | O64: — | P64: — | Q64: RH-10.08
A65: RH-10.06 | B65: RH-10 | C65: =IFERROR(INDEX(Thèmes!$D$2:$D$190,MATCH(B65,Thèmes!$A$2:$A$190,0)),"") | D65: R08 · Urgences et interruptions | E65: Moment de la journée le plus touché | F65: Choix | G65: Demandée | H65: Approfondi | I65: — | J65: — | K65: ● | L65: ● | M65: ● | N65: Levier | O65: — | P65: — | Q65: XR03
A66: RH-10.07 | B66: RH-10 | C66: =IFERROR(INDEX(Thèmes!$D$2:$D$190,MATCH(B66,Thèmes!$A$2:$A$190,0)),"") | D66: — | E66: Temps fragmenté par les interruptions, par semaine | F66: Heures | G66: Calculée | H66: — | I66: — | J66: — | K66: ● | L66: ● | M66: ● | N66: Capacité | O66: Interruptions par jour × temps perdu × jours travaillés | P66: RH-10.01, RH-10.02, ACQ-22.01 | Q66: RH-10.08, XR03
A67: RH-10.08 | B67: RH-10 | C67: =IFERROR(INDEX(Thèmes!$D$2:$D$190,MATCH(B67,Thèmes!$A$2:$A$190,0)),"") | D67: — | E67: Heures récupérables en regroupant les interruptions évitables | F67: Heures | G67: Calculée | H67: — | I67: — | J67: — | K67: ● | L67: ● | M67: ● | N67: Levier | O67: Temps fragmenté × part évitable | P67: RH-10.07, RH-10.05 | Q67: RH-05.08, XR03
A68: RH-11.01 | B68: RH-11 | C68: =IFERROR(INDEX(Thèmes!$D$2:$D$190,MATCH(B68,Thèmes!$A$2:$A$190,0)),"") | D68: A23 · Vos 12 derniers mois (tableau) | E68: CA de chacun des 12 derniers mois | F68: 12 montants | G68: Partagée | H68: Essentiel | I68: — | J68: Période adaptée : depuis la création si moins de 12 mois | K68: ● | L68: ● | M68: ● | N68: Problème | O68: Posée une seule fois, par le premier agent souscrit qui en a besoin (ACQ-23.01), sinon ici | P68: ACQ-23.01 | Q68: Affichée dans le rapport
A69: RH-11.02 | B69: RH-11 | C69: =IFERROR(INDEX(Thèmes!$D$2:$D$190,MATCH(B69,Thèmes!$A$2:$A$190,0)),"") | D69: R05 · La charge de l'équipe | E69: Pendant vos mois forts, vous ajoutez : intérim ou extras, heures supplémentaires, rien | F69: Choix | G69: Demandée | H69: Essentiel | I69: — | J69: — | L69: ● | M69: ● | N69: Levier | O69: — | P69: — | Q69: RH-11.03, XR30
A70: RH-11.03 | B70: RH-11 | C70: =IFERROR(INDEX(Thèmes!$D$2:$D$190,MATCH(B70,Thèmes!$A$2:$A$190,0)),"") | D70: — | E70: Mois forts sans renfort prévu | F70: Liste de mois | G70: Calculée | H70: — | I70: — | J70: — | L70: ● | M70: ● | N70: Risque | O70: Mois forts croisés avec l'absence de renfort et les semaines d'heures supplémentaires | P70: ACQ-23.05, RH-11.02, RH-06.05 | Q70: XR30
A71: RH-12.01 | B71: RH-12 | C71: =IFERROR(INDEX(Thèmes!$D$2:$D$190,MATCH(B71,Thèmes!$A$2:$A$190,0)),"") | D71: R09 · Méthodes, informations et outils | E71: Tâches clés de l'activité, et combien sont décrites par écrit (procédure, liste, vidéo) | F71: Nombre et nombre | G71: Demandée | H71: Essentiel | I71: — | J71: — | K71: ● | L71: ● | M71: ● | N71: Risque | O71: — | P71: — | Q71: RH-12.02, RH-27.02
A72: RH-12.02 | B72: RH-12 | C72: =IFERROR(INDEX(Thèmes!$D$2:$D$190,MATCH(B72,Thèmes!$A$2:$A$190,0)),"") | D72: — | E72: Part des tâches clés décrites par écrit | F72: % | G72: Calculée | H72: — | I72: — | J72: — | K72: ● | L72: ● | M72: ● | N72: Cible | O72: Tâches décrites ÷ tâches clés | P72: RH-12.01 | Q72: XR23, XR24
A73: RH-13.01 | B73: RH-13 | C73: =IFERROR(INDEX(Thèmes!$D$2:$D$190,MATCH(B73,Thèmes!$A$2:$A$190,0)),"") | D73: R09 · Méthodes, informations et outils | E73: Quand quelqu'un est absent, son travail est repris : grâce à des consignes écrites, à l'oral, pas repris | F73: Choix | G73: Demandée | H73: Essentiel | I73: — | J73: — | L73: ● | M73: ● | N73: Risque | O73: — | P73: — | Q73: Notée directement (couleur du thème)
A74: RH-14.01 | B74: RH-14 | C74: =IFERROR(INDEX(Thèmes!$D$2:$D$190,MATCH(B74,Thèmes!$A$2:$A$190,0)),"") | D74: R09 · Méthodes, informations et outils | E74: Les informations utiles (dossiers clients, accès, tarifs) sont : dans un espace partagé, en partie, chacun garde les siennes | F74: Choix | G74: Demandée | H74: Essentiel | I74: — | J74: — | L74: ● | M74: ● | N74: Risque | O74: — | P74: — | Q74: XR25
A75: RH-14.02 | B75: RH-14 | C75: =IFERROR(INDEX(Thèmes!$D$2:$D$190,MATCH(B75,Thèmes!$A$2:$A$190,0)),"") | D75: R09 · Méthodes, informations et outils | E75: Temps perdu par semaine et par personne à chercher une information ou à attendre quelqu'un pour l'avoir | F75: Tranches : 0 · 1-3 h · 3-6 h · 6-10 h · plus de 10 h · je ne sais pas | G75: Demandée | H75: Approfondi | I75: — | J75: — | K75: ● | L75: ● | M75: ● | N75: Capacité | O75: — | P75: — | Q75: RH-14.03
A76: RH-14.03 | B76: RH-14 | C76: =IFERROR(INDEX(Thèmes!$D$2:$D$190,MATCH(B76,Thèmes!$A$2:$A$190,0)),"") | D76: — | E76: Temps perdu à chercher l'information, toute l'équipe | F76: Heures par semaine | G76: Calculée | H76: — | I76: — | J76: — | K76: ● | L76: ● | M76: ● | N76: Capacité | O76: Temps perdu par personne × effectif | P76: RH-14.02, Inscription · effectif | Q76: XR25
A77: RH-15.01 | B77: RH-15 | C77: =IFERROR(INDEX(Thèmes!$D$2:$D$190,MATCH(B77,Thèmes!$A$2:$A$190,0)),"") | D77: R09 · Méthodes, informations et outils | E77: Outils pour organiser le travail (planning partagé, gestion de tâches, logiciel métier, messagerie d'équipe), et utilisés par tous : oui, en partie, non | F77: Cases + choix | G77: Demandée | H77: Essentiel | I77: — | J77: — | K77: ● | L77: ● | M77: ● | N77: Levier | O77: — | P77: — | Q77: Notée directement (couleur du thème)
A78: RH-15.02 | B78: RH-15 | C78: =IFERROR(INDEX(Thèmes!$D$2:$D$190,MATCH(B78,Thèmes!$A$2:$A$190,0)),"") | D78: R09 · Méthodes, informations et outils | E78: Matériel qui ralentit le travail — déclencheur D47 | F78: Oui / non + heures | G78: Demandée | H78: Approfondi | I78: — | J78: — | K78: ● | L78: ● | M78: ● | N78: Capacité | O78: — | P78: — | Q78: XR29 | R78: Libellé (« Donnée »)
A79: RH-15.03 | B79: RH-15 | C79: =IFERROR(INDEX(Thèmes!$D$2:$D$190,MATCH(B79,Thèmes!$A$2:$A$190,0)),"") | D79: — | E79: Heures perdues par semaine à cause du matériel | F79: Heures | G79: Demandée | H79: Approfondi | I79: D47 · si du matériel ralentit le travail | J79: — | K79: ● | L79: ● | M79: ● | N79: — | O79: — | P79: — | Q79: — | R79: Nouveau
A80: RH-16.01 | B80: RH-16 | C80: =IFERROR(INDEX(Thèmes!$D$2:$D$190,MATCH(B80,Thèmes!$A$2:$A$190,0)),"") | D80: F07 · Vos erreurs et gestes commerciaux | E80: Reprises par mois et temps moyen d'une reprise — champs partagés avec FIN-10.01 (reprises par mois) et FIN-10.03 (heures par reprise) : chaque chiffre n'est demandé qu'une fois, le second agent reprend la réponse — déclencheur D49 | F80: Nombre et heures | G80: Partagée | H80: Essentiel | I80: — | J80: — | K80: ● | L80: ● | M80: ● | N80: Perte | O80: Posée une seule fois, par le premier agent souscrit qui en a besoin (FIN-10.01, FIN-10.03), sinon ici | P80: FIN-10.01, FIN-10.03 | Q80: RH-16.05 | R80: Libellé (« Donnée »)
A81: RH-16.02 | B81: RH-16 | C81: =IFERROR(INDEX(Thèmes!$D$2:$D$190,MATCH(B81,Thèmes!$A$2:$A$190,0)),"") | D81: R10 · Les reprises | E81: Cause principale : erreur humaine, consignes incomplètes, pas de procédure, mauvaise information, problème logiciel, problème fournisseur, mauvaise communication, manque de formation | F81: Choix | G81: Demandée | H81: Approfondi | I81: D49 · si vous avez des reprises | J81: — | K81: ● | L81: ● | M81: ● | N81: Levier | O81: — | P81: — | Q81: XR14 | R81: Condition d'affichage · Niveau
A82: RH-16.03 | B82: RH-16 | C82: =IFERROR(INDEX(Thèmes!$D$2:$D$190,MATCH(B82,Thèmes!$A$2:$A$190,0)),"") | D82: R10 · Les reprises | E82: Parmi les reprises : corrections mineures, reprises complètes | F82: 2 nombres | G82: Demandée | H82: Approfondi | I82: D49 · si vous avez des reprises | J82: — | K82: ● | L82: ● | M82: ● | N82: Problème | O82: — | P82: — | Q82: Lue par l'IA pour adapter le conseil | R82: Condition d'affichage
A83: RH-16.04 | B83: RH-16 | C83: =IFERROR(INDEX(Thèmes!$D$2:$D$190,MATCH(B83,Thèmes!$A$2:$A$190,0)),"") | D83: R10 · Les reprises | E83: Fonctions les plus concernées | F83: Choix | G83: Demandée | H83: Approfondi | I83: D49 · si vous avez des reprises | J83: — | L83: ● | M83: ● | N83: Levier | O83: — | P83: — | Q83: Lue par l'IA pour adapter le conseil | R83: Condition d'affichage
A84: RH-16.05 | B84: RH-16 | C84: =IFERROR(INDEX(Thèmes!$D$2:$D$190,MATCH(B84,Thèmes!$A$2:$A$190,0)),"") | D84: — | E84: Temps perdu en reprises par mois | F84: Heures | G84: Calculée | H84: — | I84: — | J84: — | K84: ● | L84: ● | M84: ● | N84: Perte | O84: Reprises × temps moyen | P84: FIN-10.01, FIN-10.03 | Q84: XR14
A85: RH-17.01 | B85: RH-17 | C85: =IFERROR(INDEX(Thèmes!$D$2:$D$190,MATCH(B85,Thèmes!$A$2:$A$190,0)),"") | D85: R11 · Les tâches répétitives (tableau) | E85: Vos 3 tâches répétitives les plus longues : laquelle (ressaisie, copier-coller, reporting, facturation, planification, emails, relances, saisie administrative, documents, réponses clients répétitives), heures par semaine, qui la fait, outil utilisé | F85: Tableau 3 × 4 | G85: Demandée | H85: Approfondi | I85: — | J85: — | K85: ● | L85: ● | M85: ● | N85: Levier | O85: — | P85: — | Q85: RH-17.03, RH-17.04, XR07, XR15 | R85: Niveau
A86: RH-17.02 | B86: RH-17 | C86: =IFERROR(INDEX(Thèmes!$D$2:$D$190,MATCH(B86,Thèmes!$A$2:$A$190,0)),"") | D86: R11 · Les tâches répétitives (tableau) | E86: Heures par semaine sur des tâches répétitives, toute l'équipe | F86: Tranches : 0 · 1-3 h · 3-6 h · 6-10 h · plus de 10 h · je ne sais pas | G86: Demandée | H86: Essentiel | I86: — | J86: — | K86: ● | L86: ● | M86: ● | N86: Capacité | O86: — | P86: — | Q86: RH-17.05
A87: RH-17.03 | B87: RH-17 | C87: =IFERROR(INDEX(Thèmes!$D$2:$D$190,MATCH(B87,Thèmes!$A$2:$A$190,0)),"") | D87: — | E87: Chaque tâche classée : à supprimer, automatiser, confier ou standardiser | F87: Choix par tâche | G87: Calculée | H87: — | I87: — | J87: — | K87: ● | L87: ● | M87: ● | N87: Levier | O87: Classée par l'IA selon le type de tâche et l'outil déclaré | P87: RH-17.01 | Q87: RH-17.04
A88: RH-17.04 | B88: RH-17 | C88: =IFERROR(INDEX(Thèmes!$D$2:$D$190,MATCH(B88,Thèmes!$A$2:$A$190,0)),"") | D88: — | E88: Heures récupérables par l'automatisation | F88: Heures par semaine | G88: Calculée | H88: — | I88: — | J88: — | K88: ● | L88: ● | M88: ● | N88: Levier | O88: Heures des tâches classées « automatiser » × part automatisable prudente | P88: RH-17.01, RH-17.03 | Q88: XR15, XR27
A89: RH-17.05 | B89: RH-17 | C89: =IFERROR(INDEX(Thèmes!$D$2:$D$190,MATCH(B89,Thèmes!$A$2:$A$190,0)),"") | D89: — | E89: Part du temps de l'équipe passée sur des tâches répétitives | F89: % | G89: Calculée | H89: — | I89: — | J89: — | K89: ● | L89: ● | M89: ● | N89: Problème | O89: Heures répétitives ÷ heures travaillées de l'équipe | P89: RH-17.02, RH-06.02, Inscription · effectif, RH-05.01 | Q89: XR15
A90: RH-18.01 | B90: RH-18 | C90: =IFERROR(INDEX(Thèmes!$D$2:$D$190,MATCH(B90,Thèmes!$A$2:$A$190,0)),"") | D90: R12 · Réunions et échanges | E90: Les priorités de la semaine sont partagées avec l'équipe : par écrit, à l'oral, pas vraiment | F90: Choix | G90: Demandée | H90: Essentiel | I90: — | J90: — | L90: ● | M90: ● | N90: Levier | O90: — | P90: — | Q90: Notée directement (couleur du thème)
A91: RH-19.01 | B91: RH-19 | C91: =IFERROR(INDEX(Thèmes!$D$2:$D$190,MATCH(B91,Thèmes!$A$2:$A$190,0)),"") | D91: R12 · Réunions et échanges | E91: Réunions d'équipe : nombre par mois, durée moyenne, participants — déclencheur D50 | F91: 3 nombres | G91: Demandée | H91: Essentiel | I91: — | J91: — | L91: ● | M91: ● | N91: Capacité | O91: — | P91: — | Q91: RH-19.05, RH-19.06 | R91: Libellé (« Donnée »)
A92: RH-19.02 | B92: RH-19 | C92: =IFERROR(INDEX(Thèmes!$D$2:$D$190,MATCH(B92,Thèmes!$A$2:$A$190,0)),"") | D92: R12 · Réunions et échanges | E92: Ces réunions ont un ordre du jour et finissent par des décisions notées : toujours, parfois, jamais | F92: Choix | G92: Demandée | H92: Essentiel | I92: D50 · si vous faites des réunions | J92: — | M92: ● | N92: Levier | O92: — | P92: — | Q92: RH-19.06 | R92: Condition d'affichage
A93: RH-19.03 | B93: RH-19 | C93: =IFERROR(INDEX(Thèmes!$D$2:$D$190,MATCH(B93,Thèmes!$A$2:$A$190,0)),"") | D93: R12 · Réunions et échanges | E93: Entretiens individuels : jamais, une fois par an, chaque trimestre, chaque mois — et date du dernier | F93: Choix + date | G93: Demandée | H93: Essentiel | I93: — | J93: — | L93: ● | M93: ● | N93: Levier | O93: — | P93: — | Q93: RH-19.06
A94: RH-19.04 | B94: RH-19 | C94: =IFERROR(INDEX(Thèmes!$D$2:$D$190,MATCH(B94,Thèmes!$A$2:$A$190,0)),"") | D94: R12 · Réunions et échanges | E94: Part des réunions vraiment utiles selon vous | F94: Tranches : moins de 10 % · 10-25 % · 25-50 % · plus de 50 % · je ne sais pas | G94: Demandée | H94: Approfondi | I94: D50 · si vous faites des réunions | J94: — | M94: ● | N94: Problème | O94: — | P94: — | Q94: XR16 | R94: Condition d'affichage
A95: RH-19.05 | B95: RH-19 | C95: =IFERROR(INDEX(Thèmes!$D$2:$D$190,MATCH(B95,Thèmes!$A$2:$A$190,0)),"") | D95: — | E95: Temps total passé en réunion par mois, toutes personnes comprises | F95: Heures | G95: Calculée | H95: — | I95: — | J95: — | L95: ● | M95: ● | N95: Capacité | O95: Réunions × durée × participants | P95: RH-19.01 | Q95: RH-19.06, XR16
A96: RH-19.06 | B96: RH-19 | C96: =IFERROR(INDEX(Thèmes!$D$2:$D$190,MATCH(B96,Thèmes!$A$2:$A$190,0)),"") | D96: — | E96: Absence de communication, réunions utiles, ou surcharge de réunions | F96: Choix | G96: Calculée | H96: — | I96: — | J96: — | L96: ● | M96: ● | N96: Problème | O96: Absence : ni réunion ni entretien. Surcharge : plus de 10 % du temps en réunion et peu de décisions. Sinon : utiles (seuils à valider). Plus de réunions n'est jamais lu comme un meilleur management | P96: RH-19.01, RH-19.05, RH-19.02, RH-19.03, RH-06.02 | Q96: XR16
A97: RH-20.01 | B97: RH-20 | C97: =IFERROR(INDEX(Thèmes!$D$2:$D$190,MATCH(B97,Thèmes!$A$2:$A$190,0)),"") | D97: R12 · Réunions et échanges | E97: Retour à chacun sur ce qui va et ce qui ne va pas : chaque semaine, chaque mois, rarement | F97: Choix | G97: Demandée | H97: Essentiel | I97: — | J97: — | L97: ● | M97: ● | N97: Levier | O97: — | P97: — | Q97: Notée directement (couleur du thème)
A98: RH-21.01 | B98: RH-21 | C98: =IFERROR(INDEX(Thèmes!$D$2:$D$190,MATCH(B98,Thèmes!$A$2:$A$190,0)),"") | D98: R12 · Réunions et échanges | E98: Quand l'équipe a besoin de vous, elle obtient une réponse : dans l'heure, dans la journée, plus tard | F98: Choix | G98: Demandée | H98: Essentiel | I98: — | J98: — | L98: ● | M98: ● | N98: Problème | O98: — | P98: — | Q98: Notée directement (couleur du thème)
A99: RH-22.01 | B99: RH-22 | C99: =IFERROR(INDEX(Thèmes!$D$2:$D$190,MATCH(B99,Thèmes!$A$2:$A$190,0)),"") | D99: R12 · Réunions et échanges | E99: Moyen prévu pour que l'équipe signale un problème ou une idée (réunion, outil, boîte à idées), et idées appliquées sur 6 mois | F99: Oui / non + nombre | G99: Demandée | H99: Essentiel | I99: — | J99: Période adaptée : depuis la création si moins de 6 mois | M99: ● | N99: Levier | O99: — | P99: — | Q99: Notée directement (couleur du thème)
A100: RH-23.01 | B100: RH-23 | C100: =IFERROR(INDEX(Thèmes!$D$2:$D$190,MATCH(B100,Thèmes!$A$2:$A$190,0)),"") | D100: R13 · Compétences et formation | E100: Compétences nécessaires que personne n'a dans l'entreprise, et comment vous faites aujourd'hui : sous-traitance, vous-même, pas fait | F100: Liste + choix | G100: Demandée | H100: Essentiel | I100: — | J100: — | K100: ● | L100: ● | M100: ● | N100: Risque | O100: — | P100: — | Q100: Notée directement (couleur du thème)
...

Sheet Comm — données
A1: Code | B1: Thème | C1: Nom du thème | D1: Écran | E1: Donnée | F1: Format de réponse | G1: Mode | H1: Niveau | I1: Condition d'affichage | J1: Période (selon l'ancienneté) | K1: RDV | L1: Commerce | M1: E-commerce | N1: Restaurant | O1: Chantier | P1: B2B | Q1: Abonnement | R1: Location | S1: Sert à | T1: Calcul ou source | U1: Données utilisées | V1: Utilisée dans | W1: Changement du 20 oct.
A2: COM-01.01 | B2: COM-01 | C2: =IFERROR(INDEX(Thèmes!$D$2:$D$190,MATCH(B2,Thèmes!$A$2:$A$190,0)),"") | D2: C01 · Votre positionnement et votre offre | E2: Votre entreprise en une phrase : ce que vous faites, pour qui, et en quoi vous êtes différent | F2: Texte court | G2: Demandée | H2: Essentiel | I2: — | J2: — | K2: ● | L2: ● | M2: ● | N2: ● | O2: ● | P2: ● | Q2: ● | R2: ● | S2: Problème | T2: — | U2: — | V2: COM-01.02
A3: COM-01.02 | B3: COM-01 | C3: =IFERROR(INDEX(Thèmes!$D$2:$D$190,MATCH(B3,Thèmes!$A$2:$A$190,0)),"") | D3: — | E3: Positionnement clair : cible, résultat et différence présents dans la phrase | F3: Oui / partiel / non | G3: Calculée | H3: — | I3: — | J3: — | K3: ● | L3: ● | M3: ● | N3: ● | O3: ● | P3: ● | Q3: ● | R3: ● | S3: Problème | T3: Grille fixe de 3 critères appliquée par l'IA | U3: COM-01.01 | V3: Affichée dans le rapport
A4: COM-02.01 | B4: COM-02 | C4: =IFERROR(INDEX(Thèmes!$D$2:$D$190,MATCH(B4,Thèmes!$A$2:$A$190,0)),"") | D4: C01 · Votre positionnement et votre offre | E4: Client que votre communication cherche à attirer en priorité (choisi parmi vos types de clients) | F4: Choix dans la liste | G4: Demandée | H4: Essentiel | I4: — | J4: — | K4: ● | L4: ● | M4: ● | N4: ● | O4: ● | P4: ● | Q4: ● | R4: ● | S4: Cible | T4: — | U4: — | V4: COM-02.02, COM-06.01, COM-11.01, COM-54.01
A5: COM-02.02 | B5: COM-02 | C5: =IFERROR(INDEX(Thèmes!$D$2:$D$190,MATCH(B5,Thèmes!$A$2:$A$190,0)),"") | D5: — | E5: Cible de la communication comparée aux clients qui rapportent le plus | F5: Oui / non | G5: Calculée | H5: — | I5: — | J5: — | K5: ● | L5: ● | M5: ● | N5: ● | O5: ● | P5: ● | Q5: ● | R5: ● | S5: Cible | T5: Cible déclarée face au type de client à la plus forte valeur annuelle (ACQ-01) | U5: COM-02.01, ACQ-01.12 | V5: XC27, DC04
A6: COM-03.01 | B6: COM-03 | C6: =IFERROR(INDEX(Thèmes!$D$2:$D$190,MATCH(B6,Thèmes!$A$2:$A$190,0)),"") | D6: C01 · Votre positionnement et votre offre | E6: Résultat concret que vous promettez à vos clients | F6: Texte court | G6: Demandée | H6: Essentiel | I6: — | J6: — | K6: ● | L6: ● | M6: ● | N6: ● | O6: ● | P6: ● | Q6: ● | R6: ● | S6: Problème | T6: — | U6: — | V6: Notée directement (couleur du thème)
A7: COM-04.01 | B7: COM-04 | C7: =IFERROR(INDEX(Thèmes!$D$2:$D$190,MATCH(B7,Thèmes!$A$2:$A$190,0)),"") | D7: C01 · Votre positionnement et votre offre | E7: Pour votre offre principale : preuve que le résultat est atteignable, délai pour l'obtenir, effort demandé au client | F7: 3 champs courts | G7: Demandée | H7: Approfondi | I7: — | J7: — | K7: ● | L7: ● | M7: ● | N7: ● | O7: ● | P7: ● | Q7: ● | R7: ● | S7: Levier | T7: — | U7: — | V7: Lue par l'IA pour adapter le conseil
A8: COM-05.01 | B8: COM-05 | C8: =IFERROR(INDEX(Thèmes!$D$2:$D$190,MATCH(B8,Thèmes!$A$2:$A$190,0)),"") | D8: C01 · Votre positionnement et votre offre | E8: Garantie proposée — déclencheur D56 | F8: Choix + texte | G8: Demandée | H8: Essentiel | I8: — | J8: — | K8: ● | L8: ● | M8: ● | N8: ● | O8: ● | P8: ● | Q8: ● | R8: ● | S8: Levier | T8: — | U8: — | V8: Notée directement (couleur du thème) | W8: Libellé (« Donnée »)
A9: COM-05.02 | B9: COM-05 | C9: =IFERROR(INDEX(Thèmes!$D$2:$D$190,MATCH(B9,Thèmes!$A$2:$A$190,0)),"") | D9: — | E9: Ce que garantit exactement le dirigeant | F9: Texte court | G9: Demandée | H9: Essentiel | I9: D56 · si garantie proposée | J9: — | K9: ● | L9: ● | M9: ● | N9: ● | O9: ● | P9: ● | Q9: ● | R9: ● | S9: — | T9: — | U9: — | V9: — | W9: Nouveau
A10: COM-06.01 | B10: COM-06 | C10: =IFERROR(INDEX(Thèmes!$D$2:$D$190,MATCH(B10,Thèmes!$A$2:$A$190,0)),"") | D10: — | E10: Ton adapté à la cible : registre, vocabulaire, niveau technique | F10: Oui / partiel / non | G10: Calculée | H10: — | I10: — | J10: — | K10: ● | L10: ● | M10: ● | N10: ● | O10: ● | P10: ● | Q10: ● | R10: ● | S10: Problème | T10: Évalué par l'IA sur les publications importées. La forme seulement : le public visé est noté en COM-54 | U10: COM-39.02, COM-02.01 | V10: Affichée dans le rapport
A11: COM-07.01 | B11: COM-07 | C11: =IFERROR(INDEX(Thèmes!$D$2:$D$190,MATCH(B11,Thèmes!$A$2:$A$190,0)),"") | D11: C01 · Votre positionnement et votre offre | E11: Logo, couleurs et ton identiques sur le site, les réseaux, les devis et la vitrine : oui, en partie, non | F11: Choix | G11: Demandée | H11: Essentiel | I11: — | J11: — | K11: ● | L11: ● | M11: ● | N11: ● | O11: ● | P11: ● | Q11: ● | R11: ● | S11: Problème | T11: — | U11: — | V11: Notée directement (couleur du thème)
A12: COM-08.01 | B12: COM-08 | C12: =IFERROR(INDEX(Thèmes!$D$2:$D$190,MATCH(B12,Thèmes!$A$2:$A$190,0)),"") | D12: C01 · Votre positionnement et votre offre | E12: Certifications, labels ou garanties professionnelles affichés | F12: Cases à cocher | G12: Demandée | H12: Approfondi | I12: — | J12: — | K12: ● | L12: ● | M12: ● | N12: ● | O12: ● | P12: ● | Q12: ● | R12: ● | S12: Cible | T12: — | U12: — | V12: COM-08.02
A13: COM-08.02 | B13: COM-08 | C13: =IFERROR(INDEX(Thèmes!$D$2:$D$190,MATCH(B13,Thèmes!$A$2:$A$190,0)),"") | D13: — | E13: Éléments de réassurance visibles | F13: Liste | G13: Calculée | H13: — | I13: — | J13: — | K13: ● | L13: ● | M13: ● | N13: ● | O13: ● | P13: ● | Q13: ● | R13: ● | S13: Levier | T13: Avis, ancienneté (inscription), certifications, preuves publiées | U13: ACQ-06.01, COM-08.01, COM-09.01 | V13: Affichée dans le rapport
A14: COM-09.01 | B14: COM-09 | C14: =IFERROR(INDEX(Thèmes!$D$2:$D$190,MATCH(B14,Thèmes!$A$2:$A$190,0)),"") | D14: C02 · Vos preuves (tableau par type) | E14: Vos preuves par type — témoignage écrit, témoignage vidéo, étude de cas avec résultat chiffré, avant / après, photos ou vidéos de réalisations, avis détaillé : nombre disponible, nombre publié sur le site, nombre publié sur les réseaux | F14: Tableau 6 × 3 | G14: Demandée | H14: Essentiel | I14: — | J14: — | K14: ● | L14: ● | M14: ● | N14: ● | O14: ● | P14: ● | Q14: ● | R14: ● | S14: Opportunité | T14: — | U14: — | V14: COM-08.02, COM-09.04, COM-09.05, COM-09.06, COM-34.03, XC15
A15: COM-09.02 | B15: COM-09 | C15: =IFERROR(INDEX(Thèmes!$D$2:$D$190,MATCH(B15,Thèmes!$A$2:$A$190,0)),"") | D15: C02 · Vos preuves (tableau par type) | E15: Date de votre preuve la plus récente | F15: Mois et année | G15: Demandée | H15: Essentiel | I15: — | J15: — | K15: ● | L15: ● | M15: ● | N15: ● | O15: ● | P15: ● | Q15: ● | R15: ● | S15: Problème | T15: — | U15: — | V15: Notée directement (couleur du thème)
A16: COM-09.03 | B16: COM-09 | C16: =IFERROR(INDEX(Thèmes!$D$2:$D$190,MATCH(B16,Thèmes!$A$2:$A$190,0)),"") | D16: C02 · Vos preuves (tableau par type) | E16: Catégories de clients représentées par au moins une preuve (les offres sont en COM-09.08) | F16: Cases (reprend ACQ-01 et ACQ-13) | G16: Demandée | H16: Approfondi | I16: — | J16: — | K16: ● | L16: ● | M16: ● | N16: ● | O16: ● | P16: ● | Q16: ● | R16: ● | S16: Levier | T16: — | U16: — | V16: COM-09.07 | W16: Libellé (« Donnée »)
A17: COM-09.04 | B17: COM-09 | C17: =IFERROR(INDEX(Thèmes!$D$2:$D$190,MATCH(B17,Thèmes!$A$2:$A$190,0)),"") | D17: — | E17: Preuves exploitables au total, dont avec résultat chiffré | F17: Nombre et % | G17: Calculée | H17: — | I17: — | J17: — | K17: ● | L17: ● | M17: ● | N17: ● | O17: ● | P17: ● | Q17: ● | R17: ● | S17: Mesure | T17: Somme du tableau ; part des études de cas chiffrées | U17: COM-09.01 | V17: XC13
A18: COM-09.05 | B18: COM-09 | C18: =IFERROR(INDEX(Thèmes!$D$2:$D$190,MATCH(B18,Thèmes!$A$2:$A$190,0)),"") | D18: — | E18: Part des preuves réellement publiées | F18: % | G18: Calculée | H18: — | I18: — | J18: — | K18: ● | L18: ● | M18: ● | N18: ● | O18: ● | P18: ● | Q18: ● | R18: ● | S18: Opportunité | T18: Preuves publiées (site ou réseaux) ÷ preuves disponibles | U18: COM-09.01 | V18: XC13, XC14, DC09
